Workbook
Name COREISADDONS: [1]LIST!#REF!
Name COREISADDONS: [1]LIST!#REF!
Name COREISADDONS: [1]LIST!#REF!
Name Currency: '[2]Named Ranges'!$A$2:$A$18
Name Currency: '[2]Named Ranges'!$A$2:$A$18
Name Currency: '[2]Named Ranges'!$A$2:$A$18
Name Currency: '[2]Named Ranges'!$A$2:$A$18
Name Currency: '[3]Named Ranges'!$A$2:$A$18
Name NewParts: 'New Parts'!$D$3:$D$26
Name Parts: '[4]Upgrade Parts Future_K_v4.0'!$H$3:$H$498
Name Parts: '[5]Upgrade Parts Future_K_v4.0'!$H$3:$H$498
Name Parts: '[5]Upgrade Parts Future_K_v4.0'!$H$3:$H$498
Name Parts: '[5]Upgrade Parts Future_K_v4.0'!$H$3:$H$498
Name Parts: '[6]Upgrade Parts Future_K_v4.1'!$H$3:$H$498
Name Parts: 'Upgrade Parts Future_K_v5.4'!$H$3:$H$498
Name Parts: 'Upgrade Parts Future_K_v6.0'!$H$3:$H$498
Name Parts: 'Upgrade Parts Future_K_v6.4'!$H$3:$H$498
Name Parts: 'Upgrade Parts Future_K_v4.1'!$H$3:$H$498
Name Route_to_Market: '[2]Named Ranges'!$E$2:$E$3
Name Route_to_Market: '[2]Named Ranges'!$E$2:$E$3
Name Route_to_Market: '[2]Named Ranges'!$E$2:$E$3
Name Route_to_Market: '[2]Named Ranges'!$E$2:$E$3
Name Route_to_Market: '[3]Named Ranges'!$E$2:$E$3
Name rsvp: '[2]Named Ranges'!$C$2:$C$11
Name rsvp: '[2]Named Ranges'!$C$2:$C$11
Name rsvp: '[2]Named Ranges'!$C$2:$C$11
Name rsvp: '[2]Named Ranges'!$C$2:$C$11
Name rsvp: '[3]Named Ranges'!$C$2:$C$11
Name usertype: '[6]New Parts'!$D$37:$D$44
Name usertype: 'New Parts'!$D$37:$D$47
Name usertypepoints: '[6]New Parts'!$D$37:$E$44
Name usertypepoints: 'New Parts'!$D$37:$E$47

Sheet Instructions
C3: MAS New Deal/Upgrade/Trade-up Request Forms
D6: Instructions All fields in the forms are required to be filled out for consideration of an upgrade or trade-up. Go to the Details tab to enter the bid details. You will also need to fill in information regarding the parts to be trading up and/or upgrading to. Follow the below steps to complete the process of raising the request: i. Complete the DETAILS tab: Please ensure all required fields are filled out. ii. Complete the Calculator Tab with the current entitlement being requested to upgrade.
A28: NOTE: Pricing and Packaging Guides located on Seismic under Maximo Application Suite/Pricing Plan - https://ibm.seismic.com/Link/Content/DCV7TR4HYCgUaD2mrkzrxzAQ | U28: Last updated 10/28/2022

Sheet Details - New Deal
A2: New Deal Request Form *Required Fields
B3: Please complete all questions
A5: Requester Info
A7: *Requester Name
A8: *Requester Email
A10: Customer Info
A12: *Customer Name
A13: *Site Number
A14: *IBM Customer Number
A15: Is this a GTS/GBS contract? | C15: *These are Not eligible - Answer should be NO
A16: Is this an ESA contract? | C16: * If yes, ESA exception approval required
A17: Is this a new customer / non upgradable
A18: Sales Connect Opportunity Number
A19: Is the customer on a Hotlist or the IWL? YES / NO / Don't Know (from SQO)
A20: Is the customer under an audit? YES / NO / Don't Know (from SQO)
A21: Currency
A23: Further Details of the Deal
A25: Expected New Contract Duration? (minimum 12 months)
A26: Projected Close Date | B26: DD/MM/YYYY
A27: Projected Deal Size
A28: Will the deal be financed? with IGF? Y/N
A29: Will special terms be required, if yes, explain?
A31: MAS REQUEST

Sheet New Deal Calculator
B1: MAS New Deal calculator
B3: Customer Name | C3: License Type | D3: Quantity | E3: Line Item Description | F3: AppPoints Required | G3: Total Required AppPoints
F4: =IF(ISBLANK(C4),"",VLOOKUP($C4,'New Parts'!D37:E54,2,FALSE)) | G4: =IFERROR(F4*D4,"")
F5: =IF(ISBLANK(C5),"",VLOOKUP($C5,'New Parts'!D37:E54,2,FALSE)) | G5: =IFERROR(F5*D5,"")
F6: =IF(ISBLANK(C6),"",VLOOKUP($C6,'New Parts'!D37:E54,2,FALSE)) | G6: =IFERROR(F6*D6,"")
F7: =IF(ISBLANK(C7),"",VLOOKUP($C7,'New Parts'!D37:E54,2,FALSE)) | G7: =IFERROR(F7*D7,"")
F8: =IF(ISBLANK(C8),"",VLOOKUP($C8,'New Parts'!D37:E54,2,FALSE)) | G8: =IFERROR(F8*D8,"")
F9: =IF(ISBLANK(C9),"",VLOOKUP($C9,'New Parts'!D37:E54,2,FALSE)) | G9: =IFERROR(F9*D9,"")
F10: =IF(ISBLANK(C10),"",VLOOKUP($C10,'New Parts'!D37:E54,2,FALSE)) | G10: =IFERROR(F10*D10,"")
F11: =IF(ISBLANK(C11),"",VLOOKUP($C11,'New Parts'!D37:E54,2,FALSE)) | G11: =IFERROR(F11*D11,"")
F12: =IF(ISBLANK(C12),"",VLOOKUP($C12,'New Parts'!D37:E54,2,FALSE)) | G12: =IFERROR(F12*D12,"")
F13: =IF(ISBLANK(C13),"",VLOOKUP($C13,'New Parts'!D37:E54,2,FALSE)) | G13: =IFERROR(F13*D13,"")
F14: =IF(ISBLANK(C14),"",VLOOKUP($C14,'New Parts'!D37:E54,2,FALSE)) | G14: =IFERROR(F14*D14,"")
F15: =IF(ISBLANK(C15),"",VLOOKUP($C15,'New Parts'!D37:E54,2,FALSE)) | G15: =IFERROR(F15*D15,"")
F16: =IF(ISBLANK(C16),"",VLOOKUP($C16,'New Parts'!D37:E54,2,FALSE)) | G16: =IFERROR(F16*D16,"")
F17: =IF(ISBLANK(C17),"",VLOOKUP($C17,'New Parts'!D37:E54,2,FALSE)) | G17: =IFERROR(F17*D17,"")
F18: =IF(ISBLANK(C18),"",VLOOKUP($C18,'New Parts'!D37:E54,2,FALSE)) | G18: =IFERROR(F18*D18,"")
F19: =IF(ISBLANK(C19),"",VLOOKUP($C19,'New Parts'!D37:E54,2,FALSE)) | G19: =IFERROR(F19*D19,"")
F20: =IF(ISBLANK(C20),"",VLOOKUP($C20,'New Parts'!D37:E54,2,FALSE)) | G20: =IFERROR(F20*D20,"")
F21: =IF(ISBLANK(C21),"",VLOOKUP($C21,'New Parts'!D37:E54,2,FALSE)) | G21: =IFERROR(F21*D21,"")
F22: =IF(ISBLANK(C22),"",VLOOKUP($C22,'New Parts'!D37:E54,2,FALSE)) | G22: =IFERROR(F22*D22,"")
B23: Total | D23: =SUM(D4:D22) -> 0 | G23: =SUM(G4:G22) -> 0
B24: NOTE:
B25: At least 1 Admin Premium User must be added to a New Deal bid.

Sheet  New Deal STL Pricing
A1: IBM CONFIDENTIAL
A2: Note : Please fill in the green highlighted cells only
A3: SQO billing needs to be "Upfront" for the term of the deal. IGF financing can be leveraged for yearly billing.
A4: Contact MAS project office for pricing guidance /non standard pricing
A6: MAS STL Pricing (USD) | H6: Import Managed Services pricing from Managed services Calculator
A7: MAS Points needed | B7: Price /Point (USD) | C7: MAS Yearly List Price | D7: Discount | E7: Net Price/Year | H7: MAS STL + Managed Services
B8: 82 | C8: =A8*B8*12 -> 0 | D8: 0 | E8: =C8*(1-D8) -> 0
D10: Year 2 | E10: =E8 -> 0
D11: Year 3 | E11: =E10 -> 0
D12: Year 4 | E12: =E11 -> 0
D13: Year 5 | E13: =E12 -> 0 | F13: MAS STL Bookable
D14: TOTAL 3yr | E14: =E8+E10+E11 -> 0 | F14: =E14*0.57 -> 0 | H14: =SUM(H8:H11) -> 0
D15: TOTAL 5yr | E15: =E14+E12+E13 -> 0 | F15: =E15*0.44 -> 0 | H15: =H14+H12+H13 -> 0

Sheet Details - Upgrade Parts
B2: Upgrade Request Form *Required Fields
B3: Please complete all questions
B5: Requester Info
B7: *Requester Name
B8: *Requester Email
B10: S&S Renewal Rep Info
B12: *S&S Renewal Rep Name
B13: *S&S Renewal Rep Email | E13: http://dimond.naasc.ibm.com:9080/DimondWebApp
B15: Customer Info
B17: *Customer Name
B18: *Site Number
B19: *IBM Customer Number | E19: Was the existing entitlement purchased direct through IBM or partner (channel)?
B20: Is this a GTS/GBS contract? *These are Not eligible - Answer should be NO | E20: Will the upgrade be purchased direct through IBM or partner (channel)?
B21: Is this an ESA contract? * If yes, ESA exception approval required | E21: Was the Channel Inentive code BP-Led for prior purchases
B22: Sales Connect Opportunity Number | E22: *Note: Flips from direct to channel not allowed if Incentive Code was Direct or Co-Led. See Play 7.14 for instructions if the Channel Incentive code was BP-Led. Exception approval needed by WW S&S; Add'l Uplifts will apply
B23: When is the opportunity expected to close? | C23: DD/MM/YYYY
B24: Currency | E24: Is the customer on a Hotlist or the IWL? YES / NO / Don't Know (from SQO)
E25: Is the customer under an audit? YES / NO / Don't Know (from SQO)
B26: Further Details of the Deal | E26: Is there existing S&S on these products? If yes, fill out the S&S section below
B28: Have you analyzed your customer's entire entitlement for all eligible parts for upgrade?
B29: When is the S&S renewal date? | C29: DD/MM/YYYY
B30: *Note: Upgrade should happen at the client's renewal date. There is no credit on exiting S&S for an early upgrade | F30: Contract type holding entitlements for upgrade
B31: Are you requesting ALL active licenses for upgrade? | F31: Has the dealmaker been engaged?
B32: Please provide justification for partial upgrade (only required if "No" to above) | F32: Dealmaker Name
B33: Is there a request to upgrade expired SS? | F33: Original contract start date | G33: DD/MM/YYYY
B34: Have you engaged your S&S Renewal Rep for a reach back quote to bring the entitlements current on S&S? | F34: Contract end date | G34: DD/MM/YYYY
B35: (only required if "Yes" to above) | F35: Year to year S&S growth rate on existing agreement (ex: Flat, 3%, 5% etc)
F36: If the contract is NOT expiring, is this part of an amendment or termination of the contract? Please select one option.
F37: Have all parts for upgrade been declared to IBM with reports / Proof of Entitlement?
F38: When is declaration expected? (only required if "No" to above)
F39: *Note - Mid-term upgrade is NOT allowed without an amendment to an ELA or termination of IULA
B41: Expected New Contract Duration? (minimum 12 months)
B42: Projected Close Date | C42: DD/MM/YYYY
B43: Projected Deal Size | D43: ww
B44: Will the deal be financed? with RBD? Y/N
B45: Will special terms be required, if yes, explain?
B46: Is customer a service provider? If yes, do you need SP Contract Variant? (Must include DM), migration period for S&S?
B50: MAS REQUEST

Sheet Upgrade Parts Calculator
B2: Maximo upgradable parts calculator for MAS
B4: Customer name | C4: Part # | D4: Part Description | E4: Current Customer Entitlement | F4: Upgrade AppPoints / Health RVU divide by 10 | G4: AppPoints for Upgrade | H4: Total Upgradable AppPoints
B5: xxxx | D5: =IF(ISBLANK(C5),"",(VLOOKUP($C5,'Upgrade Parts Future_K_v6.4'!$H$3:$M$528,2,FALSE))) | F5: =IF(ISBLANK(E5), "", IF(AND(VLOOKUP(C5,'Upgrade Parts Future_K_v6.0'!$H$3:$K$528,4,FALSE)="Resource Value Unit", E5 < 10), 1, IF(VLOOKUP(C5,'Upgrade Parts Future_K_v6.0'!$H$3:$K$528,4,FALSE)="Resource Value Unit", E5/10, E5 ) ) ) | G5: =IF(ISBLANK(E5),"",(VLOOKUP($C5,'Upgrade Parts Future_K_v6.4'!$H$3:$M$528,5,FALSE))) | H5: =IF(ISBLANK(E5),"",ROUNDUP((F5*G5),0))
D6: =IF(ISBLANK(C6),"",(VLOOKUP($C6,'Upgrade Parts Future_K_v6.4'!$H$3:$M$528,2,FALSE))) | F6: =IF(ISBLANK(E6), "", IF(AND(VLOOKUP(C6,'Upgrade Parts Future_K_v6.0'!$H$3:$K$528,4,FALSE)="Resource Value Unit", E6 < 10), 1, IF(VLOOKUP(C6,'Upgrade Parts Future_K_v6.0'!$H$3:$K$528,4,FALSE)="Resource Value Unit", E6/10, E6 ) ) ) | G6: =IF(ISBLANK(E6),"",(VLOOKUP($C6,'Upgrade Parts Future_K_v6.4'!$H$3:$M$528,5,FALSE))) | H6: =IF(ISBLANK(E6),"",ROUNDUP((F6*G6),0))
D7: =IF(ISBLANK(C7),"",(VLOOKUP($C7,'Upgrade Parts Future_K_v6.4'!$H$3:$M$528,2,FALSE))) | F7: =IF(ISBLANK(E7), "", IF(AND(VLOOKUP(C7,'Upgrade Parts Future_K_v6.0'!$H$3:$K$528,4,FALSE)="Resource Value Unit", E7 < 10), 1, IF(VLOOKUP(C7,'Upgrade Parts Future_K_v6.0'!$H$3:$K$528,4,FALSE)="Resource Value Unit", E7/10, E7 ) ) ) | G7: =IF(ISBLANK(E7),"",(VLOOKUP($C7,'Upgrade Parts Future_K_v6.4'!$H$3:$M$528,5,FALSE))) | H7: =IF(ISBLANK(E7),"",ROUNDUP((F7*G7),0))
D8: =IF(ISBLANK(C8),"",(VLOOKUP($C8,'Upgrade Parts Future_K_v6.4'!$H$3:$M$528,2,FALSE))) | F8: =IF(ISBLANK(E8), "", IF(AND(VLOOKUP(C8,'Upgrade Parts Future_K_v6.0'!$H$3:$K$528,4,FALSE)="Resource Value Unit", E8 < 10), 1, IF(VLOOKUP(C8,'Upgrade Parts Future_K_v6.0'!$H$3:$K$528,4,FALSE)="Resource Value Unit", E8/10, E8 ) ) ) | G8: =IF(ISBLANK(E8),"",(VLOOKUP($C8,'Upgrade Parts Future_K_v6.4'!$H$3:$M$528,5,FALSE))) | H8: =IF(ISBLANK(E8),"",ROUNDUP((F8*G8),0))
D9: =IF(ISBLANK(C9),"",(VLOOKUP($C9,'Upgrade Parts Future_K_v6.4'!$H$3:$M$528,2,FALSE))) | F9: =IF(ISBLANK(E9), "", IF(AND(VLOOKUP(C9,'Upgrade Parts Future_K_v6.0'!$H$3:$K$528,4,FALSE)="Resource Value Unit", E9 < 10), 1, IF(VLOOKUP(C9,'Upgrade Parts Future_K_v6.0'!$H$3:$K$528,4,FALSE)="Resource Value Unit", E9/10, E9 ) ) ) | G9: =IF(ISBLANK(E9),"",(VLOOKUP($C9,'Upgrade Parts Future_K_v6.4'!$H$3:$M$528,5,FALSE))) | H9: =IF(ISBLANK(E9),"",ROUNDUP((F9*G9),0))
D10: =IF(ISBLANK(C10),"",(VLOOKUP($C10,'Upgrade Parts Future_K_v6.4'!$H$3:$M$528,2,FALSE))) | F10: =IF(ISBLANK(E10), "", IF(AND(VLOOKUP(C10,'Upgrade Parts Future_K_v6.0'!$H$3:$K$528,4,FALSE)="Resource Value Unit", E10 < 10), 1, IF(VLOOKUP(C10,'Upgrade Parts Future_K_v6.0'!$H$3:$K$528,4,FALSE)="Resource Value Unit", E10/10, E10 ) ) ) | G10: =IF(ISBLANK(E10),"",(VLOOKUP($C10,'Upgrade Parts Future_K_v6.4'!$H$3:$M$528,5,FALSE))) | H10: =IF(ISBLANK(E10),"",ROUNDUP((F10*G10),0))
D11: =IF(ISBLANK(C11),"",(VLOOKUP($C11,'Upgrade Parts Future_K_v6.4'!$H$3:$M$528,2,FALSE))) | F11: =IF(ISBLANK(E11), "", IF(AND(VLOOKUP(C11,'Upgrade Parts Future_K_v6.0'!$H$3:$K$528,4,FALSE)="Resource Value Unit", E11 < 10), 1, IF(VLOOKUP(C11,'Upgrade Parts Future_K_v6.0'!$H$3:$K$528,4,FALSE)="Resource Value Unit", E11/10, E11 ) ) ) | G11: =IF(ISBLANK(E11),"",(VLOOKUP($C11,'Upgrade Parts Future_K_v6.4'!$H$3:$M$528,5,FALSE))) | H11: =IF(ISBLANK(E11),"",ROUNDUP((F11*G11),0))
D12: =IF(ISBLANK(C12),"",(VLOOKUP($C12,'Upgrade Parts Future_K_v6.4'!$H$3:$M$528,2,FALSE))) | F12: =IF(ISBLANK(E12), "", IF(AND(VLOOKUP(C12,'Upgrade Parts Future_K_v6.0'!$H$3:$K$528,4,FALSE)="Resource Value Unit", E12 < 10), 1, IF(VLOOKUP(C12,'Upgrade Parts Future_K_v6.0'!$H$3:$K$528,4,FALSE)="Resource Value Unit", E12/10, E12 ) ) ) | G12: =IF(ISBLANK(E12),"",(VLOOKUP($C12,'Upgrade Parts Future_K_v6.4'!$H$3:$M$528,5,FALSE))) | H12: =IF(ISBLANK(E12),"",ROUNDUP((F12*G12),0))
D13: =IF(ISBLANK(C13),"",(VLOOKUP($C13,'Upgrade Parts Future_K_v6.4'!$H$3:$M$528,2,FALSE))) | F13: =IF(ISBLANK(E13), "", IF(AND(VLOOKUP(C13,'Upgrade Parts Future_K_v6.0'!$H$3:$K$528,4,FALSE)="Resource Value Unit", E13 < 10), 1, IF(VLOOKUP(C13,'Upgrade Parts Future_K_v6.0'!$H$3:$K$528,4,FALSE)="Resource Value Unit", E13/10, E13 ) ) ) | G13: =IF(ISBLANK(E13),"",(VLOOKUP($C13,'Upgrade Parts Future_K_v6.4'!$H$3:$M$528,5,FALSE))) | H13: =IF(ISBLANK(E13),"",ROUNDUP((F13*G13),0))
D14: =IF(ISBLANK(C14),"",(VLOOKUP($C14,'Upgrade Parts Future_K_v6.4'!$H$3:$M$528,2,FALSE))) | F14: =IF(ISBLANK(E14), "", IF(AND(VLOOKUP(C14,'Upgrade Parts Future_K_v6.0'!$H$3:$K$528,4,FALSE)="Resource Value Unit", E14 < 10), 1, IF(VLOOKUP(C14,'Upgrade Parts Future_K_v6.0'!$H$3:$K$528,4,FALSE)="Resource Value Unit", E14/10, E14 ) ) ) | G14: =IF(ISBLANK(E14),"",(VLOOKUP($C14,'Upgrade Parts Future_K_v6.4'!$H$3:$M$528,5,FALSE))) | H14: =IF(ISBLANK(E14),"",ROUNDUP((F14*G14),0))
D15: =IF(ISBLANK(C15),"",(VLOOKUP($C15,'Upgrade Parts Future_K_v6.4'!$H$3:$M$528,2,FALSE))) | F15: =IF(ISBLANK(E15), "", IF(AND(VLOOKUP(C15,'Upgrade Parts Future_K_v6.0'!$H$3:$K$528,4,FALSE)="Resource Value Unit", E15 < 10), 1, IF(VLOOKUP(C15,'Upgrade Parts Future_K_v6.0'!$H$3:$K$528,4,FALSE)="Resource Value Unit", E15/10, E15 ) ) ) | G15: =IF(ISBLANK(E15),"",(VLOOKUP($C15,'Upgrade Parts Future_K_v6.4'!$H$3:$M$528,5,FALSE))) | H15: =IF(ISBLANK(E15),"",ROUNDUP((F15*G15),0))
D16: =IF(ISBLANK(C16),"",(VLOOKUP($C16,'Upgrade Parts Future_K_v6.4'!$H$3:$M$528,2,FALSE))) | F16: =IF(ISBLANK(E16), "", IF(AND(VLOOKUP(C16,'Upgrade Parts Future_K_v6.0'!$H$3:$K$528,4,FALSE)="Resource Value Unit", E16 < 10), 1, IF(VLOOKUP(C16,'Upgrade Parts Future_K_v6.0'!$H$3:$K$528,4,FALSE)="Resource Value Unit", E16/10, E16 ) ) ) | G16: =IF(ISBLANK(E16),"",(VLOOKUP($C16,'Upgrade Parts Future_K_v6.4'!$H$3:$M$528,5,FALSE))) | H16: =IF(ISBLANK(E16),"",ROUNDUP((F16*G16),0))
D17: =IF(ISBLANK(C17),"",(VLOOKUP($C17,'Upgrade Parts Future_K_v6.4'!$H$3:$M$528,2,FALSE))) | F17: =IF(ISBLANK(E17), "", IF(AND(VLOOKUP(C17,'Upgrade Parts Future_K_v6.0'!$H$3:$K$528,4,FALSE)="Resource Value Unit", E17 < 10), 1, IF(VLOOKUP(C17,'Upgrade Parts Future_K_v6.0'!$H$3:$K$528,4,FALSE)="Resource Value Unit", E17/10, E17 ) ) ) | G17: =IF(ISBLANK(E17),"",(VLOOKUP($C17,'Upgrade Parts Future_K_v6.4'!$H$3:$M$528,5,FALSE))) | H17: =IF(ISBLANK(E17),"",ROUNDUP((F17*G17),0))
... D35: =IF(ISBLANK(C35),"",(VLOOKUP($C35,'Upgrade Parts Future_K_v6.4'!$H$3:$M$528,2,FALSE))) | F35: =IF(ISBLANK(E35), "", IF(AND(VLOOKUP(C35,'Upgrade Parts Future_K_v6.0'!$H$3:$K$528,4,FALSE)="Resource Value Unit", E35 < 10), 1, IF(VLOOKUP(C35,'Upgrade Parts Future_K_v6.0'!$H$3:$K$528,4,FALSE)="Resource Value Unit", E35/10, E35 ) ) ) | G35: =IF(ISBLANK(E35),"",(VLOOKUP($C35,'Upgrade Parts Future_K_v6.4'!$H$3:$M$528,5,FALSE))) | H35: =IF(ISBLANK(E35),"",ROUNDUP((F35*G35),0))
B36: Total | E36: =SUM(E5:E35) -> 0 | H36: =MROUND(SUM(H5:H35),5) -> 0

Sheet Subscription Upgrade Pricing
A1: IBM Internal and Business Partner Use Only | G1: Input Cells
A2: Note : Please fill in the green highlighted cells only | G2: Formula Cells
A3: MAS upgrade pricing needs to be uplifted a minimum of 35% (Could be higher but not lower than 35%)
A4: SQO billing needs to be "Upfront" for the term of the deal if >$2M. IGF financing can be leveraged for yearly payments
A5: Reminder : Attach the S&S checklist (See Play 7.14); Make sure you say Yes in the SQO bid that a Play is being used (see Play 7.14)
A6: Contact MAS project office for pricing guidance /non standard pricing; Consult the 7.14 Play for Uplifts on RTM shifts and guidance
A8: Is this an FCT client (y/n) | B8: NO | C8: (If NO, leave cell "A11" blank )
A10: UPFRONT PAYMENTS at 3% - MAS STL Pricing (USD) / Update to local currency if ouside US and note currency being used
A11: LPP on FCT 2022 (Provided by the FCT S&S rep) | B11: LPP on PA uplifted 0% from FCT LPP (Provided by S&S rep) | C11: MAS Uplift of 35%* | D11: MAS Points needed (qty for the Upgrade part number D28B5LL) | E11: Uprade Price /Point (Local Currency) | F11: Upgrade Yearly List Price | G11: Discount | H11: Net Price/Year | K11: Import Managed Services pricing from Managed services Calculator
C12: =B12*1.35 -> 0 | E12: 36 | F12: =D12*E12*12 -> 0 | G12: =1-(H12/F12) -> #DIV/0! | H12: =C12 -> 0 | K12: MAS STL + Managed Services
A14: *Adjust this rate for Play approved RTM shifts if approved. | F14: =+F12 -> 0 | G14: Year 2 | H14: =H12 *1.03 -> 0
F15: =+F14 -> 0 | G15: Year 3 | H15: =H14 *1.03 -> 0
F16: =+F15 -> 0 | G16: Year 4 | H16: =H15 *1.03 -> 0
F17: =+F16 -> 0 | G17: Year 5 | H17: =H16 *1.03 -> 0 | I17: MAS STL Bookable
F18: =F12+F14+F15 -> 0 | G18: TOTAL 3yr | H18: =H12+H14+H15 -> 0 | I18: =H18*0.15 -> 0 | K18: =SUM(K13:K15) -> 0
F19: =F18+F16+F17 -> 0 | G19: TOTAL 5yr | H19: =H18+H16+H17 -> 0 | I19: =H19*0.11 -> 0 | K19: =K18+K16+K17 -> 0
A29: ANNUAL PAYMENTS at 5% - MAS STL Pricing (USD) / Update to local currency if ouside US and note currency being used
A30: LPP on FCT 2022 (Provided by the FCT S&S rep) | B30: LPP on PA uplifted 0% from FCT LPP (Provided by S&S rep) | C30: MAS Uplift of 35%* | D30: MAS Points needed (qty for the Upgrade part number D28B5LL) | E30: Uprade Price /Point (Local Currency) | F30: Upgrade Yearly List Price | G30: Discount | H30: Net Price/Year | K30: Import Managed Services pricing from Managed services Calculator
C31: =B31*1.35 -> 0 | E31: 36 | F31: =D31*E31*12 -> 0 | G31: =1-(H31/F31) -> #DIV/0! | H31: =C31 -> 0 | K31: MAS STL + Managed Services
A33: *Adjust this rate for Play approved RTM shifts if approved. | F33: =+F31 -> 0 | G33: Year 2 | H33: =H31 * 1.05 -> 0
F34: =+F33 -> 0 | G34: Year 3 | H34: =H33 * 1.05 -> 0
F35: =+F34 -> 0 | G35: Year 4 | H35: =H34 * 1.05 -> 0
F36: =+F35 -> 0 | G36: Year 5 | H36: =H35 * 1.05 -> 0 | I36: MAS STL Bookable
F37: =F31+F33+F34 -> 0 | G37: TOTAL 3yr | H37: =H31+H33+H34 -> 0 | I37: =H37*0.15 -> 0 | K37: =SUM(K32:K34) -> 0
F38: =F37+F35+F36 -> 0 | G38: TOTAL 5yr | H38: =H37+H35+H36 -> 0 | I38: =H38*0.11 -> 0 | K38: =K37+K35+K36 -> 0
A40: RTM Shift Scenario outside of the Play approved scenarios or when Geo rates are not available in the Play:
A42: MAS STL Pricing (USD) / Update to local currency if ouside US and note currency being used
A43: LPP on FCT 2020 (Provided by the FCT S&S rep) | B43: LPP on PA uplifted 0% from FCT LPP (Provided by S&S rep) | C43: MAS Uplift of 35%* | D43: MAS Points needed (qty for the Upgrade part number D28B5LL) | E43: Uprade Price /Point (Local Currency) | F43: Upgrade Yearly List Price | G43: Discount | H43: Net Price/Year | I43: Add'l Incentive Uplifts if required (modify the % based on Lamar Murphy input) | J43: Min Price required w RTM Shift | K43: Discount
B44: 100 | C44: =B44*1.35 -> 135 | D44: 100 | E44: 36 | F44: =D44*E44*12 -> 43200 | G44: =1-(H44/F44) -> 0.996875 | H44: =C44 -> 135 | I44: 0.12 | J44: =H44*(1+I44) -> 151.2 | K44: =1-J44/F44 -> 0.9965
F46: =+F44 -> 43200 | G46: Year 2 | H46: =H44 -> 135
F47: =+F46 -> 43200 | G47: Year 3 | H47: =H46 -> 135
A48: * Adjust this rate to what John Dewey/Carlos Belak tell you; Also add the add'l incentive from Lamar Murphy. | F48: =+F47 -> 43200 | G48: Year 4 | H48: =H47 -> 135
F49: =+F48 -> 43200 | G49: Year 5 | H49: =H48 -> 135 | I49: MAS STL Bookable
F50: =F44+F46+F47 -> 129600 | G50: TOTAL 3yr | H50: =H44+H46+H47 -> 405 | I50: =H50*0.15 -> 60.75
F51: =F50+F48+F49 -> 216000 | G51: TOTAL 5yr | H51: =H50+H48+H49 -> 675 | I51: =H51*0.11 -> 74.25

Sheet Details - Trade-up Parts 
B2: Trade-up Request Form *Required Fields
B3: Please complete all questions
B5: Requester Info
B7: *Requester Name
B8: *Requester Email
B10: S&S Renewal Rep Info
B12: *S&S Renewal Rep Name
B13: *S&S Renewal Rep Email | E13: http://dimond.naasc.ibm.com:9080/DimondWebApp
B15: Customer Info
B17: *Customer Name
B18: *Site Number
B19: *IBM Customer Number | E19: Was the existing entitlement purchased direct through IBM or partner (channel)?
B20: Is this a GTS/GBS contract? *These are Not eligible - Answer should be NO | E20: Will the upgrade be purchased direct through IBM or partner (channel)?
B21: Is this an ESA contract? | E21: *Note: Flips from direct to channel not allowed. Exception approval needed by WW S&S
B22: Sales Connect Opportunity Number
B23: When is the opportunity expected to close? | C23: DD/MM/YYYY | E23: Is the customer on a Hotlist or the IWL? YES / NO / Don't Know (from SQO)
B24: Currency | E24: Is the customer under an audit? YES / NO / Don't Know (from SQO)
E25: Is there existing S&S on these products? If yes, fill out the S&S section below
B26: Further Details of the Deal
B28: Have you analyzed your customer's entire entitlement for all eligible parts for upgrade?
B29: When is the S&S renewal date? | C29: DD/MM/YYYY | F29: Contract type holding entitlements for upgrade
B30: *Note: Upgrade should happen at the client's renewal date. There is no credit on exiting S&S for an early upgrade | F30: Has the dealmaker been engaged?
B31: Are you requesting ALL active licenses for upgrade? | F31: Dealmaker Name
B32: Please provide justification for partial upgrade (only required if "No" to above) | F32: Original contract start date | G32: DD/MM/YYYY
B33: Is there a request to upgrade expired SS? | F33: Contract end date | G33: DD/MM/YYYY
B34: Have you engaged your S&S Renewal Rep for a reach back quote to bring the entitlements current on S&S? | F34: Year to year S&S growth rate on existing agreement (ex: Flat, 3%, 5% etc)
B35: (only required if "Yes" to above) | F35: If the contract is NOT expiring, is this part of an amendment or termination of the contract? Please select one option.
F36: Have all parts for upgrade been declared to IBM with reports / Proof of Entitlement?
F37: When is declaration expected? (only required if "No" to above)
F38: *Note - Mid-term upgrade is NOT allowed without an amendment to an ELA or termination of IULA
B41: MAS REQUEST

Sheet Trade-up Parts Calculator
B2: Maximo trade-up parts calculator for MAS
B4: Customer name | C4: Part # | D4: Part Description | E4: Current Customer Entitlement | F4: Authorized User to Concurrent User Normalization by Dividing by 3, Health RVU by 10 | G4: AppPoints for Upgrade | H4: Total Upgradable AppPoints
B5: xxxx | D5: =IF(ISBLANK(C5),"",(VLOOKUP($C5,'Upgrade Parts Future_K_v6.4'!$H$3:$M$528,2,FALSE))) | F5: =IF(ISBLANK(E5), "", IF(AND(VLOOKUP(C5,'Upgrade Parts Future_K_v6.4'!$H$3:$K$528,4,FALSE)="Resource Value Unit", E5 < 10), 1, IF(VLOOKUP(C5,'Upgrade Parts Future_K_v6.4'!$H$3:$K$528,4,FALSE)="Resource Value Unit", E5/10, E5 ) ) ) | G5: =IF(ISBLANK(E5),"",(VLOOKUP($C5,'Upgrade Parts Future_K_v6.4'!$H$3:$M$528,5,FALSE))) | H5: =IF(ISBLANK(E5),"",ROUNDUP((F5*G5),0))
D6: =IF(ISBLANK(C6),"",(VLOOKUP($C6,'Upgrade Parts Future_K_v6.4'!$H$3:$M$528,2,FALSE))) | F6: =IF(ISBLANK(E6), "", IF(AND(VLOOKUP(C6,'Upgrade Parts Future_K_v6.4'!$H$3:$K$528,4,FALSE)="Resource Value Unit", E6 < 10), 1, IF(VLOOKUP(C6,'Upgrade Parts Future_K_v6.4'!$H$3:$K$528,4,FALSE)="Resource Value Unit", E6/10, E6 ) ) ) | G6: =IF(ISBLANK(E6),"",(VLOOKUP($C6,'Upgrade Parts Future_K_v6.4'!$H$3:$M$528,5,FALSE))) | H6: =IF(ISBLANK(E6),"",ROUNDUP((F6*G6),0))
D7: =IF(ISBLANK(C7),"",(VLOOKUP($C7,'Upgrade Parts Future_K_v6.4'!$H$3:$M$528,2,FALSE))) | F7: =IF(ISBLANK(E7), "", IF(AND(VLOOKUP(C7,'Upgrade Parts Future_K_v6.4'!$H$3:$K$528,4,FALSE)="Resource Value Unit", E7 < 10), 1, IF(VLOOKUP(C7,'Upgrade Parts Future_K_v6.4'!$H$3:$K$528,4,FALSE)="Resource Value Unit", E7/10, E7 ) ) ) | G7: =IF(ISBLANK(E7),"",(VLOOKUP($C7,'Upgrade Parts Future_K_v6.4'!$H$3:$M$528,5,FALSE))) | H7: =IF(ISBLANK(E7),"",ROUNDUP((F7*G7),0))
D8: =IF(ISBLANK(C8),"",(VLOOKUP($C8,'Upgrade Parts Future_K_v6.4'!$H$3:$M$528,2,FALSE))) | F8: =IF(ISBLANK(E8), "", IF(AND(VLOOKUP(C8,'Upgrade Parts Future_K_v6.4'!$H$3:$K$528,4,FALSE)="Resource Value Unit", E8 < 10), 1, IF(VLOOKUP(C8,'Upgrade Parts Future_K_v6.4'!$H$3:$K$528,4,FALSE)="Resource Value Unit", E8/10, E8 ) ) ) | G8: =IF(ISBLANK(E8),"",(VLOOKUP($C8,'Upgrade Parts Future_K_v6.4'!$H$3:$M$528,5,FALSE))) | H8: =IF(ISBLANK(E8),"",ROUNDUP((F8*G8),0))
D9: =IF(ISBLANK(C9),"",(VLOOKUP($C9,'Upgrade Parts Future_K_v6.4'!$H$3:$M$528,2,FALSE))) | F9: =IF(ISBLANK(E9), "", IF(AND(VLOOKUP(C9,'Upgrade Parts Future_K_v6.4'!$H$3:$K$528,4,FALSE)="Resource Value Unit", E9 < 10), 1, IF(VLOOKUP(C9,'Upgrade Parts Future_K_v6.4'!$H$3:$K$528,4,FALSE)="Resource Value Unit", E9/10, E9 ) ) ) | G9: =IF(ISBLANK(E9),"",(VLOOKUP($C9,'Upgrade Parts Future_K_v6.4'!$H$3:$M$528,5,FALSE))) | H9: =IF(ISBLANK(E9),"",ROUNDUP((F9*G9),0))
D10: =IF(ISBLANK(C10),"",(VLOOKUP($C10,'Upgrade Parts Future_K_v6.4'!$H$3:$M$528,2,FALSE))) | F10: =IF(ISBLANK(E10), "", IF(AND(VLOOKUP(C10,'Upgrade Parts Future_K_v6.4'!$H$3:$K$528,4,FALSE)="Resource Value Unit", E10 < 10), 1, IF(VLOOKUP(C10,'Upgrade Parts Future_K_v6.4'!$H$3:$K$528,4,FALSE)="Resource Value Unit", E10/10, E10 ) ) ) | G10: =IF(ISBLANK(E10),"",(VLOOKUP($C10,'Upgrade Parts Future_K_v6.4'!$H$3:$M$528,5,FALSE))) | H10: =IF(ISBLANK(E10),"",ROUNDUP((F10*G10),0))
D11: =IF(ISBLANK(C11),"",(VLOOKUP($C11,'Upgrade Parts Future_K_v6.4'!$H$3:$M$528,2,FALSE))) | F11: =IF(ISBLANK(E11), "", IF(AND(VLOOKUP(C11,'Upgrade Parts Future_K_v6.4'!$H$3:$K$528,4,FALSE)="Resource Value Unit", E11 < 10), 1, IF(VLOOKUP(C11,'Upgrade Parts Future_K_v6.4'!$H$3:$K$528,4,FALSE)="Resource Value Unit", E11/10, E11 ) ) ) | G11: =IF(ISBLANK(E11),"",(VLOOKUP($C11,'Upgrade Parts Future_K_v6.4'!$H$3:$M$528,5,FALSE))) | H11: =IF(ISBLANK(E11),"",ROUNDUP((F11*G11),0))
D12: =IF(ISBLANK(C12),"",(VLOOKUP($C12,'Upgrade Parts Future_K_v6.4'!$H$3:$M$528,2,FALSE))) | F12: =IF(ISBLANK(E12), "", IF(AND(VLOOKUP(C12,'Upgrade Parts Future_K_v6.4'!$H$3:$K$528,4,FALSE)="Resource Value Unit", E12 < 10), 1, IF(VLOOKUP(C12,'Upgrade Parts Future_K_v6.4'!$H$3:$K$528,4,FALSE)="Resource Value Unit", E12/10, E12 ) ) ) | G12: =IF(ISBLANK(E12),"",(VLOOKUP($C12,'Upgrade Parts Future_K_v6.4'!$H$3:$M$528,5,FALSE))) | H12: =IF(ISBLANK(E12),"",ROUNDUP((F12*G12),0))
D13: =IF(ISBLANK(C13),"",(VLOOKUP($C13,'Upgrade Parts Future_K_v6.4'!$H$3:$M$528,2,FALSE))) | F13: =IF(ISBLANK(E13), "", IF(AND(VLOOKUP(C13,'Upgrade Parts Future_K_v6.4'!$H$3:$K$528,4,FALSE)="Resource Value Unit", E13 < 10), 1, IF(VLOOKUP(C13,'Upgrade Parts Future_K_v6.4'!$H$3:$K$528,4,FALSE)="Resource Value Unit", E13/10, E13 ) ) ) | G13: =IF(ISBLANK(E13),"",(VLOOKUP($C13,'Upgrade Parts Future_K_v6.4'!$H$3:$M$528,5,FALSE))) | H13: =IF(ISBLANK(E13),"",ROUNDUP((F13*G13),0))
D14: =IF(ISBLANK(C14),"",(VLOOKUP($C14,'Upgrade Parts Future_K_v6.4'!$H$3:$M$528,2,FALSE))) | F14: =IF(ISBLANK(E14), "", IF(AND(VLOOKUP(C14,'Upgrade Parts Future_K_v6.4'!$H$3:$K$528,4,FALSE)="Resource Value Unit", E14 < 10), 1, IF(VLOOKUP(C14,'Upgrade Parts Future_K_v6.4'!$H$3:$K$528,4,FALSE)="Resource Value Unit", E14/10, E14 ) ) ) | G14: =IF(ISBLANK(E14),"",(VLOOKUP($C14,'Upgrade Parts Future_K_v6.4'!$H$3:$M$528,5,FALSE))) | H14: =IF(ISBLANK(E14),"",ROUNDUP((F14*G14),0))
D15: =IF(ISBLANK(C15),"",(VLOOKUP($C15,'Upgrade Parts Future_K_v6.4'!$H$3:$M$528,2,FALSE))) | F15: =IF(ISBLANK(E15), "", IF(AND(VLOOKUP(C15,'Upgrade Parts Future_K_v6.4'!$H$3:$K$528,4,FALSE)="Resource Value Unit", E15 < 10), 1, IF(VLOOKUP(C15,'Upgrade Parts Future_K_v6.4'!$H$3:$K$528,4,FALSE)="Resource Value Unit", E15/10, E15 ) ) ) | G15: =IF(ISBLANK(E15),"",(VLOOKUP($C15,'Upgrade Parts Future_K_v6.4'!$H$3:$M$528,5,FALSE))) | H15: =IF(ISBLANK(E15),"",ROUNDUP((F15*G15),0))
D16: =IF(ISBLANK(C16),"",(VLOOKUP($C16,'Upgrade Parts Future_K_v6.4'!$H$3:$M$528,2,FALSE))) | F16: =IF(ISBLANK(E16), "", IF(AND(VLOOKUP(C16,'Upgrade Parts Future_K_v6.4'!$H$3:$K$528,4,FALSE)="Resource Value Unit", E16 < 10), 1, IF(VLOOKUP(C16,'Upgrade Parts Future_K_v6.4'!$H$3:$K$528,4,FALSE)="Resource Value Unit", E16/10, E16 ) ) ) | G16: =IF(ISBLANK(E16),"",(VLOOKUP($C16,'Upgrade Parts Future_K_v6.4'!$H$3:$M$528,5,FALSE))) | H16: =IF(ISBLANK(E16),"",ROUNDUP((F16*G16),0))
D17: =IF(ISBLANK(C17),"",(VLOOKUP($C17,'Upgrade Parts Future_K_v6.4'!$H$3:$M$528,2,FALSE))) | F17: =IF(ISBLANK(E17), "", IF(AND(VLOOKUP(C17,'Upgrade Parts Future_K_v6.4'!$H$3:$K$528,4,FALSE)="Resource Value Unit", E17 < 10), 1, IF(VLOOKUP(C17,'Upgrade Parts Future_K_v6.4'!$H$3:$K$528,4,FALSE)="Resource Value Unit", E17/10, E17 ) ) ) | G17: =IF(ISBLANK(E17),"",(VLOOKUP($C17,'Upgrade Parts Future_K_v6.4'!$H$3:$M$528,5,FALSE))) | H17: =IF(ISBLANK(E17),"",ROUNDUP((F17*G17),0))
... D35: =IF(ISBLANK(C35),"",(VLOOKUP($C35,'Upgrade Parts Future_K_v6.4'!$H$3:$M$528,2,FALSE))) | F35: =IF(ISBLANK(E35), "", IF(AND(VLOOKUP(C35,'Upgrade Parts Future_K_v6.4'!$H$3:$K$528,4,FALSE)="Resource Value Unit", E35 < 10), 1, IF(VLOOKUP(C35,'Upgrade Parts Future_K_v6.4'!$H$3:$K$528,4,FALSE)="Resource Value Unit", E35/10, E35 ) ) ) | G35: =IF(ISBLANK(E35),"",(VLOOKUP($C35,'Upgrade Parts Future_K_v6.4'!$H$3:$M$528,5,FALSE))) | H35: =IF(ISBLANK(E35),"",ROUNDUP((F35*G35),0))
B36: Total | E36: =SUM(E5:E35) -> 0 | H36: =MROUND(SUM(H5:H35),5) -> 0

Sheet Perpetual Trade-up Pricing
A1: IBM Internal and Business Partner Use Only | H1: Input Cells
A2: Note : Please fill in the green highlighted cells only using local currency | H2: Formula Cells
A3: MAS Perpetual Trade-up pricing needs to be uplifted a minimum of 48.5% | H3: Rev License
A4: Contact MAS project office for pricing guidance /non standard pricing; Consult the 7.14 Play for Uplifts on RTM shifts and guidance
A7: Is this an FCT client (y/n) | C7: (If NO, leave cell "A11" blank )
A9: MAS Perpetual Pricing (USD) / Update to Local Currency if outside US and note currency being used (confirm from SQO)
A10: LPP on FCT 2022 (Provided by the FCT S&S rep) | B10: LPP on PA uplifted 0% from FCT LPP (Provided by S&S rep) | C10: MAS Uplift of 48.5% | D10: MAS Points needed (qty for the Tradeup part number D29HYLL) | E10: TradeUp Price /Point (Local Currency) | F10: TradeUp Yearly List Price | G10: Discount | H10: Net Price/Year | I10: S&S | J10: Sales
C11: =B11*1.485 -> 0 | E11: 664 | F11: =D11*E11 -> 0 | G11: =1-(H11/F11) -> #DIV/0! | H11: =C11 -> 0 | I11: =(+H11*0.7407) -> 0 | J11: =(+H11*0.2593) -> 0
F13: =+F11 -> 0 | G13: Year 2 | H13: =(+H11*0.7407)*1.1 -> 0 | I13: S&S Organization has delegation on non-committed outyear Uplifts
F14: =+F13 -> 0 | G14: Year 3 | H14: =+H13*1.1 -> 0 | I14: S&S Organization has delegation on non-committed outyear Uplifts
F15: =+F14 -> 0 | G15: Year 4 | H15: =+H14*1.1 -> 0 | I15: S&S Organization has delegation on non-committed outyear Uplifts
F16: =+F15 -> 0 | G16: Year 5 | H16: =+H15*1.1 -> 0 | I16: MAS Trans Bookable
F17: =F11+F13+F14 -> 0 | G17: TOTAL 3yr | H17: =H11+H13+H14 -> 0 | I17: =+H11*0.2593 -> 0
F18: =F17+F15+F16 -> 0 | G18: TOTAL 5yr | H18: =H17+H15+H16 -> 0 | I18: =+H11*0.2593 -> 0
A19: MAS Managed Services | I19: =H19*0.11 -> 0
A20: Concurrent Users | B20: Services | C20: VPC | D20: GB | E20: Unit List Price | G20: Discount | H20: Net Price /Year
A31: RTM Shift Scenario outside of the Play approved scenarios or when Geo rates are not available in the Play:
A33: MAS Perpetual Pricing (USD) / Update to local currency if ouside US and note currency being used
A34: LPP on FCT 2022 (Provided by the FCT S&S rep) | B34: LPP on PA uplifted 0% from FCT LPP (Provided by S&S rep) | C34: MAS Uplift of 48.5% | D34: MAS Points needed (qty for the Tradeup part number D29HYLL) | E34: TradeUp Price /Point (Local Currency) | F34: TradeUp Yearly List Price | G34: Discount | H34: Net Price/Year | I34: S&S | J34: Sales | K34: Add'l Incentive Uplifts if required (modify the % based on Lamar Murphy input) | L34: Min Price required w RTM Shift | M34: Discount
C35: =B35*1.485 -> 0 | E35: 664 | F35: =D35*E35 -> 0 | G35: =1-(H35/F35) -> #DIV/0! | H35: =C35 -> 0 | I35: =(+H35*0.7407) -> 0 | J35: =(+H35*0.2593) -> 0 | K35: 0.12 | L35: =H35*(1+K35) -> 0 | M35: =1-L35/F35 -> #DIV/0!
F37: =+F35 -> 0 | G37: Year 2 | H37: =(+H35*0.7407)*1.1 -> 0 | I37: S&S Organization has delegation on non-committed outyear Uplifts
F38: =+F37 -> 0 | G38: Year 3 | H38: =+H37*1.1 -> 0 | I38: S&S Organization has delegation on non-committed outyear Uplifts
F39: =+F38 -> 0 | G39: Year 4 | H39: =+H38*1.1 -> 0 | I39: S&S Organization has delegation on non-committed outyear Uplifts
F40: =+F39 -> 0 | G40: Year 5 | H40: =+H39*1.1 -> 0 | I40: MAS Trans Bookable
F41: =F35+F37+F38 -> 0 | G41: TOTAL 3yr | H41: =H35+H37+H38 -> 0 | I41: =+H35*0.2593 -> 0
F42: =F41+F39+F40 -> 0 | G42: TOTAL 5yr | H42: =H41+H39+H40 -> 0 | I42: =+H35*0.2593 -> 0

Sheet List of Eligible Parts
A2: UT_LEVEL_CODE_30_DSCR | B2: IBM_SW_FAM_CODE | C2: IBM_PROD_ID | D2: IBM_PROD_ID_DSCR | E2: WWIDE_PROD_CODE_DSCR | F2: Eligible Part # | G2: Eligible Part Description | H2: Eligible Part Parent Lic + S&S Part # | I2: CU_DSCR | J2: Part Type
A3: Enterprise Asset Management | B3: MXA ANYWHERE | C3: 5725M39 | D3: IBM Maximo Anywhere | E3: Maximo Anywhere | F3: E0K39LL | G3: IBM MAXIMO ANYWHERE ADD-ON AUTHORIZED USER ANNUAL SW SUBSCRIPTION & SUPPORT RENEWAL | H3: D17CCLL | I3: Authorized User | J3: Renewal
A4: Enterprise Asset Management | B4: MXA ANYWHERE | C4: 5725M39 | D4: IBM Maximo Anywhere | E4: Maximo Anywhere | F4: D17CCLL | G4: IBM MAXIMO ANYWHERE ADD-ON AUTHORIZED USER LICENSE + SW SUBSCRIPTION & SUPPORT 12 MONTHS | H4: D17CCLL | I4: Authorized User | J4: License + S&S
A5: Enterprise Asset Management | B5: MXA ANYWHERE | C5: 5725M39 | D5: IBM Maximo Anywhere | E5: Maximo Anywhere | F5: D17CDLL | G5: IBM MAXIMO ANYWHERE ADD-ON AUTHORIZED USER SW SUBSCRIPTION & SUPPORT REINSTATEMENT 12 MONTHS | H5: D17CCLL | I5: Authorized User | J5: Reinstatement
A6: Enterprise Asset Management | B6: MXA ANYWHERE | C6: 5725M39 | D6: IBM Maximo Anywhere | E6: Maximo Anywhere | F6: E0N3QLL | G6: IBM MAXIMO ANYWHERE ADD-ON CONCURRENT USER ANNUAL SW SUBSCRIPTION & SUPPORT RENEWAL 12 MONTHS | H6: D1QBGLL | I6: Concurrent User | J6: Renewal
A7: Enterprise Asset Management | B7: MXA ANYWHERE | C7: 5725M39 | D7: IBM Maximo Anywhere | E7: Maximo Anywhere | F7: D1QBGLL | G7: IBM MAXIMO ANYWHERE ADD-ON CONCURRENT USER LICENSE + SW SUBSCRIPTION & SUPPORT 12 MONTHS | H7: D1QBGLL | I7: Concurrent User | J7: License + S&S
A8: Enterprise Asset Management | B8: MXA ANYWHERE | C8: 5725M39 | D8: IBM Maximo Anywhere | E8: Maximo Anywhere | F8: D1QBHLL | G8: IBM MAXIMO ANYWHERE ADD-ON CONCURRENT USER SW SUBSCRIPTION & SUPPORT REINSTATEMENT 12 MONTHS | H8: D1QBGLL | I8: Concurrent User | J8: Reinstatement
A9: Enterprise Asset Management | B9: MXA ANYWHERE | C9: 5725M39 | D9: IBM Maximo Anywhere | E9: Maximo Anywhere | F9: D1QBMLL | G9: IBM MAXIMO ANYWHERE ADD-ON CONCURRENT USER LINUX ON Z SYSTEM TRADE UP FROM 3 MAXIMO ANYWHERE ADD-ON AUTHORIZED USER ON Z SYSTEM + SW SUBSCRIPTION & SUPPORT 12 MONTHS | H9: D1QBKLL | I9: Concurrent User | J9: Trade-Up
A10: Enterprise Asset Management | B10: MXA ANYWHERE | C10: 5725M39 | D10: IBM Maximo Anywhere | E10: Maximo Anywhere | F10: E0N3RLL | G10: IBM MAXIMO ANYWHERE ADD-ON CONCURRENT USER LINUX Z SYSTEM ANNUAL SW SUBSCRIPTION & SUPPORT RENEWAL | H10: D1QBKLL | I10: Concurrent User | J10: Renewal
A11: Enterprise Asset Management | B11: MXA ANYWHERE | C11: 5725M39 | D11: IBM Maximo Anywhere | E11: Maximo Anywhere | F11: D1QBKLL | G11: IBM MAXIMO ANYWHERE ADD-ON CONCURRENT USER LINUX Z SYSTEM SW SUBSCRIPTION & SUPPORT 12 MONTHS | H11: D1QBKLL | I11: Concurrent User | J11: License + S&S
A12: Enterprise Asset Management | B12: MXA ANYWHERE | C12: 5725M39 | D12: IBM Maximo Anywhere | E12: Maximo Anywhere | F12: D1QBLLL | G12: IBM MAXIMO ANYWHERE ADD-ON CONCURRENT USER LINUX Z SYSTEM SW SUBSCRIPTION & SUPPORT REINSTATEMENT 12 MONTHS | H12: D1QBKLL | I12: Concurrent User | J12: Reinstatement
A13: Enterprise Asset Management | B13: MXA ANYWHERE | C13: 5725M39 | D13: IBM Maximo Anywhere | E13: Maximo Anywhere | F13: D1QBILL | G13: IBM MAXIMO ANYWHERE ADD-ON CONCURRENT USER TRADE UP FROM 3 MAXIMO ANYWHERE ADD-ON AUTHORIZED USER + SW SUBSCRIPTION & SUPPORT 12 MONTHS | H13: D1QBGLL | I13: Concurrent User | J13: Trade-Up
... A505: Maximo | B505: MVI | C505: 5737H10 | D505: IBM Maximo Visual Inspections | E505: Maximo Visual Inspections | F505: D1Y6BLL | G505: IBM Maximo Visual Inspections | H505: D1Y6BLL | I505: per vServer | J505: License + S&S
A506: APM | B506: EMA | D506: IBM Maximo Equipment Maintenance Assistant | E506: Maximo Equipment Maintenance Assistant | F506: E0QC7LL | G506: IBM MAXIMO EQUIPMENT MAINTENANCE ASSISTANT BASE PER 48 VIRTUAL PROCESSOR CORES ANNUAL SW SUBSCRIPTION & SUPPORT RENEWAL 12 MONTHS | H506: E0QC7LL | I506: VPC | J506: Renewal
A507: APM | B507: EMA | D507: IBM Maximo Equipment Maintenance Assistant | E507: Maximo Equipment Maintenance Assistant | F507: D24Z1LL | G507: IBM MAXIMO EQUIPMENT MAINTENANCE ASSISTANT BASE PER 48 VIRTUAL PROCESSOR CORES LICENSE + SW SUBSCRIPTION & SUPPORT 12 MONTHS | H507: D24Z1LL | I507: VPC | J507: License + S&S
A508: APM | B508: EMA | D508: IBM Maximo Equipment Maintenance Assistant | E508: Maximo Equipment Maintenance Assistant | F508: E0QC8LL | G508: IBM MAXIMO EQUIPMENT MAINTENANCE ASSISTANT PER RESOURCE VALUE UNIT ANNUAL SW SUBSCRIPTION & SUPPORT RENEWAL 12 MONTHS | H508: E0QC8LL | I508: RVU | J508: Renewal
A509: APM | B509: EMA | D509: IBM Maximo Equipment Maintenance Assistant | E509: Maximo Equipment Maintenance Assistant | F509: D24Z4LL | G509: IBM MAXIMO EQUIPMENT MAINTENANCE ASSISTANT PER RESOURCE VALUE UNIT LICENSE + SW SUBSCRIPTION & SUPPORT 12 MONTHS | H509: D24Z4LL | I509: RVU | J509: License + S&S
A510: Asset Performance Management | B510: ENERGY SIGHT | C510: 5725W39 | D510: IBM Maximo Ass Perf Mgnt for Engy & Uti On-prem | E510: Max APM for Energy & Utilities | F510: E0LT5LL | G510: IBM MAXIMO APM FOR E&U ON-PREMISE - ASSETS PER RESOURCE VALUE UNIT ANNUAL SW SUBSCRIPTION & SUPPORT RENEWAL | H510: D1I2WLL | I510: RVU | J510: Renewal
A511: Asset Performance Management | B511: ENERGY SIGHT | C511: 5725W39 | D511: IBM Maximo Ass Perf Mgnt for Engy & Uti On-prem | E511: Max APM for Energy & Utilities | F511: D1I2WLL | G511: IBM MAXIMO APM FOR E&U ON-PREMISE - ASSETS PER RESOURCE VALUE UNIT LICENSE + SW SUBSCRIPTION & SUPPORT 12 MONTHS | H511: D1I2WLL | I511: RVU | J511: License + S&S
A512: Asset Performance Management | B512: ENERGY SIGHT | C512: 5725W39 | D512: IBM Maximo Ass Perf Mgnt for Engy & Uti On-prem | E512: Max APM for Energy & Utilities | F512: D1I2XLL | G512: IBM MAXIMO APM FOR E&U ON-PREMISE - ASSETS PER RESOURCE VALUE UNIT SW SUBSCRIPTION & SUPPORT REINSTATEMENT 12 MONTHS | H512: D1I2WLL | I512: ERVU | J512: Reinstatement
A513: Asset Performance Management | B513: ENERGY SIGHT | C513: 5725W39 | D513: IBM Maximo Ass Perf Mgnt for Engy & Uti On-prem | E513: Max APM for Energy & Utilities | F513: E0LT3LL | G513: IBM MAXIMO APM FOR E&U ON-PREMISE - LIMITED USER PER USER VALUE UNIT ANNUAL SW SUBSCRIPTION & SUPPORT RENEWAL | H513: D1I2TLL | I513: User Value Unit | J513: Renewal
A514: Asset Performance Management | B514: ENERGY SIGHT | C514: 5725W39 | D514: IBM Maximo Ass Perf Mgnt for Engy & Uti On-prem | E514: Max APM for Energy & Utilities | F514: D1I2TLL | G514: IBM MAXIMO APM FOR E&U ON-PREMISE - LIMITED USER PER USER VALUE UNIT LICENSE + SW SUBSCRIPTION & SUPPORT 12 MONTHS | H514: D1I2TLL | I514: User Value Unit | J514: License + S&S
A515: Asset Performance Management | B515: ENERGY SIGHT | C515: 5725W39 | D515: IBM Maximo Ass Perf Mgnt for Engy & Uti On-prem | E515: Max APM for Energy & Utilities | F515: D1I2ULL | G515: IBM MAXIMO APM FOR E&U ON-PREMISE - LIMITED USER PER USER VALUE UNIT SW SUBSCRIPTION & SUPPORT REINSTATEMENT 12 MONTHS | H515: D1I2TLL | I515: User Value Unit | J515: Reinstatement
A516: Asset Performance Management | B516: ENERGY SIGHT | C516: 5725W39 | D516: IBM Maximo Ass Perf Mgnt for Engy & Uti On-prem | E516: Max APM for Energy & Utilities | F516: E0LT2LL | G516: IBM MAXIMO APM FOR E&U ON-PREMISE - STANDARD USER PER AUTHORIZED USER ANNUAL SW SUBSCRIPTION & SUPPORT RENEWAL | H516: D1I2QLL | I516: Authorized User | J516: Renewal
A517: Asset Performance Management | B517: ENERGY SIGHT | C517: 5725W39 | D517: IBM Maximo Ass Perf Mgnt for Engy & Uti On-prem | E517: Max APM for Energy & Utilities | F517: D1I2QLL | G517: IBM MAXIMO APM FOR E&U ON-PREMISE - STANDARD USER PER AUTHORIZED USER LICENSE + SW SUBSCRIPTION & SUPPORT 12 MONTHS | H517: D1I2QLL | I517: Authorized User | J517: License + S&S
A518: Asset Performance Management | B518: ENERGY SIGHT | C518: 5725W39 | D518: IBM Maximo Ass Perf Mgnt for Engy & Uti On-prem | E518: Max APM for Energy & Utilities | F518: D1I2RLL | G518: IBM MAXIMO APM FOR E&U ON-PREMISE - STANDARD USER PER AUTHORIZED USER SW SUBSCRIPTION & SUPPORT REINSTATEMENT 12 MONTHS | H518: D1I2QLL | I518: Authorized User | J518: Reinstatement
A519: Asset Performance Management | B519: ENERGY SIGHT | C519: 5725W39 | D519: IBM Maximo Ass Perf Mgnt for Engy & Uti On-prem | E519: Max APM for Energy & Utilities | F519: E0P37LL | G519: IBM MAXIMO APM FOR E&U ON-PREMISE - STANDARD USER PER CONCURRENT USER ANNUAL SW SUBSCRIPTION & SUPPORT RENEWAL | H519: D1W7FLL | I519: Concurrent User | J519: Renewal
A520: Asset Performance Management | B520: ENERGY SIGHT | C520: 5725W39 | D520: IBM Maximo Ass Perf Mgnt for Engy & Uti On-prem | E520: Max APM for Energy & Utilities | F520: D1W7FLL | G520: IBM MAXIMO APM FOR E&U ON-PREMISE - STANDARD USER PER CONCURRENT USER LICENSE + SW SUBSCRIPTION & SUPPORT 12 MONTHS | H520: D1W7FLL | I520: Concurrent User | J520: License + S&S
A521: Asset Performance Management | B521: ENERGY SIGHT | C521: 5725W39 | D521: IBM Maximo Ass Perf Mgnt for Engy & Uti On-prem | E521: Max APM for Energy & Utilities | F521: D1W7GLL | G521: IBM MAXIMO APM FOR E&U ON-PREMISE - STANDARD USER PER CONCURRENT USER SW SUBSCRIPTION & SUPPORT REINSTATEMENT 12 MONTHS | H521: D1W7FLL | I521: Concurrent User | J521: Reinstatement
A522: Enterprise Asset Management | B522: MAXIMO | C522: 5724U18 | D522: IBM Maximo Asset Management | E522: IBM Maximo Asset Management | F522: E05B6LL | G522: IBM MAXIMO ASSET MANAGEMENT INTERNAL SERVICE PROVIDERS INSTALL + SW SUBSCRIPTION & SUPPORT 12 MONTHS | H522: E05B6LL | I522: User | J522: Renewal | P522: 1070 | Q522: renewal | R522: INTERNAL SERVICE PROVIDERS | S522: ADD-ON | T522: Install | U522: =IF(ISNUMBER(SEARCH("ADD-ON",$I522)),"ADD-ON","NOT AN ADD-ON") -> NOT AN ADD-ON
A523: Enterprise Asset Management | B523: MAXIMO | C523: 5724U18 | D523: IBM Maximo Asset Management | E523: IBM Maximo Asset Management | F523: D28NMLL | G523: IBM MAXIMO SCHEDULER OPTIMIZATION PER INSTALL LICENSE + SW SUBSCRIPTION & SUPPORT 12 MONTHS | H523: E05B6LL | I523: Install | J523: License + S&S | P523: 1070 | Q523: renewal | R523: INTERNAL SERVICE PROVIDERS | S523: ADD-ON | T523: Install | U523: =IF(ISNUMBER(SEARCH("ADD-ON",$I523)),"ADD-ON","NOT AN ADD-ON") -> NOT AN ADD-ON
A524: Enterprise Asset Management | B524: MAXIMO | C524: 5724U18 | D524: IBM Maximo Asset Management | E524: IBM Maximo Asset Management | F524: E0R3ELL | G524: IBM MAXIMO SCHEDULER OPTIMIZATION PER INSTALL ANNUAL SW SUBSCRIPTION & SUPPORT RENEWAL | H524: E05B6LL | I524: Install | J524: Renewal | P524: 1070 | Q524: renewal | R524: INTERNAL SERVICE PROVIDERS | S524: ADD-ON | T524: Install | U524: =IF(ISNUMBER(SEARCH("ADD-ON",$I524)),"ADD-ON","NOT AN ADD-ON") -> NOT AN ADD-ON
A525: Enterprise Asset Management | B525: MAXIMO | C525: 5725U87 | D525: IBM Maximo Asset Management | E525: IBM Maximo Asset Management | F525: D20V8LL | G525: IBM MAXIMO FOR AVIATION MAINTENANCE OPTIMIZATION INSTALL LICENSE SW SUBSCRIPTION & SUPPORT 12 MONTHS | H525: E05B6LL | I525: Install | J525: License + S&S | P525: 1070 | Q525: renewal | R525: INTERNAL SERVICE PROVIDERS | S525: ADD-ON | T525: Install | U525: =IF(ISNUMBER(SEARCH("ADD-ON",$I525)),"ADD-ON","NOT AN ADD-ON") -> NOT AN ADD-ON
A526: Enterprise Asset Management | B526: MAXIMO | C526: 5725U87 | D526: IBM Maximo Asset Management | E526: IBM Maximo Asset Management | F526: E0PNBLL | G526: IBM MAXIMO FOR AVIATION MAINTENANCE OPTIMIZATION INSTALL LICENCE ANNUAL SW SUBSCRIPTION & SUPPORT RENEWAL | H526: E05B6LL | I526: Install | J526: Renewal | P526: 1070 | Q526: renewal | R526: INTERNAL SERVICE PROVIDERS | S526: ADD-ON | T526: Install | U526: =IF(ISNUMBER(SEARCH("ADD-ON",$I526)),"ADD-ON","NOT AN ADD-ON") -> NOT AN ADD-ON
A527: Asset Performance Management | B527: ENERGY SIGHT | C527: 5725W39 | D527: IBM Maximo Ass Perf Mgnt for Engy & Uti On-prem | E527: Max APM for Energy & Utilities | F527: D1W7HLL | G527: IBM MAXIMO APM FOR E&U ON-PREMISE - DECISION OPTIMIZATION USER PER CONCURRENT USER LICENSE + SW SUBSCRIPTION & SUPPORT 12 MONTHS | H527: D1W7HLL | I527: User | J527: License + S&S
A528: Asset Performance Management | B528: ENERGY SIGHT | C528: 5725W39 | D528: IBM Maximo Ass Perf Mgnt for Engy & Uti On-prem | E528: Max APM for Energy & Utilities | F528: E0P38LL | G528: IBM MAXIMO APM FOR E&U ON-PREMISE - DECISION OPTIMIZATION USER PER CONCURRENT USER ANNUAL SW SUBSCRIPTION & SUPPORT RENEWAL | H528: E0P38LL | I528: User | J528: Reinstatement

Sheet Version
A1: Date | B1: Version | C1: Changes
A2: 11/24/2020 | B2: 5.4 | C2: Updated New Deal Calculator tab - N/A error on MVI after first row
A3: 11/25/2020 | B3: 5.4a | C3: Rounded to the 5th on Upgrade/Tradeup Total cell
A4: 12/14/2020 | B4: 5.4b | C4: Added new Line Item Description column to New Deal Calc tab & sorted Upgrade/Tradeup lookup list
A5: 01/07/2021 | B5: 6 | C5: Added Assist, APM4EU, MVI Edge to New Deal tab, Assist/APM4EU parts to Upgrade and Tradeup tabs
A6: 03/12/2021 | B6: 6.1 | C6: Updated Perpetual Trade-up Pricing tab to add S&S and Sales perentages along with YoY at 10% per S&S request/ Updated Note section in New Deal tab
A7: 04/06/2021 | B7: 6.2 | C7: Added Civil Infrastructure Install AppPoints on New Deal tab
A8: 06/14/2021 | B8: 6.3 | C8: Updated default List Price on Pricing tabs
A9: 06/22/2021 | B9: 6.3a | C9: Added additional rows to the Upgrade/Trade up tabs
A10: 08/16/2021 | B10: 6.4 | C10: Addition of Authorized Users to New Deal and Updated Sales S&S on Trade-up Pricing tab
A11: 10/05/2021 | B11: 6.5 | C11: Addition of Eligible Parts tab and details added to Pricing tabs
A12: 11/04/2021 | B12: 6.5a | C12: Added part numbers to the upgrade/tradeup pricing tabs
A13: 05/22/2022 | B13: 6.5b | C13: corrected aviation CU mapping part to 15 app points vs 5.
A14: 06/02/2022 | B14: 6.5c | C14: addition of SP internal Install part
A15: 07/26/2022 | B15: 7 | C15: addition of Maximo Optimizer along with update of Edge as 1 AppPoint
A16: 10/26/2022 | B16: 7a | C16: updated add-on AppPoints to authorized plus addition of upfront and annual pricing to subscription pricing tab
A17: 10/28/2022 | B17: 7b | C17: updated HSE concurrent

Sheet New Parts
E2: Required AppPoints
C3: Install | D3: ADAPTER FOR ORACLE | E3: 80
C4: Install | D4: ADAPTER FOR SAP | E4: 80
C5: Limited Concurrent User | D5: ANYWHERE | E5: 5
C6: Premium Concurrent User | D6: ASSET CONFIGURATION MANAGER | E6: 15
C7: Limited Concurrent User | D7: ASSET CONFIGURATION MANAGER LIMITED | E7: 5
C8: Base Concurrent User | D8: ASSET MANAGEMENT (CORE) | E8: 10
C9: Limited Concurrent User | D9: ASSET MANAGEMENT (CORE) LIMITED | E9: 5
C10: Premium Concurrent User | D10: AVIATION | E10: 15
C11: Limited Concurrent User | D11: AVIATION LIMITED | E11: 5
C12: Premium Concurrent User | D12: CIVIL INFRASTRUCTRE | E12: 15
C13: Limited Concurrent User | D13: CIVIL INFRASTRUCTURE LIMITED | E13: 5
C14: Premium Concurrent User | D14: HEALTH SAFETY & ENVIORNMENT | E14: 15
... C26: Limited Concurrent User | D26: UTILITIES LIMITED | E26: 5
D27: CALIBRATION FULL | E27: 10
D28: CALIBRATION LIMITED | E28: 5
D29: LINEAR FULL | E29: 10
D30: LINEAR LIMITED | E30: 5
D31: SCHEDULER FULL | E31: 10
D33: SPATIAL FULL | E33: 10
D34: SPATIAL LIMITED | E34: 5
D37: Admin Premium User | E37: 15
D38: Admin Base User | E38: 10
D39: Premium Concurrent User | E39: 15
D40: Base Concurrent User | E40: 10
D41: Limited Concurrent User | E41: 5
... D54: Install - Optimizer Limited | E54: 60

Sheet Upgrade Parts Future_K_v5.4
A2: UT_LEVEL_CODE_30_DSCR | B2: IBM_SW_PILLAR_CODE | C2: IBM_SW_FAM_CODE | D2: IBM_PROD_ID | E2: IBM_PROD_ID_DSCR | F2: WWIDE_PROD_CODE_DSCR | G2: Eligible Part List Price | H2: Eligible Part # | I2: Eligible Part Description | J2: Eligible Part Parent Lic + S&S Part # | K2: CU_DSCR | L2: AppPoint for upgrade | M2: Upgrade Price Metric Conversion | N2: MAS AppPoint (Ltd, Base, Prm) | O2: Price Metric Conversion | P2: Parent Lic + S&S Part # US List Price | Q2: Part Type | R2: Offering name | S2: Core/IS/Add-ons/Anywhere | T2: AUTHORIZED | U2: Add-on Parts
A3: Enterprise Asset Management | B3: MAXIMO | C3: MXA CONFIG | D3: 5724U28 | E3: IBM Maximo Asset Configuration Manager | F3: Maximo Asset Configuration Manager | G3: 8980 | H3: D03WULL | I3: IBM MAXIMO ASSET CONFIGURATION MANAGER ASSET LICENSE + SW SUBSCRIPTION & SUPPORT 12 MONTHS | J3: D03WULL | K3: Asset | L3: Manual Input required | M3: =ROUND(IF(K3="Authorized User",L3/3,L3),2) -> #VALUE! | N3: 15 | O3: 5 | P3: 8980 | Q3: License + S&S | R3: ASSET CONFIGURATION MANAGER | S3: ACM | T3: ASSET | U3: =IF(ISNUMBER(SEARCH("ADD-ON",$I3)),"ADD-ON","NOT AN ADD-ON") -> NOT AN ADD-ON | V3: =CONCATENATE(R3,S3,T3,U3) -> ASSET CONFIGURATION MANAGERACMASSETNOT AN ADD-ON
A4: Enterprise Asset Management | B4: MAXIMO | C4: MXA CONFIG | D4: 5724U28 | E4: IBM Maximo Asset Configuration Manager | F4: Maximo Asset Configuration Manager | G4: 5390 | H4: D03WVLL | I4: IBM MAXIMO ASSET CONFIGURATION MANAGER ASSET SW SUBSCRIPTION & SUPPORT REINSTATEMENT 12 MONTHS | J4: D03WULL | K4: Asset | L4: Manual Input required | M4: =ROUND(IF(K4="Authorized User",L4/3,L4),2) -> #VALUE! | N4: 15 | O4: 5 | P4: 8980 | Q4: Reinstatement | R4: ASSET CONFIGURATION MANAGER | S4: ACM | T4: ASSET | U4: =IF(ISNUMBER(SEARCH("ADD-ON",$I4)),"ADD-ON","NOT AN ADD-ON") -> NOT AN ADD-ON | V4: =CONCATENATE(R4,S4,T4,U4) -> ASSET CONFIGURATION MANAGERACMASSETNOT AN ADD-ON
A5: Enterprise Asset Management | B5: MAXIMO | C5: MXA CONFIG | D5: 5724U28 | E5: IBM Maximo Asset Configuration Manager | F5: Maximo Asset Configuration Manager | G5: 5740 | H5: D03WYLL | I5: IBM MAXIMO ASSET CONFIGURATION MANAGER AUTHORIZED USER LICENSE + SW SUBSCRIPTION & SUPPORT 12 MONTHS | J5: D03WYLL | K5: Authorized User | L5: 15 | M5: =ROUND(IF(K5="Authorized User",L5/3,L5),2) -> 5 | N5: 15 | O5: 5 | P5: 5740 | Q5: License + S&S | R5: ASSET CONFIGURATION MANAGER | S5: ACM | T5: AUTHORIZED | U5: =IF(ISNUMBER(SEARCH("ADD-ON",$I5)),"ADD-ON","NOT AN ADD-ON") -> NOT AN ADD-ON | V5: =CONCATENATE(R5,S5,T5,U5) -> ASSET CONFIGURATION MANAGERACMAUTHORIZEDNOT AN ADD-ON
A6: Enterprise Asset Management | B6: MAXIMO | C6: MXA CONFIG | D6: 5724U28 | E6: IBM Maximo Asset Configuration Manager | F6: Maximo Asset Configuration Manager | G6: 3440 | H6: D03WZLL | I6: IBM MAXIMO ASSET CONFIGURATION MANAGER AUTHORIZED USER SW SUBSCRIPTION & SUPPORT REINSTATEMENT 12 MONTHS | J6: D03WYLL | K6: Authorized User | L6: 15 | M6: =ROUND(IF(K6="Authorized User",L6/3,L6),2) -> 5 | N6: 15 | O6: 5 | P6: 5740 | Q6: Reinstatement | R6: ASSET CONFIGURATION MANAGER | S6: ACM | T6: AUTHORIZED | U6: =IF(ISNUMBER(SEARCH("ADD-ON",$I6)),"ADD-ON","NOT AN ADD-ON") -> NOT AN ADD-ON | V6: =CONCATENATE(R6,S6,T6,U6) -> ASSET CONFIGURATION MANAGERACMAUTHORIZEDNOT AN ADD-ON
A7: Enterprise Asset Management | B7: MAXIMO | C7: MXA CALIBRAT | D7: 5724U33 | E7: IBM Maximo Calibration | F7: Maximo Calibration | G7: 584 | H7: D03X4LL | I7: IBM MAXIMO CALIBRATION AUTHORIZED USER LICENSE + SW SUBSCRIPTION & SUPPORT 12 MONTHS | J7: D03X4LL | K7: Authorized User | L7: 0 | M7: =ROUND(IF(K7="Authorized User",L7/3,L7),2) -> 0 | N7: 5 | O7: 1.6666667 | P7: 584 | Q7: License + S&S | R7: CALIBRATION | S7: ADD-ON | T7: AUTHORIZED | U7: =IF(ISNUMBER(SEARCH("ADD-ON",$I7)),"ADD-ON","NOT AN ADD-ON") -> NOT AN ADD-ON | V7: =CONCATENATE(R7,S7,T7,U7) -> CALIBRATIONADD-ONAUTHORIZEDNOT AN ADD-ON
A8: Enterprise Asset Management | B8: MAXIMO | C8: MXA CALIBRAT | D8: 5724U33 | E8: IBM Maximo Calibration | F8: Maximo Calibration | G8: 350 | H8: D03X5LL | I8: IBM MAXIMO CALIBRATION AUTHORIZED USER SW SUBSCRIPTION & SUPPORT REINSTATEMENT 12 MONTHS | J8: D03X4LL | K8: Authorized User | L8: 0 | M8: =ROUND(IF(K8="Authorized User",L8/3,L8),2) -> 0 | N8: 5 | O8: 1.6666667 | P8: 584 | Q8: Reinstatement | R8: CALIBRATION | S8: ADD-ON | T8: AUTHORIZED | U8: =IF(ISNUMBER(SEARCH("ADD-ON",$I8)),"ADD-ON","NOT AN ADD-ON") -> NOT AN ADD-ON | V8: =CONCATENATE(R8,S8,T8,U8) -> CALIBRATIONADD-ONAUTHORIZEDNOT AN ADD-ON
A9: Enterprise Asset Management | B9: MAXIMO | C9: MXA LINEAR | D9: 5724U18 | E9: IBM Maximo Asset Management | F9: Maximo Asset Management | G9: 712 | H9: D040SLL | I9: IBM MAXIMO LINEAR ASSET MANAGER AUTHORIZED USER LICENSE + SW SUBSCRIPTION & SUPPORT 12 MONTHS | J9: D040SLL | K9: Authorized User | L9: 0 | M9: =ROUND(IF(K9="Authorized User",L9/3,L9),2) -> 0 | N9: 5 | O9: 1.6666667 | P9: 712 | Q9: License + S&S | R9: LINEAR | S9: ADD-ON | T9: AUTHORIZED | U9: =IF(ISNUMBER(SEARCH("ADD-ON",$I9)),"ADD-ON","NOT AN ADD-ON") -> NOT AN ADD-ON | V9: =CONCATENATE(R9,S9,T9,U9) -> LINEARADD-ONAUTHORIZEDNOT AN ADD-ON
A10: Enterprise Asset Management | B10: MAXIMO | C10: MXA LINEAR | D10: 5724U18 | E10: IBM Maximo Asset Management | F10: Maximo Asset Management | G10: 427 | H10: D040TLL | I10: IBM MAXIMO LINEAR ASSET MANAGER AUTHORIZED USER SW SUBSCRIPTION & SUPPORT REINSTATEMENT 12 MONTHS | J10: D040SLL | K10: Authorized User | L10: 0 | M10: =ROUND(IF(K10="Authorized User",L10/3,L10),2) -> 0 | N10: 5 | O10: 1.6666667 | P10: 712 | Q10: Reinstatement | R10: LINEAR | S10: ADD-ON | T10: AUTHORIZED | U10: =IF(ISNUMBER(SEARCH("ADD-ON",$I10)),"ADD-ON","NOT AN ADD-ON") -> NOT AN ADD-ON | V10: =CONCATENATE(R10,S10,T10,U10) -> LINEARADD-ONAUTHORIZEDNOT AN ADD-ON
A11: Enterprise Asset Management | B11: MAXIMO | C11: MX ENT ADP | D11: 5724T00 | E11: IBM Maximo Enterprise Adapter | F11: Maximo Enterprise Adapter | G11: 161000 | H11: D04QDLL | I11: IBM MAXIMO ENTERPRISE ADAPTER FOR SAP APPLICATIONS SERVER LICENSE + SW SUBSCRIPTION & SUPPORT 12 MONTHS | J11: D04QDLL | K11: Server | L11: 80 | M11: =ROUND(IF(K11="Authorized User",L11/3,L11),2) -> 80 | N11: 80 | O11: 1 | P11: 161000 | Q11: License + S&S | R11: ADAPTER FOR SAP | S11: ADAPTER | T11: ADAPTER | U11: =IF(ISNUMBER(SEARCH("ADD-ON",$I11)),"ADD-ON","NOT AN ADD-ON") -> NOT AN ADD-ON | V11: =CONCATENATE(R11,S11,T11,U11) -> ADAPTER FOR SAPADAPTERADAPTERNOT AN ADD-ON
A12: Enterprise Asset Management | B12: MAXIMO | C12: MX ENT ADP | D12: 5724T00 | E12: IBM Maximo Enterprise Adapter | F12: Maximo Enterprise Adapter | G12: 96300 | H12: D04QELL | I12: IBM MAXIMO ENTERPRISE ADAPTER FOR SAP APPLICATIONS SERVER SW SUBSCRIPTION & SUPPORT REINSTATEMENT 12 MONTHS | J12: D04QDLL | K12: Server | L12: 80 | M12: =ROUND(IF(K12="Authorized User",L12/3,L12),2) -> 80 | N12: 80 | O12: 1 | P12: 161000 | Q12: Reinstatement | R12: ADAPTER FOR SAP | S12: ADAPTER | T12: ADAPTER | U12: =IF(ISNUMBER(SEARCH("ADD-ON",$I12)),"ADD-ON","NOT AN ADD-ON") -> NOT AN ADD-ON | V12: =CONCATENATE(R12,S12,T12,U12) -> ADAPTER FOR SAPADAPTERADAPTERNOT AN ADD-ON
A13: Enterprise Asset Management | B13: MAXIMO | C13: MXS EAM | D13: 5724U18 | E13: IBM Maximo Asset Management | F13: Maximo Asset Management | G13: 1780 | H13: D04XSLL | I13: IBM MAXIMO ASSET MANAGEMENT MANAGED SERVICE PROVIDERS LIMITED USE AUTHORIZED USER LICENSE + SW SUBSCRIPTION & SUPPORT 12 MONTHS | J13: D04XSLL | K13: Authorized User | L13: 0 | M13: =ROUND(IF(K13="Authorized User",L13/3,L13),2) -> 0 | N13: 5 | O13: 1.6666667 | P13: 1780 | Q13: License + S&S | R13: MANAGED SERVICE PROVIDERS | S13: MSP | T13: LIMITED | U13: =IF(ISNUMBER(SEARCH("ADD-ON",$I13)),"ADD-ON","NOT AN ADD-ON") -> NOT AN ADD-ON | V13: =CONCATENATE(R13,S13,T13,U13) -> MANAGED SERVICE PROVIDERSMSPLIMITEDNOT AN ADD-ON
A14: Enterprise Asset Management | B14: MAXIMO | C14: MXS EAM | D14: 5724U18 | E14: IBM Maximo Asset Management | F14: Maximo Asset Management | G14: 1070 | H14: D04XTLL | I14: IBM MAXIMO ASSET MANAGEMENT MANAGED SERVICE PROVIDERS LIMITED USE AUTHORIZED USER SW SUBSCRIPTION & SUPPORT REINSTATEMENT 12 MONTHS | J14: D04XSLL | K14: Authorized User | L14: 0 | M14: =ROUND(IF(K14="Authorized User",L14/3,L14),2) -> 0 | N14: 5 | O14: 1.6666667 | P14: 1780 | Q14: Reinstatement | R14: MANAGED SERVICE PROVIDERS | S14: MSP | T14: LIMITED | U14: =IF(ISNUMBER(SEARCH("ADD-ON",$I14)),"ADD-ON","NOT AN ADD-ON") -> NOT AN ADD-ON | V14: =CONCATENATE(R14,S14,T14,U14) -> MANAGED SERVICE PROVIDERSMSPLIMITEDNOT AN ADD-ON
A15: Enterprise Asset Management | B15: MAXIMO | C15: MXS EAM | D15: 5724U18 | E15: IBM Maximo Asset Management | F15: Maximo Asset Management | G15: 3570 | H15: D04XWLL | I15: IBM MAXIMO ASSET MANAGEMENT MANAGED SERVICE PROVIDERS AUTHORIZED USER LICENSE + SW SUBSCRIPTION & SUPPORT 12 MONTHS | J15: D04XWLL | K15: Authorized User | L15: 5 | M15: =ROUND(IF(K15="Authorized User",L15/3,L15),2) -> 1.67 | N15: 15 | O15: 5 | P15: 3570 | Q15: License + S&S | R15: MANAGED SERVICE PROVIDERS | S15: MSP | T15: AUTHORIZED | U15: =IF(ISNUMBER(SEARCH("ADD-ON",$I15)),"ADD-ON","NOT AN ADD-ON") -> NOT AN ADD-ON | V15: =CONCATENATE(R15,S15,T15,U15) -> MANAGED SERVICE PROVIDERSMSPAUTHORIZEDNOT AN ADD-ON
A16: Enterprise Asset Management | B16: MAXIMO | C16: MXS EAM | D16: 5724U18 | E16: IBM Maximo Asset Management | F16: Maximo Asset Management | G16: 2140 | H16: D04XXLL | I16: IBM MAXIMO ASSET MANAGEMENT MANAGED SERVICE PROVIDERS AUTHORIZED USER SW SUBSCRIPTION & SUPPORT REINSTATEMENT 12 MONTHS | J16: D04XWLL | K16: Authorized User | L16: 5 | M16: =ROUND(IF(K16="Authorized User",L16/3,L16),2) -> 1.67 | N16: 15 | O16: 5 | P16: 3570 | Q16: Reinstatement | R16: MANAGED SERVICE PROVIDERS | S16: MSP | T16: AUTHORIZED | U16: =IF(ISNUMBER(SEARCH("ADD-ON",$I16)),"ADD-ON","NOT AN ADD-ON") -> NOT AN ADD-ON | V16: =CONCATENATE(R16,S16,T16,U16) -> MANAGED SERVICE PROVIDERSMSPAUTHORIZEDNOT AN ADD-ON
... A26: Enterprise Asset Management | B26: MAXIMO | C26: MXS EAM | D26: 5724U18 | E26: IBM Maximo Asset Management | F26: Maximo Asset Management | G26: 1070 | H26: D06FVLL | I26: IBM MAXIMO ASSET MANAGEMENT MANAGED SERVICE PROVIDERS LIMITED USE FOR LINUX ON SYSTEM Z AUTHORIZED USER SW SUBSCRIPTION & SUPPORT REINSTATEMENT 12 MONTHS | J26: D06FULL | K26: Authorized User | L26: 0 | M26: =ROUND(IF(K26="Authorized User",L26/3,L26),2) -> 0 | N26: 5 | O26: 1.6666667 | P26: 1780 | Q26: Reinstatement | R26: MANAGED SERVICE PROVIDERS | S26: MSP | T26: LIMITED | U26: =IF(ISNUMBER(SEARCH("ADD-ON",$I26)),"ADD-ON","NOT AN ADD-ON") -> NOT AN ADD-ON | V26: =CONCATENATE(R26,S26,T26,U26) -> MANAGED SERVICE PROVIDERSMSPLIMITEDNOT AN ADD-ON
A27: Enterprise Asset Management | B27: MAXIMO | C27: MXA CONFIG | D27: 5724U28 | E27: IBM Maximo Asset Configuration Manager | F27: Maximo Asset Configuration Manager | G27: 8980 | H27: D06GFLL | I27: IBM MAXIMO ASSET CONFIGURATION MANAGER FOR LINUX ON SYSTEM Z ASSET LICENSE + SW SUBSCRIPTION & SUPPORT 12 MONTHS | J27: D06GFLL | K27: Asset | L27: Manual Input required | M27: =ROUND(IF(K27="Authorized User",L27/3,L27),2) -> #VALUE! | N27: 15 | O27: 5 | P27: 8980 | Q27: License + S&S | R27: ASSET CONFIGURATION MANAGER | S27: ACM | T27: ASSET | U27: =IF(ISNUMBER(SEARCH("ADD-ON",$I27)),"ADD-ON","NOT AN ADD-ON") -> NOT AN ADD-ON | V27: =CONCATENATE(R27,S27,T27,U27) -> ASSET CONFIGURATION MANAGERACMASSETNOT AN ADD-ON
A28: Enterprise Asset Management | B28: MAXIMO | C28: MXA CONFIG | D28: 5724U28 | E28: IBM Maximo Asset Configuration Manager | F28: Maximo Asset Configuration Manager | G28: 5390 | H28: D06GGLL | I28: IBM MAXIMO ASSET CONFIGURATION MANAGER FOR LINUX ON SYSTEM Z ASSET SW SUBSCRIPTION & SUPPORT REINSTATEMENT 12 MONTHS | J28: D06GFLL | K28: Asset | L28: Manual Input required | M28: =ROUND(IF(K28="Authorized User",L28/3,L28),2) -> #VALUE! | N28: 15 | O28: 5 | P28: 8980 | Q28: Reinstatement | R28: ASSET CONFIGURATION MANAGER | S28: ACM | T28: ASSET | U28: =IF(ISNUMBER(SEARCH("ADD-ON",$I28)),"ADD-ON","NOT AN ADD-ON") -> NOT AN ADD-ON | V28: =CONCATENATE(R28,S28,T28,U28) -> ASSET CONFIGURATION MANAGERACMASSETNOT AN ADD-ON
A29: Enterprise Asset Management | B29: MAXIMO | C29: MXA CONFIG | D29: 5724U28 | E29: IBM Maximo Asset Configuration Manager | F29: Maximo Asset Configuration Manager | G29: 5740 | H29: D06GWLL | I29: IBM MAXIMO ASSET CONFIGURATION MANAGER FOR LINUX ON SYSTEM Z AUTHORIZED USER LICENSE + SW SUBSCRIPTION & SUPPORT 12 MONTHS | J29: D06GWLL | K29: Authorized User | L29: 15 | M29: =ROUND(IF(K29="Authorized User",L29/3,L29),2) -> 5 | N29: 15 | O29: 5 | P29: 5740 | Q29: License + S&S | R29: ASSET CONFIGURATION MANAGER | S29: ACM | T29: AUTHORIZED | U29: =IF(ISNUMBER(SEARCH("ADD-ON",$I29)),"ADD-ON","NOT AN ADD-ON") -> NOT AN ADD-ON | V29: =CONCATENATE(R29,S29,T29,U29) -> ASSET CONFIGURATION MANAGERACMAUTHORIZEDNOT AN ADD-ON
A30: Enterprise Asset Management | B30: MAXIMO | C30: MXA CONFIG | D30: 5724U28 | E30: IBM Maximo Asset Configuration Manager | F30: Maximo Asset Configuration Manager | G30: 3440 | H30: D06GXLL | I30: IBM MAXIMO ASSET CONFIGURATION MANAGER FOR LINUX ON SYSTEM Z AUTHORIZED USER SW SUBSCRIPTION & SUPPORT REINSTATEMENT 12 MONTHS | J30: D06GWLL | K30: Authorized User | L30: 15 | M30: =ROUND(IF(K30="Authorized User",L30/3,L30),2) -> 5 | N30: 15 | O30: 5 | P30: 5740 | Q30: Reinstatement | R30: ASSET CONFIGURATION MANAGER | S30: ACM | T30: AUTHORIZED | U30: =IF(ISNUMBER(SEARCH("ADD-ON",$I30)),"ADD-ON","NOT AN ADD-ON") -> NOT AN ADD-ON | V30: =CONCATENATE(R30,S30,T30,U30) -> ASSET CONFIGURATION MANAGERACMAUTHORIZEDNOT AN ADD-ON
A31: Enterprise Asset Management | B31: MAXIMO | C31: MX ENT ADP O | D31: 5724T00 | E31: IBM Maximo Enterprise Adapter | F31: Maximo Enterprise Adapter | G31: 161000 | H31: D06HTLL | I31: IBM MAXIMO ENTERPRISE ADAPTER FOR ORACLE APPLICATIONS FOR LINUX ON SYSTEM Z SERVER LICENSE + SW SUBSCRIPTION & SUPPORT 12 MONTHS | J31: D06HTLL | K31: Server | L31: 80 | M31: =ROUND(IF(K31="Authorized User",L31/3,L31),2) -> 80 | N31: 80 | O31: 1 | P31: 161000 | Q31: License + S&S | R31: ADAPTER FOR ORACLE | S31: ADAPTER | T31: ADAPTER | U31: =IF(ISNUMBER(SEARCH("ADD-ON",$I31)),"ADD-ON","NOT AN ADD-ON") -> NOT AN ADD-ON | V31: =CONCATENATE(R31,S31,T31,U31) -> ADAPTER FOR ORACLEADAPTERADAPTERNOT AN ADD-ON
A32: Enterprise Asset Management | B32: MAXIMO | C32: MX ENT ADP O | D32: 5724T00 | E32: IBM Maximo Enterprise Adapter | F32: Maximo Enterprise Adapter | G32: 96300 | H32: D06HULL | I32: IBM MAXIMO ENTERPRISE ADAPTER FOR ORACLE APPLICATIONS FOR LINUX ON SYSTEM Z SERVER SW SUBSCRIPTION & SUPPORT REINSTATEMENT 12 MONTHS | J32: D06HTLL | K32: Server | L32: 80 | M32: =ROUND(IF(K32="Authorized User",L32/3,L32),2) -> 80 | N32: 80 | O32: 1 | P32: 161000 | Q32: Reinstatement | R32: ADAPTER FOR ORACLE | S32: ADAPTER | T32: ADAPTER | U32: =IF(ISNUMBER(SEARCH("ADD-ON",$I32)),"ADD-ON","NOT AN ADD-ON") -> NOT AN ADD-ON | V32: =CONCATENATE(R32,S32,T32,U32) -> ADAPTER FOR ORACLEADAPTERADAPTERNOT AN ADD-ON
A33: Enterprise Asset Management | B33: MAXIMO | C33: MX ENT ADP | D33: 5724T00 | E33: IBM Maximo Enterprise Adapter | F33: Maximo Enterprise Adapter | G33: 161000 | H33: D06ITLL | I33: IBM MAXIMO ENTERPRISE ADAPTER FOR SAP APPLICATIONS FOR LINUX ON SYSTEM Z SERVER LICENSE + SW SUBSCRIPTION & SUPPORT 12 MONTHS | J33: D06ITLL | K33: Server | L33: 80 | M33: =ROUND(IF(K33="Authorized User",L33/3,L33),2) -> 80 | N33: 80 | O33: 1 | P33: 161000 | Q33: License + S&S | R33: ADAPTER FOR SAP | S33: ADAPTER | T33: ADAPTER | U33: =IF(ISNUMBER(SEARCH("ADD-ON",$I33)),"ADD-ON","NOT AN ADD-ON") -> NOT AN ADD-ON | V33: =CONCATENATE(R33,S33,T33,U33) -> ADAPTER FOR SAPADAPTERADAPTERNOT AN ADD-ON
A34: Enterprise Asset Management | B34: MAXIMO | C34: MX ENT ADP | D34: 5724T00 | E34: IBM Maximo Enterprise Adapter | F34: Maximo Enterprise Adapter | G34: 96300 | H34: D06IULL | I34: IBM MAXIMO ENTERPRISE ADAPTER FOR SAP APPLICATIONS FOR LINUX ON SYSTEM Z SERVER SW SUBSCRIPTION & SUPPORT REINSTATEMENT 12 MONTHS | J34: D06ITLL | K34: Server | L34: 80 | M34: =ROUND(IF(K34="Authorized User",L34/3,L34),2) -> 80 | N34: 80 | O34: 1 | P34: 161000 | Q34: Reinstatement | R34: ADAPTER FOR SAP | S34: ADAPTER | T34: ADAPTER | U34: =IF(ISNUMBER(SEARCH("ADD-ON",$I34)),"ADD-ON","NOT AN ADD-ON") -> NOT AN ADD-ON | V34: =CONCATENATE(R34,S34,T34,U34) -> ADAPTER FOR SAPADAPTERADAPTERNOT AN ADD-ON
A35: Enterprise Asset Management | B35: MAXIMO | C35: MXA CALIBRAT | D35: 5724U33 | E35: IBM Maximo Calibration | F35: Maximo Calibration | G35: 584 | H35: D06MBLL | I35: IBM MAXIMO CALIBRATION FOR LINUX ON SYSTEM Z AUTHORIZED USER LICENSE + SW SUBSCRIPTION & SUPPORT 12 MONTHS | J35: D06MBLL | K35: Authorized User | L35: 0 | M35: =ROUND(IF(K35="Authorized User",L35/3,L35),2) -> 0 | N35: 5 | O35: 1.67 | P35: 584 | Q35: License + S&S | R35: CALIBRATION | S35: ADD-ON | T35: AUTHORIZED | U35: =IF(ISNUMBER(SEARCH("ADD-ON",$I35)),"ADD-ON","NOT AN ADD-ON") -> NOT AN ADD-ON | V35: =CONCATENATE(R35,S35,T35,U35) -> CALIBRATIONADD-ONAUTHORIZEDNOT AN ADD-ON
A36: Enterprise Asset Management | B36: MAXIMO | C36: MXA CALIBRAT | D36: 5724U33 | E36: IBM Maximo Calibration | F36: Maximo Calibration | G36: 350 | H36: D06MCLL | I36: IBM MAXIMO CALIBRATION FOR LINUX ON SYSTEM Z AUTHORIZED USER SW SUBSCRIPTION & SUPPORT REINSTATEMENT 12 MONTHS | J36: D06MBLL | K36: Authorized User | L36: 0 | M36: =ROUND(IF(K36="Authorized User",L36/3,L36),2) -> 0 | N36: 5 | O36: 1.67 | P36: 584 | Q36: Reinstatement | R36: CALIBRATION | S36: ADD-ON | T36: AUTHORIZED | U36: =IF(ISNUMBER(SEARCH("ADD-ON",$I36)),"ADD-ON","NOT AN ADD-ON") -> NOT AN ADD-ON | V36: =CONCATENATE(R36,S36,T36,U36) -> CALIBRATIONADD-ONAUTHORIZEDNOT AN ADD-ON
A37: Enterprise Asset Management | B37: MAXIMO | C37: MXA SCHEDUL | D37: 5724U18 | E37: IBM Maximo Asset Management | F37: Maximo Asset Management | G37: 2020 | H37: D0AYULL | I37: IBM MAXIMO ASSET MANAGEMENT SCHEDULER AUTHORIZED USER LICENSE + SW SUBSCRIPTION & SUPPORT 12 MONTHS | J37: D0AYULL | K37: Authorized User | L37: 0 | M37: =ROUND(IF(K37="Authorized User",L37/3,L37),2) -> 0 | N37: 10 | O37: 3.3333333 | P37: 2020 | Q37: License + S&S | R37: SCHEDULER | S37: ADD-ON | T37: AUTHORIZED | U37: =IF(ISNUMBER(SEARCH("ADD-ON",$I37)),"ADD-ON","NOT AN ADD-ON") -> NOT AN ADD-ON | V37: =CONCATENATE(R37,S37,T37,U37) -> SCHEDULERADD-ONAUTHORIZEDNOT AN ADD-ON
A38: Enterprise Asset Management | B38: MAXIMO | C38: MXA SCHEDUL | D38: 5724U18 | E38: IBM Maximo Asset Management | F38: Maximo Asset Management | G38: 1190 | H38: D0AYVLL | I38: IBM MAXIMO ASSET MANAGEMENT SCHEDULER AUTHORIZED USER SW SUBSCRIPTION & SUPPORT REINSTATEMENT 12 MONTHS | J38: D0AYULL | K38: Authorized User | L38: 0 | M38: =ROUND(IF(K38="Authorized User",L38/3,L38),2) -> 0 | N38: 10 | O38: 3.3333333 | P38: 2020 | Q38: Reinstatement | R38: SCHEDULER | S38: ADD-ON | T38: AUTHORIZED | U38: =IF(ISNUMBER(SEARCH("ADD-ON",$I38)),"ADD-ON","NOT AN ADD-ON") -> NOT AN ADD-ON | V38: =CONCATENATE(R38,S38,T38,U38) -> SCHEDULERADD-ONAUTHORIZEDNOT AN ADD-ON
A39: Enterprise Asset Management | B39: MAXIMO | C39: MXA SCHEDUL | D39: 5724U18 | E39: IBM Maximo Asset Management | F39: Maximo Asset Management | G39: 2020 | H39: D0AYWLL | I39: IBM MAXIMO ASSET MANAGEMENT SCHEDULER FOR LINUX ON SYSTEM Z AUTHORIZED USER LICENSE + SW SUBSCRIPTION & SUPPORT 12 MONTHS | J39: D0AYWLL | K39: Authorized User | L39: 0 | M39: =ROUND(IF(K39="Authorized User",L39/3,L39),2) -> 0 | N39: 10 | O39: 3.3333333 | P39: 2020 | Q39: License + S&S | R39: SCHEDULER | S39: ADD-ON | T39: AUTHORIZED | U39: =IF(ISNUMBER(SEARCH("ADD-ON",$I39)),"ADD-ON","NOT AN ADD-ON") -> NOT AN ADD-ON | V39: =CONCATENATE(R39,S39,T39,U39) -> SCHEDULERADD-ONAUTHORIZEDNOT AN ADD-ON
A40: Enterprise Asset Management | B40: MAXIMO | C40: MXA SCHEDUL | D40: 5724U18 | E40: IBM Maximo Asset Management | F40: Maximo Asset Management | G40: 1190 | H40: D0AYXLL | I40: IBM MAXIMO ASSET MANAGEMENT SCHEDULER FOR LINUX ON SYSTEM Z AUTHORIZED USER SW SUBSCRIPTION & SUPPORT REINSTATEMENT 12 MONTHS | J40: D0AYWLL | K40: Authorized User | L40: 0 | M40: =ROUND(IF(K40="Authorized User",L40/3,L40),2) -> 0 | N40: 10 | O40: 3.3333333 | P40: 2020 | Q40: Reinstatement | R40: SCHEDULER | S40: ADD-ON | T40: AUTHORIZED | U40: =IF(ISNUMBER(SEARCH("ADD-ON",$I40)),"ADD-ON","NOT AN ADD-ON") -> NOT AN ADD-ON | V40: =CONCATENATE(R40,S40,T40,U40) -> SCHEDULERADD-ONAUTHORIZEDNOT AN ADD-ON
... A52: Enterprise Asset Management | B52: MAXIMO | C52: MXI NUCLEAR | D52: 5724U19 | E52: IBM Maximo for Nuclear Power | F52: Maximo for Nuclear Power | G52: 5470 | H52: D0GZ2LL | I52: IBM MAXIMO FOR NUCLEAR POWER AUTHORIZED USER FROM MAXIMO ASSET MANAGEMENT LIMITED USE AUTHORIZED USER TRADE UP LICENSE + SW SUBSCRIPTION & SUPPORT 12 MONTHS | J52: D0GYZLL | K52: Authorized User | L52: 15 | M52: =ROUND(IF(K52="Authorized User",L52/3,L52),2) -> 5 | N52: 15 | O52: 5 | P52: 7660 | Q52: Trade-Up | R52: NUCLEAR POWER | S52: INDUSTRY SOLUTION | T52: AUTHORIZED | U52: =IF(ISNUMBER(SEARCH("ADD-ON",$I52)),"ADD-ON","NOT AN ADD-ON") -> NOT AN ADD-ON | V52: =CONCATENATE(R52,S52,T52,U52) -> NUCLEAR POWERINDUSTRY SOLUTIONAUTHORIZEDNOT AN ADD-ON
A53: Enterprise Asset Management | B53: MAXIMO | C53: MXI NUCLEAR | D53: 5724U19 | E53: IBM Maximo for Nuclear Power | F53: Maximo for Nuclear Power | G53: 2150 | H53: D0GZ3LL | I53: IBM MAXIMO FOR NUCLEAR POWER ADD ON AUTHORIZED USER LICENSE + SW SUBSCRIPTION & SUPPORT 12 MONTHS | J53: D0GZ3LL | K53: Authorized User | L53: 5 | M53: =ROUND(IF(K53="Authorized User",L53/3,L53),2) -> 1.67 | N53: 15 | O53: 5 | P53: 2150 | Q53: License + S&S | R53: NUCLEAR POWER | S53: INDUSTRY SOLUTION | T53: AUTHORIZED | U53: ADD-ON | V53: =CONCATENATE(R53,S53,T53,U53) -> NUCLEAR POWERINDUSTRY SOLUTIONAUTHORIZEDADD-ON
A54: Enterprise Asset Management | B54: MAXIMO | C54: MXI NUCLEAR | D54: 5724U19 | E54: IBM Maximo for Nuclear Power | F54: Maximo for Nuclear Power | G54: 1300 | H54: D0GZ4LL | I54: IBM MAXIMO FOR NUCLEAR POWER ADD ON AUTHORIZED USER SW SUBSCRIPTION & SUPPORT REINSTATEMENT 12 MONTHS | J54: D0GZ3LL | K54: Authorized User | L54: 5 | M54: =ROUND(IF(K54="Authorized User",L54/3,L54),2) -> 1.67 | N54: 15 | O54: 5 | P54: 2150 | Q54: Reinstatement | R54: NUCLEAR POWER | S54: INDUSTRY SOLUTION | T54: AUTHORIZED | U54: ADD-ON | V54: =CONCATENATE(R54,S54,T54,U54) -> NUCLEAR POWERINDUSTRY SOLUTIONAUTHORIZEDADD-ON
A55: Enterprise Asset Management | B55: MAXIMO | C55: MXI NUCLEAR | D55: 5724U19 | E55: IBM Maximo for Nuclear Power | F55: Maximo for Nuclear Power | G55: 7660 | H55: D0GZ5LL | I55: IBM MAXIMO FOR NUCLEAR POWER FOR LINUX ON SYSTEM Z AUTHORIZED USER LICENSE + SW SUBSCRIPTION & SUPPORT 12 MONTHS | J55: D0GZ5LL | K55: Authorized User | L55: 15 | M55: =ROUND(IF(K55="Authorized User",L55/3,L55),2) -> 5 | N55: 15 | O55: 5 | P55: 7660 | Q55: License + S&S | R55: NUCLEAR POWER | S55: INDUSTRY SOLUTION | T55: AUTHORIZED | U55: =IF(ISNUMBER(SEARCH("ADD-ON",$I55)),"ADD-ON","NOT AN ADD-ON") -> NOT AN ADD-ON | V55: =CONCATENATE(R55,S55,T55,U55) -> NUCLEAR POWERINDUSTRY SOLUTIONAUTHORIZEDNOT AN ADD-ON
A56: Enterprise Asset Management | B56: MAXIMO | C56: MXI NUCLEAR | D56: 5724U19 | E56: IBM Maximo for Nuclear Power | F56: Maximo for Nuclear Power | G56: 4600 | H56: D0GZ6LL | I56: IBM MAXIMO FOR NUCLEAR POWER FOR LINUX ON SYSTEM Z AUTHORIZED USER SW SUBSCRIPTION & SUPPORT REINSTATEMENT 12 MONTHS | J56: D0GZ5LL | K56: Authorized User | L56: 15 | M56: =ROUND(IF(K56="Authorized User",L56/3,L56),2) -> 5 | N56: 15 | O56: 5 | P56: 7660 | Q56: Reinstatement | R56: NUCLEAR POWER | S56: INDUSTRY SOLUTION | T56: AUTHORIZED | U56: =IF(ISNUMBER(SEARCH("ADD-ON",$I56)),"ADD-ON","NOT AN ADD-ON") -> NOT AN ADD-ON | V56: =CONCATENATE(R56,S56,T56,U56) -> NUCLEAR POWERINDUSTRY SOLUTIONAUTHORIZEDNOT AN ADD-ON
A57: Enterprise Asset Management | B57: MAXIMO | C57: MXI NUCLEAR | D57: 5724U19 | E57: IBM Maximo for Nuclear Power | F57: Maximo for Nuclear Power | G57: 5470 | H57: D0GZ7LL | I57: IBM MAXIMO FOR NUCLEAR POWER FOR LINUX ON SYSTEM Z AUTHORIZED USER FROM MAXIMO ASSET MANAGEMENT LINUX ON SYSTEM Z LIMITED USE AUTHORIZED USER TRADE UP LICENSE + SW SUBSCRIPTION & SUPPORT 12 MONTHS | J57: D0GZ5LL | K57: Authorized User | L57: 15 | M57: =ROUND(IF(K57="Authorized User",L57/3,L57),2) -> 5 | N57: 15 | O57: 5 | P57: 7660 | Q57: Trade-Up | R57: NUCLEAR POWER | S57: INDUSTRY SOLUTION | T57: AUTHORIZED | U57: =IF(ISNUMBER(SEARCH("ADD-ON",$I57)),"ADD-ON","NOT AN ADD-ON") -> NOT AN ADD-ON | V57: =CONCATENATE(R57,S57,T57,U57) -> NUCLEAR POWERINDUSTRY SOLUTIONAUTHORIZEDNOT AN ADD-ON
A58: Enterprise Asset Management | B58: MAXIMO | C58: MXI NUCLEAR | D58: 5724U19 | E58: IBM Maximo for Nuclear Power | F58: Maximo for Nuclear Power | G58: 2680 | H58: D0GZ8LL | I58: IBM MAXIMO FOR NUCLEAR POWER FOR LINUX ON SYSTEM Z AUTHORIZED USER FROM MAXIMO ASSET MANAGEMENT LINUX ON SYSTEM Z AUTHORIZED USER TRADE UP LICENSE + SW SUBSCRIPTION & SUPPORT 12 MONTHS | J58: D0GZ5LL | K58: Authorized User | L58: 15 | M58: =ROUND(IF(K58="Authorized User",L58/3,L58),2) -> 5 | N58: 15 | O58: 5 | P58: 7660 | Q58: Trade-Up | R58: NUCLEAR POWER | S58: INDUSTRY SOLUTION | T58: AUTHORIZED | U58: =IF(ISNUMBER(SEARCH("ADD-ON",$I58)),"ADD-ON","NOT AN ADD-ON") -> NOT AN ADD-ON | V58: =CONCATENATE(R58,S58,T58,U58) -> NUCLEAR POWERINDUSTRY SOLUTIONAUTHORIZEDNOT AN ADD-ON
A59: Enterprise Asset Management | B59: MAXIMO | C59: MXI NUCLEAR | D59: 5724U19 | E59: IBM Maximo for Nuclear Power | F59: Maximo for Nuclear Power | G59: 2150 | H59: D0GZ9LL | I59: IBM MAXIMO FOR NUCLEAR POWER FOR LINUX ON SYSTEM Z ADD ON AUTHORIZED USER LICENSE + SW SUBSCRIPTION & SUPPORT 12 MONTHS | J59: D0GZ9LL | K59: Authorized User | L59: 5 | M59: =ROUND(IF(K59="Authorized User",L59/3,L59),2) -> 1.67 | N59: 15 | O59: 5 | P59: 2150 | Q59: License + S&S | R59: NUCLEAR POWER | S59: INDUSTRY SOLUTION | T59: AUTHORIZED | U59: ADD-ON | V59: =CONCATENATE(R59,S59,T59,U59) -> NUCLEAR POWERINDUSTRY SOLUTIONAUTHORIZEDADD-ON
A60: Enterprise Asset Management | B60: MAXIMO | C60: MXI NUCLEAR | D60: 5724U19 | E60: IBM Maximo for Nuclear Power | F60: Maximo for Nuclear Power | G60: 1300 | H60: D0GZALL | I60: IBM MAXIMO FOR NUCLEAR POWER FOR LINUX ON SYSTEM Z ADD ON AUTHORIZED USER SW SUBSCRIPTION & SUPPORT REINSTATEMENT 12 MONTHS | J60: D0GZ9LL | K60: Authorized User | L60: 5 | M60: =ROUND(IF(K60="Authorized User",L60/3,L60),2) -> 1.67 | N60: 15 | O60: 5 | P60: 2150 | Q60: Reinstatement | R60: NUCLEAR POWER | S60: INDUSTRY SOLUTION | T60: AUTHORIZED | U60: ADD-ON | V60: =CONCATENATE(R60,S60,T60,U60) -> NUCLEAR POWERINDUSTRY SOLUTIONAUTHORIZEDADD-ON
A61: Enterprise Asset Management | B61: MAXIMO | C61: MXI OILGAS | D61: 5724U20 | E61: IBM Maximo for Oil and Gas | F61: Maximo for Oil and Gas | G61: 7660 | H61: D0GZBLL | I61: IBM MAXIMO FOR OIL AND GAS AUTHORIZED USER LICENSE + SW SUBSCRIPTION & SUPPORT 12 MONTHS | J61: D0GZBLL | K61: Authorized User | L61: 15 | M61: =ROUND(IF(K61="Authorized User",L61/3,L61),2) -> 5 | N61: 15 | O61: 5 | P61: 7660 | Q61: License + S&S | R61: OIL AND GAS | S61: INDUSTRY SOLUTION | T61: AUTHORIZED | U61: =IF(ISNUMBER(SEARCH("ADD-ON",$I61)),"ADD-ON","NOT AN ADD-ON") -> NOT AN ADD-ON | V61: =CONCATENATE(R61,S61,T61,U61) -> OIL AND GASINDUSTRY SOLUTIONAUTHORIZEDNOT AN ADD-ON
A62: Enterprise Asset Management | B62: MAXIMO | C62: MXI OILGAS | D62: 5724U20 | E62: IBM Maximo for Oil and Gas | F62: Maximo for Oil and Gas | G62: 4600 | H62: D0GZCLL | I62: IBM MAXIMO FOR OIL AND GAS AUTHORIZED USER SW SUBSCRIPTION & SUPPORT REINSTATEMENT 12 MONTHS | J62: D0GZBLL | K62: Authorized User | L62: 15 | M62: =ROUND(IF(K62="Authorized User",L62/3,L62),2) -> 5 | N62: 15 | O62: 5 | P62: 7660 | Q62: Reinstatement | R62: OIL AND GAS | S62: INDUSTRY SOLUTION | T62: AUTHORIZED | U62: =IF(ISNUMBER(SEARCH("ADD-ON",$I62)),"ADD-ON","NOT AN ADD-ON") -> NOT AN ADD-ON | V62: =CONCATENATE(R62,S62,T62,U62) -> OIL AND GASINDUSTRY SOLUTIONAUTHORIZEDNOT AN ADD-ON
A63: Enterprise Asset Management | B63: MAXIMO | C63: MXI OILGAS | D63: 5724U20 | E63: IBM Maximo for Oil and Gas | F63: Maximo for Oil and Gas | G63: 5470 | H63: D0GZDLL | I63: IBM MAXIMO FOR OIL AND GAS AUTHORIZED USER FROM MAXIMO ASSET MANAGEMENT LIMITED USE AUTHORIZED USER TRADE UP LICENSE + SW SUBSCRIPTION & SUPPORT 12 MONTHS | J63: D0GZBLL | K63: Authorized User | L63: 15 | M63: =ROUND(IF(K63="Authorized User",L63/3,L63),2) -> 5 | N63: 15 | O63: 5 | P63: 7660 | Q63: Trade-Up | R63: OIL AND GAS | S63: INDUSTRY SOLUTION | T63: AUTHORIZED | U63: =IF(ISNUMBER(SEARCH("ADD-ON",$I63)),"ADD-ON","NOT AN ADD-ON") -> NOT AN ADD-ON | V63: =CONCATENATE(R63,S63,T63,U63) -> OIL AND GASINDUSTRY SOLUTIONAUTHORIZEDNOT AN ADD-ON
A64: Enterprise Asset Management | B64: MAXIMO | C64: MXI OILGAS | D64: 5724U20 | E64: IBM Maximo for Oil and Gas | F64: Maximo for Oil and Gas | G64: 2680 | H64: D0GZELL | I64: IBM MAXIMO FOR OIL AND GAS AUTHORIZED USER FROM MAXIMO ASSET MANAGEMENT AUTHORIZED USER TRADE UP LICENSE + SW SUBSCRIPTION & SUPPORT 12 MONTHS | J64: D0GZBLL | K64: Authorized User | L64: 15 | M64: =ROUND(IF(K64="Authorized User",L64/3,L64),2) -> 5 | N64: 15 | O64: 5 | P64: 7660 | Q64: Trade-Up | R64: OIL AND GAS | S64: INDUSTRY SOLUTION | T64: AUTHORIZED | U64: =IF(ISNUMBER(SEARCH("ADD-ON",$I64)),"ADD-ON","NOT AN ADD-ON") -> NOT AN ADD-ON | V64: =CONCATENATE(R64,S64,T64,U64) -> OIL AND GASINDUSTRY SOLUTIONAUTHORIZEDNOT AN ADD-ON
A65: Enterprise Asset Management | B65: MAXIMO | C65: MXI OILGAS | D65: 5724U20 | E65: IBM Maximo for Oil and Gas | F65: Maximo for Oil and Gas | G65: 2150 | H65: D0GZFLL | I65: IBM MAXIMO FOR OIL AND GAS ADD ON AUTHORIZED USER LICENSE + SW SUBSCRIPTION & SUPPORT 12 MONTHS | J65: D0GZFLL | K65: Authorized User | L65: 5 | M65: =ROUND(IF(K65="Authorized User",L65/3,L65),2) -> 1.67 | N65: 15 | O65: 5 | P65: 2150 | Q65: License + S&S | R65: OIL AND GAS | S65: INDUSTRY SOLUTION | T65: AUTHORIZED | U65: ADD-ON | V65: =CONCATENATE(R65,S65,T65,U65) -> OIL AND GASINDUSTRY SOLUTIONAUTHORIZEDADD-ON
A66: Enterprise Asset Management | B66: MAXIMO | C66: MXI OILGAS | D66: 5724U20 | E66: IBM Maximo for Oil and Gas | F66: Maximo for Oil and Gas | G66: 1300 | H66: D0GZGLL | I66: IBM MAXIMO FOR OIL AND GAS ADD ON AUTHORIZED USER SW SUBSCRIPTION & SUPPORT REINSTATEMENT 12 MONTHS | J66: D0GZFLL | K66: Authorized User | L66: 5 | M66: =ROUND(IF(K66="Authorized User",L66/3,L66),2) -> 1.67 | N66: 15 | O66: 5 | P66: 2150 | Q66: Reinstatement | R66: OIL AND GAS | S66: INDUSTRY SOLUTION | T66: AUTHORIZED | U66: ADD-ON | V66: =CONCATENATE(R66,S66,T66,U66) -> OIL AND GASINDUSTRY SOLUTIONAUTHORIZEDADD-ON
A67: Enterprise Asset Management | B67: MAXIMO | C67: MXI OILGAS | D67: 5724U20 | E67: IBM Maximo for Oil and Gas | F67: Maximo for Oil and Gas | G67: 7660 | H67: D0GZHLL | I67: IBM MAXIMO FOR OIL AND GAS FOR LINUX ON SYSTEM Z AUTHORIZED USER LICENSE + SW SUBSCRIPTION & SUPPORT 12 MONTHS | J67: D0GZHLL | K67: Authorized User | L67: 15 | M67: =ROUND(IF(K67="Authorized User",L67/3,L67),2) -> 5 | N67: 15 | O67: 5 | P67: 7660 | Q67: License + S&S | R67: OIL AND GAS | S67: INDUSTRY SOLUTION | T67: AUTHORIZED | U67: =IF(ISNUMBER(SEARCH("ADD-ON",$I67)),"ADD-ON","NOT AN ADD-ON") -> NOT AN ADD-ON | V67: =CONCATENATE(R67,S67,T67,U67) -> OIL AND GASINDUSTRY SOLUTIONAUTHORIZEDNOT AN ADD-ON
A68: Enterprise Asset Management | B68: MAXIMO | C68: MXI OILGAS | D68: 5724U20 | E68: IBM Maximo for Oil and Gas | F68: Maximo for Oil and Gas | G68: 4600 | H68: D0GZILL | I68: IBM MAXIMO FOR OIL AND GAS FOR LINUX ON SYSTEM Z AUTHORIZED USER SW SUBSCRIPTION & SUPPORT REINSTATEMENT 12 MONTHS | J68: D0GZHLL | K68: Authorized User | L68: 15 | M68: =ROUND(IF(K68="Authorized User",L68/3,L68),2) -> 5 | N68: 15 | O68: 5 | P68: 7660 | Q68: Reinstatement | R68: OIL AND GAS | S68: INDUSTRY SOLUTION | T68: AUTHORIZED | U68: =IF(ISNUMBER(SEARCH("ADD-ON",$I68)),"ADD-ON","NOT AN ADD-ON") -> NOT AN ADD-ON | V68: =CONCATENATE(R68,S68,T68,U68) -> OIL AND GASINDUSTRY SOLUTIONAUTHORIZEDNOT AN ADD-ON
A69: Enterprise Asset Management | B69: MAXIMO | C69: MXI OILGAS | D69: 5724U20 | E69: IBM Maximo for Oil and Gas | F69: Maximo for Oil and Gas | G69: 2680 | H69: D0GZJLL | I69: IBM MAXIMO FOR OIL AND GAS FOR LINUX ON SYSTEM Z AUTHORIZED USER FROM MAXIMO ASSET MANAGEMENT LINUX ON SYSTEM Z AUTHORIZED USER TRADE UP LICENSE + SW SUBSCRIPTION & SUPPORT 12 MONTHS | J69: D0GZLLL | K69: Authorized User | L69: 15 | M69: =ROUND(IF(K69="Authorized User",L69/3,L69),2) -> 5 | N69: 15 | O69: 5 | P69: 7660 | Q69: Trade-Up | R69: OIL AND GAS | S69: INDUSTRY SOLUTION | T69: AUTHORIZED | U69: =IF(ISNUMBER(SEARCH("ADD-ON",$I69)),"ADD-ON","NOT AN ADD-ON") -> NOT AN ADD-ON | V69: =CONCATENATE(R69,S69,T69,U69) -> OIL AND GASINDUSTRY SOLUTIONAUTHORIZEDNOT AN ADD-ON
A70: Enterprise Asset Management | B70: MAXIMO | C70: MXI OILGAS | D70: 5724U20 | E70: IBM Maximo for Oil and Gas | F70: Maximo for Oil and Gas | G70: 5470 | H70: D0GZKLL | I70: IBM MAXIMO FOR OIL AND GAS FOR LINUX ON SYSTEM Z AUTHORIZED USER FROM MAXIMO ASSET MANAGEMENT LINUX ON SYSTEM Z LIMITED USE AUTHORIZED USER TRADE UP LICENSE + SW SUBSCRIPTION & SUPPORT 12 MONTHS | J70: D0GZLLL | K70: Authorized User | L70: 15 | M70: =ROUND(IF(K70="Authorized User",L70/3,L70),2) -> 5 | N70: 15 | O70: 5 | P70: 7660 | Q70: Trade-Up | R70: OIL AND GAS | S70: INDUSTRY SOLUTION | T70: AUTHORIZED | U70: =IF(ISNUMBER(SEARCH("ADD-ON",$I70)),"ADD-ON","NOT AN ADD-ON") -> NOT AN ADD-ON | V70: =CONCATENATE(R70,S70,T70,U70) -> OIL AND GASINDUSTRY SOLUTIONAUTHORIZEDNOT AN ADD-ON
A71: Enterprise Asset Management | B71: MAXIMO | C71: MXI OILGAS | D71: 5724U20 | E71: IBM Maximo for Oil and Gas | F71: Maximo for Oil and Gas | G71: 2150 | H71: D0GZLLL | I71: IBM MAXIMO FOR OIL AND GAS FOR LINUX ON SYSTEM Z ADD ON AUTHORIZED USER LICENSE + SW SUBSCRIPTION & SUPPORT 12 MONTHS | J71: D0GZLLL | K71: Authorized User | L71: 5 | M71: =ROUND(IF(K71="Authorized User",L71/3,L71),2) -> 1.67 | N71: 15 | O71: 5 | P71: 2150 | Q71: License + S&S | R71: OIL AND GAS | S71: INDUSTRY SOLUTION | T71: AUTHORIZED | U71: ADD-ON | V71: =CONCATENATE(R71,S71,T71,U71) -> OIL AND GASINDUSTRY SOLUTIONAUTHORIZEDADD-ON
A72: Enterprise Asset Management | B72: MAXIMO | C72: MXI OILGAS | D72: 5724U20 | E72: IBM Maximo for Oil and Gas | F72: Maximo for Oil and Gas | G72: 1300 | H72: D0GZMLL | I72: IBM MAXIMO FOR OIL AND GAS FOR LINUX ON SYSTEM Z ADD ON AUTHORIZED USER SW SUBSCRIPTION & SUPPORT REINSTATEMENT 12 MONTHS | J72: D0GZLLL | K72: Authorized User | L72: 5 | M72: =ROUND(IF(K72="Authorized User",L72/3,L72),2) -> 1.67 | N72: 15 | O72: 5 | P72: 2150 | Q72: Reinstatement | R72: OIL AND GAS | S72: INDUSTRY SOLUTION | T72: AUTHORIZED | U72: ADD-ON | V72: =CONCATENATE(R72,S72,T72,U72) -> OIL AND GASINDUSTRY SOLUTIONAUTHORIZEDADD-ON
A73: Enterprise Asset Management | B73: MAXIMO | C73: MXI TRANSPRT | D73: 5724U21 | E73: IBM Maximo for Transportation | F73: Maximo for Transportation | G73: 7660 | H73: D0GZNLL | I73: IBM MAXIMO FOR TRANSPORTATION AUTHORIZED USER LICENSE + SW SUBSCRIPTION & SUPPORT 12 MONTHS | J73: D0GZNLL | K73: Authorized User | L73: 15 | M73: =ROUND(IF(K73="Authorized User",L73/3,L73),2) -> 5 | N73: 15 | O73: 5 | P73: 7660 | Q73: License + S&S | R73: TRANSPORATION | S73: INDUSTRY SOLUTION | T73: AUTHORIZED | U73: =IF(ISNUMBER(SEARCH("ADD-ON",$I73)),"ADD-ON","NOT AN ADD-ON") -> NOT AN ADD-ON | V73: =CONCATENATE(R73,S73,T73,U73) -> TRANSPORATIONINDUSTRY SOLUTIONAUTHORIZEDNOT AN ADD-ON
A74: Enterprise Asset Management | B74: MAXIMO | C74: MXI TRANSPRT | D74: 5724U21 | E74: IBM Maximo for Transportation | F74: Maximo for Transportation | G74: 4600 | H74: D0GZPLL | I74: IBM MAXIMO FOR TRANSPORTATION AUTHORIZED USER SW SUBSCRIPTION & SUPPORT REINSTATEMENT 12 MONTHS | J74: D0GZNLL | K74: Authorized User | L74: 15 | M74: =ROUND(IF(K74="Authorized User",L74/3,L74),2) -> 5 | N74: 15 | O74: 5 | P74: 7660 | Q74: Reinstatement | R74: TRANSPORATION | S74: INDUSTRY SOLUTION | T74: AUTHORIZED | U74: =IF(ISNUMBER(SEARCH("ADD-ON",$I74)),"ADD-ON","NOT AN ADD-ON") -> NOT AN ADD-ON | V74: =CONCATENATE(R74,S74,T74,U74) -> TRANSPORATIONINDUSTRY SOLUTIONAUTHORIZEDNOT AN ADD-ON
A75: Enterprise Asset Management | B75: MAXIMO | C75: MXI TRANSPRT | D75: 5724U21 | E75: IBM Maximo for Transportation | F75: Maximo for Transportation | G75: 2680 | H75: D0GZQLL | I75: IBM MAXIMO FOR TRANSPORTATION AUTHORIZED USER FROM MAXIMO ASSET MANAGEMENT AUTHORIZED USER TRADE UP LICENSE + SW SUBSCRIPTION & SUPPORT 12 MONTHS | J75: D0GZNLL | K75: Authorized User | L75: 15 | M75: =ROUND(IF(K75="Authorized User",L75/3,L75),2) -> 5 | N75: 15 | O75: 5 | P75: 7660 | Q75: Trade-Up | R75: TRANSPORATION | S75: INDUSTRY SOLUTION | T75: AUTHORIZED | U75: =IF(ISNUMBER(SEARCH("ADD-ON",$I75)),"ADD-ON","NOT AN ADD-ON") -> NOT AN ADD-ON | V75: =CONCATENATE(R75,S75,T75,U75) -> TRANSPORATIONINDUSTRY SOLUTIONAUTHORIZEDNOT AN ADD-ON
A76: Enterprise Asset Management | B76: MAXIMO | C76: MXI TRANSPRT | D76: 5724U21 | E76: IBM Maximo for Transportation | F76: Maximo for Transportation | G76: 5470 | H76: D0GZRLL | I76: IBM MAXIMO FOR TRANSPORTATION AUTHORIZED USER FROM MAXIMO ASSET MANAGEMENT LIMITED USE AUTHORIZED USER TRADE UP LICENSE + SW SUBSCRIPTION & SUPPORT 12 MONTHS | J76: D0GZNLL | K76: Authorized User | L76: 15 | M76: =ROUND(IF(K76="Authorized User",L76/3,L76),2) -> 5 | N76: 15 | O76: 5 | P76: 7660 | Q76: Trade-Up | R76: TRANSPORATION | S76: INDUSTRY SOLUTION | T76: AUTHORIZED | U76: =IF(ISNUMBER(SEARCH("ADD-ON",$I76)),"ADD-ON","NOT AN ADD-ON") -> NOT AN ADD-ON | V76: =CONCATENATE(R76,S76,T76,U76) -> TRANSPORATIONINDUSTRY SOLUTIONAUTHORIZEDNOT AN ADD-ON
A77: Enterprise Asset Management | B77: MAXIMO | C77: MXI TRANSPRT | D77: 5724U21 | E77: IBM Maximo for Transportation | F77: Maximo for Transportation | G77: 2150 | H77: D0GZSLL | I77: IBM MAXIMO FOR TRANSPORTATION ADD ON AUTHORIZED USER LICENSE + SW SUBSCRIPTION & SUPPORT 12 MONTHS | J77: D0GZSLL | K77: Authorized User | L77: 5 | M77: =ROUND(IF(K77="Authorized User",L77/3,L77),2) -> 1.67 | N77: 15 | O77: 5 | P77: 2150 | Q77: License + S&S | R77: TRANSPORATION | S77: INDUSTRY SOLUTION | T77: AUTHORIZED | U77: ADD-ON | V77: =CONCATENATE(R77,S77,T77,U77) -> TRANSPORATIONINDUSTRY SOLUTIONAUTHORIZEDADD-ON
A78: Enterprise Asset Management | B78: MAXIMO | C78: MXI TRANSPRT | D78: 5724U21 | E78: IBM Maximo for Transportation | F78: Maximo for Transportation | G78: 1300 | H78: D0GZTLL | I78: IBM MAXIMO FOR TRANSPORTATION ADD ON AUTHORIZED USER SW SUBSCRIPTION & SUPPORT REINSTATEMENT 12 MONTHS | J78: D0GZSLL | K78: Authorized User | L78: 5 | M78: =ROUND(IF(K78="Authorized User",L78/3,L78),2) -> 1.67 | N78: 15 | O78: 5 | P78: 2150 | Q78: Reinstatement | R78: TRANSPORATION | S78: INDUSTRY SOLUTION | T78: AUTHORIZED | U78: ADD-ON | V78: =CONCATENATE(R78,S78,T78,U78) -> TRANSPORATIONINDUSTRY SOLUTIONAUTHORIZEDADD-ON
A79: Enterprise Asset Management | B79: MAXIMO | C79: MXI TRANSPRT | D79: 5724U21 | E79: IBM Maximo for Transportation | F79: Maximo for Transportation | G79: 7660 | H79: D0GZULL | I79: IBM MAXIMO FOR TRANSPORTATION FOR LINUX ON SYSTEM Z AUTHORIZED USER LICENSE + SW SUBSCRIPTION & SUPPORT 12 MONTHS | J79: D0GZULL | K79: Authorized User | L79: 15 | M79: =ROUND(IF(K79="Authorized User",L79/3,L79),2) -> 5 | N79: 15 | O79: 5 | P79: 7660 | Q79: License + S&S | R79: TRANSPORATION | S79: INDUSTRY SOLUTION | T79: AUTHORIZED | U79: =IF(ISNUMBER(SEARCH("ADD-ON",$I79)),"ADD-ON","NOT AN ADD-ON") -> NOT AN ADD-ON | V79: =CONCATENATE(R79,S79,T79,U79) -> TRANSPORATIONINDUSTRY SOLUTIONAUTHORIZEDNOT AN ADD-ON
A80: Enterprise Asset Management | B80: MAXIMO | C80: MXI TRANSPRT | D80: 5724U21 | E80: IBM Maximo for Transportation | F80: Maximo for Transportation | G80: 4600 | H80: D0GZVLL | I80: IBM MAXIMO FOR TRANSPORTATION FOR LINUX ON SYSTEM Z AUTHORIZED USER SW SUBSCRIPTION & SUPPORT REINSTATEMENT 12 MONTHS | J80: D0GZULL | K80: Authorized User | L80: 15 | M80: =ROUND(IF(K80="Authorized User",L80/3,L80),2) -> 5 | N80: 15 | O80: 5 | P80: 7660 | Q80: Reinstatement | R80: TRANSPORATION | S80: INDUSTRY SOLUTION | T80: AUTHORIZED | U80: =IF(ISNUMBER(SEARCH("ADD-ON",$I80)),"ADD-ON","NOT AN ADD-ON") -> NOT AN ADD-ON | V80: =CONCATENATE(R80,S80,T80,U80) -> TRANSPORATIONINDUSTRY SOLUTIONAUTHORIZEDNOT AN ADD-ON
A81: Enterprise Asset Management | B81: MAXIMO | C81: MXI TRANSPRT | D81: 5724U21 | E81: IBM Maximo for Transportation | F81: Maximo for Transportation | G81: 2680 | H81: D0GZWLL | I81: IBM MAXIMO FOR TRANSPORTATION FOR LINUX ON SYSTEM Z AUTHORIZED USER FROM MAXIMO ASSET MANAGEMENT LINUX ON SYSTEM Z AUTHORIZED USER TRADE UP LICENSE + SW SUBSCRIPTION & SUPPORT 12 MONTHS | J81: D0GZULL | K81: Authorized User | L81: 15 | M81: =ROUND(IF(K81="Authorized User",L81/3,L81),2) -> 5 | N81: 15 | O81: 5 | P81: 7660 | Q81: Trade-Up | R81: TRANSPORATION | S81: INDUSTRY SOLUTION | T81: AUTHORIZED | U81: =IF(ISNUMBER(SEARCH("ADD-ON",$I81)),"ADD-ON","NOT AN ADD-ON") -> NOT AN ADD-ON | V81: =CONCATENATE(R81,S81,T81,U81) -> TRANSPORATIONINDUSTRY SOLUTIONAUTHORIZEDNOT AN ADD-ON
A82: Enterprise Asset Management | B82: MAXIMO | C82: MXI TRANSPRT | D82: 5724U21 | E82: IBM Maximo for Transportation | F82: Maximo for Transportation | G82: 5470 | H82: D0GZXLL | I82: IBM MAXIMO FOR TRANSPORTATION FOR LINUX ON SYSTEM Z AUTHORIZED USER FROM MAXIMO ASSET MANAGEMENT LINUX ON SYSTEM Z LIMITED USE AUTHORIZED USER TRADE UP LICENSE + SW SUBSCRIPTION & SUPPORT 12 MONTHS | J82: D0GZULL | K82: Authorized User | L82: 15 | M82: =ROUND(IF(K82="Authorized User",L82/3,L82),2) -> 5 | N82: 15 | O82: 5 | P82: 7660 | Q82: Trade-Up | R82: TRANSPORATION | S82: INDUSTRY SOLUTION | T82: AUTHORIZED | U82: =IF(ISNUMBER(SEARCH("ADD-ON",$I82)),"ADD-ON","NOT AN ADD-ON") -> NOT AN ADD-ON | V82: =CONCATENATE(R82,S82,T82,U82) -> TRANSPORATIONINDUSTRY SOLUTIONAUTHORIZEDNOT AN ADD-ON
A83: Enterprise Asset Management | B83: MAXIMO | C83: MXI TRANSPRT | D83: 5724U21 | E83: IBM Maximo for Transportation | F83: Maximo for Transportation | G83: 2150 | H83: D0GZYLL | I83: IBM MAXIMO FOR TRANSPORTATION FOR LINUX ON SYSTEM Z ADD ON AUTHORIZED USER LICENSE + SW SUBSCRIPTION & SUPPORT 12 MONTHS | J83: D0GZYLL | K83: Authorized User | L83: 5 | M83: =ROUND(IF(K83="Authorized User",L83/3,L83),2) -> 1.67 | N83: 15 | O83: 5 | P83: 2150 | Q83: License + S&S | R83: TRANSPORATION | S83: INDUSTRY SOLUTION | T83: AUTHORIZED | U83: ADD-ON | V83: =CONCATENATE(R83,S83,T83,U83) -> TRANSPORATIONINDUSTRY SOLUTIONAUTHORIZEDADD-ON
A84: Enterprise Asset Management | B84: MAXIMO | C84: MXI TRANSPRT | D84: 5724U21 | E84: IBM Maximo for Transportation | F84: Maximo for Transportation | G84: 1300 | H84: D0GZZLL | I84: IBM MAXIMO FOR TRANSPORTATION FOR LINUX ON SYSTEM Z ADD ON AUTHORIZED USER SW SUBSCRIPTION & SUPPORT REINSTATEMENT 12 MONTHS | J84: D0GZYLL | K84: Authorized User | L84: 5 | M84: =ROUND(IF(K84="Authorized User",L84/3,L84),2) -> 1.67 | N84: 15 | O84: 5 | P84: 2150 | Q84: Reinstatement | R84: TRANSPORATION | S84: INDUSTRY SOLUTION | T84: AUTHORIZED | U84: ADD-ON | V84: =CONCATENATE(R84,S84,T84,U84) -> TRANSPORATIONINDUSTRY SOLUTIONAUTHORIZEDADD-ON
A85: Enterprise Asset Management | B85: MAXIMO | C85: MXI UTILITY | D85: 5724U22 | E85: IBM Maximo for Utilities | F85: Maximo for Utilities | G85: 7660 | H85: D0H00LL | I85: IBM MAXIMO FOR UTILITIES AUTHORIZED USER LICENSE + SW SUBSCRIPTION & SUPPORT 12 MONTHS | J85: D0H00LL | K85: Authorized User | L85: 15 | M85: =ROUND(IF(K85="Authorized User",L85/3,L85),2) -> 5 | N85: 15 | O85: 5 | P85: 7660 | Q85: License + S&S | R85: UTILITIES | S85: INDUSTRY SOLUTION | T85: AUTHORIZED | U85: =IF(ISNUMBER(SEARCH("ADD-ON",$I85)),"ADD-ON","NOT AN ADD-ON") -> NOT AN ADD-ON | V85: =CONCATENATE(R85,S85,T85,U85) -> UTILITIESINDUSTRY SOLUTIONAUTHORIZEDNOT AN ADD-ON
A86: Enterprise Asset Management | B86: MAXIMO | C86: MXI UTILITY | D86: 5724U22 | E86: IBM Maximo for Utilities | F86: Maximo for Utilities | G86: 4600 | H86: D0H01LL | I86: IBM MAXIMO FOR UTILITIES AUTHORIZED USER SW SUBSCRIPTION & SUPPORT REINSTATEMENT 12 MONTHS | J86: D0H00LL | K86: Authorized User | L86: 15 | M86: =ROUND(IF(K86="Authorized User",L86/3,L86),2) -> 5 | N86: 15 | O86: 5 | P86: 7660 | Q86: Reinstatement | R86: UTILITIES | S86: INDUSTRY SOLUTION | T86: AUTHORIZED | U86: =IF(ISNUMBER(SEARCH("ADD-ON",$I86)),"ADD-ON","NOT AN ADD-ON") -> NOT AN ADD-ON | V86: =CONCATENATE(R86,S86,T86,U86) -> UTILITIESINDUSTRY SOLUTIONAUTHORIZEDNOT AN ADD-ON
A87: Enterprise Asset Management | B87: MAXIMO | C87: MXI UTILITY | D87: 5724U22 | E87: IBM Maximo for Utilities | F87: Maximo for Utilities | G87: 2680 | H87: D0H02LL | I87: IBM MAXIMO FOR UTILITIES AUTHORIZED USER FROM MAXIMO ASSET MANAGEMENT AUTHORIZED USER TRADE UP LICENSE + SW SUBSCRIPTION & SUPPORT 12 MONTHS | J87: D0H00LL | K87: Authorized User | L87: 15 | M87: =ROUND(IF(K87="Authorized User",L87/3,L87),2) -> 5 | N87: 15 | O87: 5 | P87: 7660 | Q87: Trade-Up | R87: UTILITIES | S87: INDUSTRY SOLUTION | T87: AUTHORIZED | U87: =IF(ISNUMBER(SEARCH("ADD-ON",$I87)),"ADD-ON","NOT AN ADD-ON") -> NOT AN ADD-ON | V87: =CONCATENATE(R87,S87,T87,U87) -> UTILITIESINDUSTRY SOLUTIONAUTHORIZEDNOT AN ADD-ON
A88: Enterprise Asset Management | B88: MAXIMO | C88: MXI UTILITY | D88: 5724U22 | E88: IBM Maximo for Utilities | F88: Maximo for Utilities | G88: 5470 | H88: D0H03LL | I88: IBM MAXIMO FOR UTILITIES AUTHORIZED USER FROM MAXIMO ASSET MANAGEMENT LIMITED USE AUTHORIZED USER TRADE UP LICENSE + SW SUBSCRIPTION & SUPPORT 12 MONTHS | J88: D0H00LL | K88: Authorized User | L88: 15 | M88: =ROUND(IF(K88="Authorized User",L88/3,L88),2) -> 5 | N88: 15 | O88: 5 | P88: 7660 | Q88: Trade-Up | R88: UTILITIES | S88: INDUSTRY SOLUTION | T88: AUTHORIZED | U88: =IF(ISNUMBER(SEARCH("ADD-ON",$I88)),"ADD-ON","NOT AN ADD-ON") -> NOT AN ADD-ON | V88: =CONCATENATE(R88,S88,T88,U88) -> UTILITIESINDUSTRY SOLUTIONAUTHORIZEDNOT AN ADD-ON
A89: Enterprise Asset Management | B89: MAXIMO | C89: MXI UTILITY | D89: 5724U22 | E89: IBM Maximo for Utilities | F89: Maximo for Utilities | G89: 2150 | H89: D0H04LL | I89: IBM MAXIMO FOR UTILITIES ADD ON AUTHORIZED USER LICENSE + SW SUBSCRIPTION & SUPPORT 12 MONTHS | J89: D0H04LL | K89: Authorized User | L89: 5 | M89: =ROUND(IF(K89="Authorized User",L89/3,L89),2) -> 1.67 | N89: 15 | O89: 5 | P89: 2150 | Q89: License + S&S | R89: UTILITIES | S89: INDUSTRY SOLUTION | T89: AUTHORIZED | U89: ADD-ON | V89: =CONCATENATE(R89,S89,T89,U89) -> UTILITIESINDUSTRY SOLUTIONAUTHORIZEDADD-ON
A90: Enterprise Asset Management | B90: MAXIMO | C90: MXI UTILITY | D90: 5724U22 | E90: IBM Maximo for Utilities | F90: Maximo for Utilities | G90: 1300 | H90: D0H05LL | I90: IBM MAXIMO FOR UTILITIES ADD ON AUTHORIZED USER SW SUBSCRIPTION & SUPPORT REINSTATEMENT 12 MONTHS | J90: D0H04LL | K90: Authorized User | L90: 5 | M90: =ROUND(IF(K90="Authorized User",L90/3,L90),2) -> 1.67 | N90: 15 | O90: 5 | P90: 2150 | Q90: Reinstatement | R90: UTILITIES | S90: INDUSTRY SOLUTION | T90: AUTHORIZED | U90: ADD-ON | V90: =CONCATENATE(R90,S90,T90,U90) -> UTILITIESINDUSTRY SOLUTIONAUTHORIZEDADD-ON
A91: Enterprise Asset Management | B91: MAXIMO | C91: MXI UTILITY | D91: 5724U22 | E91: IBM Maximo for Utilities | F91: Maximo for Utilities | G91: 7660 | H91: D0H06LL | I91: IBM MAXIMO FOR UTILITIES FOR LINUX ON SYSTEM Z AUTHORIZED USER LICENSE + SW SUBSCRIPTION & SUPPORT 12 MONTHS | J91: D0H06LL | K91: Authorized User | L91: 15 | M91: =ROUND(IF(K91="Authorized User",L91/3,L91),2) -> 5 | N91: 15 | O91: 5 | P91: 7660 | Q91: License + S&S | R91: UTILITIES | S91: INDUSTRY SOLUTION | T91: AUTHORIZED | U91: =IF(ISNUMBER(SEARCH("ADD-ON",$I91)),"ADD-ON","NOT AN ADD-ON") -> NOT AN ADD-ON | V91: =CONCATENATE(R91,S91,T91,U91) -> UTILITIESINDUSTRY SOLUTIONAUTHORIZEDNOT AN ADD-ON
A92: Enterprise Asset Management | B92: MAXIMO | C92: MXI UTILITY | D92: 5724U22 | E92: IBM Maximo for Utilities | F92: Maximo for Utilities | G92: 4600 | H92: D0H07LL | I92: IBM MAXIMO FOR UTILITIES FOR LINUX ON SYSTEM Z AUTHORIZED USER SW SUBSCRIPTION & SUPPORT REINSTATEMENT 12 MONTHS | J92: D0H06LL | K92: Authorized User | L92: 15 | M92: =ROUND(IF(K92="Authorized User",L92/3,L92),2) -> 5 | N92: 15 | O92: 5 | P92: 7660 | Q92: Reinstatement | R92: UTILITIES | S92: INDUSTRY SOLUTION | T92: AUTHORIZED | U92: =IF(ISNUMBER(SEARCH("ADD-ON",$I92)),"ADD-ON","NOT AN ADD-ON") -> NOT AN ADD-ON | V92: =CONCATENATE(R92,S92,T92,U92) -> UTILITIESINDUSTRY SOLUTIONAUTHORIZEDNOT AN ADD-ON
A93: Enterprise Asset Management | B93: MAXIMO | C93: MXI UTILITY | D93: 5724U22 | E93: IBM Maximo for Utilities | F93: Maximo for Utilities | G93: 5470 | H93: D0H08LL | I93: IBM MAXIMO FOR UTILITIES FOR LINUX ON SYSTEM Z AUTHORIZED USER FROM MAXIMO ASSET MANAGEMENT LINUX ON SYSTEM Z LIMITED USE AUTHORIZED USER TRADE UP LICENSE + SW SUBSCRIPTION & SUPPORT 12 MONTHS | J93: D0H06LL | K93: Authorized User | L93: 15 | M93: =ROUND(IF(K93="Authorized User",L93/3,L93),2) -> 5 | N93: 15 | O93: 5 | P93: 7660 | Q93: Trade-Up | R93: UTILITIES | S93: INDUSTRY SOLUTION | T93: AUTHORIZED | U93: =IF(ISNUMBER(SEARCH("ADD-ON",$I93)),"ADD-ON","NOT AN ADD-ON") -> NOT AN ADD-ON | V93: =CONCATENATE(R93,S93,T93,U93) -> UTILITIESINDUSTRY SOLUTIONAUTHORIZEDNOT AN ADD-ON
A94: Enterprise Asset Management | B94: MAXIMO | C94: MXI UTILITY | D94: 5724U22 | E94: IBM Maximo for Utilities | F94: Maximo for Utilities | G94: 2680 | H94: D0H09LL | I94: IBM MAXIMO FOR UTILITIES FOR LINUX ON SYSTEM Z AUTHORIZED USER FROM MAXIMO ASSET MANAGEMENT LINUX ON SYSTEM Z AUTHORIZED USER TRADE UP LICENSE + SW SUBSCRIPTION & SUPPORT 12 MONTHS | J94: D0H06LL | K94: Authorized User | L94: 15 | M94: =ROUND(IF(K94="Authorized User",L94/3,L94),2) -> 5 | N94: 15 | O94: 5 | P94: 7660 | Q94: Trade-Up | R94: UTILITIES | S94: INDUSTRY SOLUTION | T94: AUTHORIZED | U94: =IF(ISNUMBER(SEARCH("ADD-ON",$I94)),"ADD-ON","NOT AN ADD-ON") -> NOT AN ADD-ON | V94: =CONCATENATE(R94,S94,T94,U94) -> UTILITIESINDUSTRY SOLUTIONAUTHORIZEDNOT AN ADD-ON
A95: Enterprise Asset Management | B95: MAXIMO | C95: MXI UTILITY | D95: 5724U22 | E95: IBM Maximo for Utilities | F95: Maximo for Utilities | G95: 2150 | H95: D0H0ALL | I95: IBM MAXIMO FOR UTILITIES FOR LINUX ON SYSTEM Z ADD ON AUTHORIZED USER LICENSE + SW SUBSCRIPTION & SUPPORT 12 MONTHS | J95: D0H0ALL | K95: Authorized User | L95: 15 | M95: =ROUND(IF(K95="Authorized User",L95/3,L95),2) -> 5 | N95: 15 | O95: 5 | P95: 2150 | Q95: License + S&S | R95: UTILITIES | S95: INDUSTRY SOLUTION | T95: AUTHORIZED | U95: =IF(ISNUMBER(SEARCH("ADD-ON",$I95)),"ADD-ON","NOT AN ADD-ON") -> NOT AN ADD-ON | V95: =CONCATENATE(R95,S95,T95,U95) -> UTILITIESINDUSTRY SOLUTIONAUTHORIZEDNOT AN ADD-ON
A96: Enterprise Asset Management | B96: MAXIMO | C96: MXI UTILITY | D96: 5724U22 | E96: IBM Maximo for Utilities | F96: Maximo for Utilities | G96: 1300 | H96: D0H0BLL | I96: IBM MAXIMO FOR UTILITIES FOR LINUX ON SYSTEM Z ADD ON AUTHORIZED USER SW SUBSCRIPTION & SUPPORT REINSTATEMENT 12 MONTHS | J96: D0H0ALL | K96: Authorized User | L96: 15 | M96: =ROUND(IF(K96="Authorized User",L96/3,L96),2) -> 5 | N96: 15 | O96: 5 | P96: 2150 | Q96: Reinstatement | R96: UTILITIES | S96: INDUSTRY SOLUTION | T96: AUTHORIZED | U96: =IF(ISNUMBER(SEARCH("ADD-ON",$I96)),"ADD-ON","NOT AN ADD-ON") -> NOT AN ADD-ON | V96: =CONCATENATE(R96,S96,T96,U96) -> UTILITIESINDUSTRY SOLUTIONAUTHORIZEDNOT AN ADD-ON
A97: Enterprise Asset Management | B97: MAXIMO | C97: MXI LIFESCI | D97: 5724U23 | E97: IBM Maximo for Life Sciences | F97: Maximo for Life Science | G97: 6980 | H97: D0H0CLL | I97: IBM MAXIMO FOR LIFE SCIENCES AUTHORIZED USER LICENSE + SW SUBSCRIPTION & SUPPORT 12 MONTHS | J97: D0H0CLL | K97: Authorized User | L97: 10 | M97: =ROUND(IF(K97="Authorized User",L97/3,L97),2) -> 3.33 | N97: 5 | O97: 1.67 | P97: 6980 | Q97: License + S&S | R97: LIFE SCIENCES | S97: LIFE SCIENCES | T97: AUTHORIZED | U97: =IF(ISNUMBER(SEARCH("ADD-ON",$I97)),"ADD-ON","NOT AN ADD-ON") -> NOT AN ADD-ON | V97: =CONCATENATE(R97,S97,T97,U97) -> LIFE SCIENCESLIFE SCIENCESAUTHORIZEDNOT AN ADD-ON
A98: Enterprise Asset Management | B98: MAXIMO | C98: MXI LIFESCI | D98: 5724U23 | E98: IBM Maximo for Life Sciences | F98: Maximo for Life Science | G98: 4180 | H98: D0H0DLL | I98: IBM MAXIMO FOR LIFE SCIENCES AUTHORIZED USER SW SUBSCRIPTION & SUPPORT REINSTATEMENT 12 MONTHS | J98: D0H0CLL | K98: Authorized User | L98: 10 | M98: =ROUND(IF(K98="Authorized User",L98/3,L98),2) -> 3.33 | N98: 5 | O98: 1.67 | P98: 6980 | Q98: Reinstatement | R98: LIFE SCIENCES | S98: LIFE SCIENCES | T98: AUTHORIZED | U98: =IF(ISNUMBER(SEARCH("ADD-ON",$I98)),"ADD-ON","NOT AN ADD-ON") -> NOT AN ADD-ON | V98: =CONCATENATE(R98,S98,T98,U98) -> LIFE SCIENCESLIFE SCIENCESAUTHORIZEDNOT AN ADD-ON
A99: Enterprise Asset Management | B99: MAXIMO | C99: MXI LIFESCI | D99: 5724U23 | E99: IBM Maximo for Life Sciences | F99: Maximo for Life Science | G99: 4710 | H99: D0H0ELL | I99: IBM MAXIMO FOR LIFE SCIENCES AUTHORIZED USER FROM MAXIMO ASSET MANAGEMENT LIMITED USE AUTHORIZED USER TRADE UP LICENSE + SW SUBSCRIPTION & SUPPORT 12 MONTHS | J99: D0H0CLL | K99: Authorized User | L99: 10 | M99: =ROUND(IF(K99="Authorized User",L99/3,L99),2) -> 3.33 | N99: 5 | O99: 1.67 | P99: 6980 | Q99: Trade-Up | R99: LIFE SCIENCES | S99: LIFE SCIENCES | T99: AUTHORIZED | U99: =IF(ISNUMBER(SEARCH("ADD-ON",$I99)),"ADD-ON","NOT AN ADD-ON") -> NOT AN ADD-ON | V99: =CONCATENATE(R99,S99,T99,U99) -> LIFE SCIENCESLIFE SCIENCESAUTHORIZEDNOT AN ADD-ON
A100: Enterprise Asset Management | B100: MAXIMO | C100: MXI LIFESCI | D100: 5724U23 | E100: IBM Maximo for Life Sciences | F100: Maximo for Life Science | G100: 1920 | H100: D0H0FLL | I100: IBM MAXIMO FOR LIFE SCIENCES AUTHORIZED USER FROM MAXIMO ASSET MANAGEMENT AUTHORIZED USER TRADE UP LICENSE + SW SUBSCRIPTION & SUPPORT 12 MONTHS | J100: D0H0CLL | K100: Authorized User | L100: 10 | M100: =ROUND(IF(K100="Authorized User",L100/3,L100),2) -> 3.33 | N100: 5 | O100: 1.67 | P100: 6980 | Q100: Trade-Up | R100: LIFE SCIENCES | S100: LIFE SCIENCES | T100: AUTHORIZED | U100: =IF(ISNUMBER(SEARCH("ADD-ON",$I100)),"ADD-ON","NOT AN ADD-ON") -> NOT AN ADD-ON | V100: =CONCATENATE(R100,S100,T100,U100) -> LIFE SCIENCESLIFE SCIENCESAUTHORIZEDNOT AN ADD-ON
A101: Enterprise Asset Management | B101: MAXIMO | C101: MXI LIFESCI | D101: 5724U23 | E101: IBM Maximo for Life Sciences | F101: Maximo for Life Science | G101: 712 | H101: D0H0GLL | I101: IBM MAXIMO FOR LIFE SCIENCES ADD ON AUTHORIZED USER LICENSE + SW SUBSCRIPTION & SUPPORT 12 MONTHS | J101: D0H0GLL | K101: Authorized User | L101: 0 | M101: =ROUND(IF(K101="Authorized User",L101/3,L101),2) -> 0 | N101: 5 | O101: 1.67 | P101: 712 | Q101: License + S&S | R101: LIFE SCIENCES | S101: LIFE SCIENCES | T101: AUTHORIZED | U101: ADD-ON | V101: =CONCATENATE(R101,S101,T101,U101) -> LIFE SCIENCESLIFE SCIENCESAUTHORIZEDADD-ON
A102: Enterprise Asset Management | B102: MAXIMO | C102: MXI LIFESCI | D102: 5724U23 | E102: IBM Maximo for Life Sciences | F102: Maximo for Life Science | G102: 427 | H102: D0H0HLL | I102: IBM MAXIMO FOR LIFE SCIENCES ADD ON AUTHORIZED USER SW SUBSCRIPTION & SUPPORT REINSTATEMENT 12 MONTHS | J102: D0H0GLL | K102: Authorized User | L102: 0 | M102: =ROUND(IF(K102="Authorized User",L102/3,L102),2) -> 0 | N102: 5 | O102: 1.67 | P102: 712 | Q102: Reinstatement | R102: LIFE SCIENCES | S102: LIFE SCIENCES | T102: AUTHORIZED | U102: ADD-ON | V102: =CONCATENATE(R102,S102,T102,U102) -> LIFE SCIENCESLIFE SCIENCESAUTHORIZEDADD-ON
A103: Enterprise Asset Management | B103: MAXIMO | C103: MXI LIFESCI | D103: 5724U23 | E103: IBM Maximo for Life Sciences | F103: Maximo for Life Science | G103: 6980 | H103: D0H0ILL | I103: IBM MAXIMO FOR LIFE SCIENCES FOR LINUX ON SYSTEM Z AUTHORIZED USER LICENSE + SW SUBSCRIPTION & SUPPORT 12 MONTHS | J103: D0H0ILL | K103: Authorized User | L103: 10 | M103: =ROUND(IF(K103="Authorized User",L103/3,L103),2) -> 3.33 | N103: 5 | O103: 1.6666667 | P103: 6980 | Q103: License + S&S | R103: LIFE SCIENCES | S103: LIFE SCIENCES | T103: AUTHORIZED | U103: =IF(ISNUMBER(SEARCH("ADD-ON",$I103)),"ADD-ON","NOT AN ADD-ON") -> NOT AN ADD-ON | V103: =CONCATENATE(R103,S103,T103,U103) -> LIFE SCIENCESLIFE SCIENCESAUTHORIZEDNOT AN ADD-ON
A104: Enterprise Asset Management | B104: MAXIMO | C104: MXI LIFESCI | D104: 5724U23 | E104: IBM Maximo for Life Sciences | F104: Maximo for Life Science | G104: 4180 | H104: D0H0JLL | I104: IBM MAXIMO FOR LIFE SCIENCES FOR LINUX ON SYSTEM Z AUTHORIZED USER SW SUBSCRIPTION & SUPPORT REINSTATEMENT 12 MONTHS | J104: D0H0ILL | K104: Authorized User | L104: 10 | M104: =ROUND(IF(K104="Authorized User",L104/3,L104),2) -> 3.33 | N104: 5 | O104: 1.6666667 | P104: 6980 | Q104: Reinstatement | R104: LIFE SCIENCES | S104: LIFE SCIENCES | T104: AUTHORIZED | U104: =IF(ISNUMBER(SEARCH("ADD-ON",$I104)),"ADD-ON","NOT AN ADD-ON") -> NOT AN ADD-ON | V104: =CONCATENATE(R104,S104,T104,U104) -> LIFE SCIENCESLIFE SCIENCESAUTHORIZEDNOT AN ADD-ON
A105: Enterprise Asset Management | B105: MAXIMO | C105: MXI LIFESCI | D105: 5724U23 | E105: IBM Maximo for Life Sciences | F105: Maximo for Life Science | G105: 1920 | H105: D0H0KLL | I105: IBM MAXIMO FOR LIFE SCIENCES FOR LINUX ON SYSTEM Z AUTHORIZED USER FROM MAXIMO ASSET MANAGEMENT LINUX ON SYSTEM Z AUTHORIZED USER TRADE UP LICENSE + SW SUBSCRIPTION & SUPPORT 12 MONTHS | J105: D0H0MLL | K105: Authorized User | L105: 10 | M105: =ROUND(IF(K105="Authorized User",L105/3,L105),2) -> 3.33 | N105: 5 | O105: 1.6666667 | P105: 712 | Q105: Trade-Up | R105: LIFE SCIENCES | S105: LIFE SCIENCES | T105: AUTHORIZED | U105: =IF(ISNUMBER(SEARCH("ADD-ON",$I105)),"ADD-ON","NOT AN ADD-ON") -> NOT AN ADD-ON | V105: =CONCATENATE(R105,S105,T105,U105) -> LIFE SCIENCESLIFE SCIENCESAUTHORIZEDNOT AN ADD-ON
A106: Enterprise Asset Management | B106: MAXIMO | C106: MXI LIFESCI | D106: 5724U23 | E106: IBM Maximo for Life Sciences | F106: Maximo for Life Science | G106: 4710 | H106: D0H0LLL | I106: IBM MAXIMO FOR LIFE SCIENCES FOR LINUX ON SYSTEM Z AUTHORIZED USER FROM MAXIMO ASSET MANAGEMENT LINUX ON SYSTEM Z LIMITED USE AUTHORIZED USER TRADE UP LICENSE + SW SUBSCRIPTION & SUPPORT 12 MONTHS | J106: D0H0MLL | K106: Authorized User | L106: 10 | M106: =ROUND(IF(K106="Authorized User",L106/3,L106),2) -> 3.33 | N106: 5 | O106: 1.6666667 | P106: 712 | Q106: Trade-Up | R106: LIFE SCIENCES | S106: LIFE SCIENCES | T106: AUTHORIZED | U106: =IF(ISNUMBER(SEARCH("ADD-ON",$I106)),"ADD-ON","NOT AN ADD-ON") -> NOT AN ADD-ON | V106: =CONCATENATE(R106,S106,T106,U106) -> LIFE SCIENCESLIFE SCIENCESAUTHORIZEDNOT AN ADD-ON
A107: Enterprise Asset Management | B107: MAXIMO | C107: MXI LIFESCI | D107: 5724U23 | E107: IBM Maximo for Life Sciences | F107: Maximo for Life Science | G107: 712 | H107: D0H0MLL | I107: IBM MAXIMO FOR LIFE SCIENCES FOR LINUX ON SYSTEM Z ADD ON AUTHORIZED USER LICENSE + SW SUBSCRIPTION & SUPPORT 12 MONTHS | J107: D0H0MLL | K107: Authorized User | L107: 0 | M107: =ROUND(IF(K107="Authorized User",L107/3,L107),2) -> 0 | N107: 5 | O107: 1.6666667 | P107: 712 | Q107: License + S&S | R107: LIFE SCIENCES | S107: LIFE SCIENCES | T107: AUTHORIZED | U107: ADD-ON | V107: =CONCATENATE(R107,S107,T107,U107) -> LIFE SCIENCESLIFE SCIENCESAUTHORIZEDADD-ON
A108: Enterprise Asset Management | B108: MAXIMO | C108: MXI LIFESCI | D108: 5724U23 | E108: IBM Maximo for Life Sciences | F108: Maximo for Life Science | G108: 427 | H108: D0H0NLL | I108: IBM MAXIMO FOR LIFE SCIENCES FOR LINUX ON SYSTEM Z ADD ON AUTHORIZED USER SW SUBSCRIPTION & SUPPORT REINSTATEMENT 12 MONTHS | J108: D0H0MLL | K108: Authorized User | L108: 0 | M108: =ROUND(IF(K108="Authorized User",L108/3,L108),2) -> 0 | N108: 5 | O108: 1.6666667 | P108: 712 | Q108: Reinstatement | R108: LIFE SCIENCES | S108: LIFE SCIENCES | T108: AUTHORIZED | U108: ADD-ON | V108: =CONCATENATE(R108,S108,T108,U108) -> LIFE SCIENCESLIFE SCIENCESAUTHORIZEDADD-ON
A109: Enterprise Asset Management | B109: MAXIMO | C109: MXA SPACIAL | D109: 5724U36 | E109: IBM Maximo Spatial Asset Management | F109: Maximo Spatial Asset Management | G109: 35700 | H109: D0H19LL | I109: IBM MAXIMO SPATIAL ASSET MANAGEMENT INSTALL LICENSE + SW SUBSCRIPTION & SUPPORT 12 MONTHS | J109: D0H19LL | K109: Install | L109: 20 | M109: =ROUND(IF(K109="Authorized User",L109/3,L109),2) -> 20 | N109: 20 | O109: 1 | P109: 35700 | Q109: License + S&S | R109: SPATIAL | S109: ADD-ON | T109: INSTALL | U109: =IF(ISNUMBER(SEARCH("ADD-ON",$I109)),"ADD-ON","NOT AN ADD-ON") -> NOT AN ADD-ON | V109: =CONCATENATE(R109,S109,T109,U109) -> SPATIALADD-ONINSTALLNOT AN ADD-ON
A110: Enterprise Asset Management | B110: MAXIMO | C110: MXA SPACIAL | D110: 5724U36 | E110: IBM Maximo Spatial Asset Management | F110: Maximo Spatial Asset Management | G110: 21400 | H110: D0H1ALL | I110: IBM MAXIMO SPATIAL ASSET MANAGEMENT INSTALL SW SUBSCRIPTION & SUPPORT REINSTATEMENT 12 MONTHS | J110: D0H19LL | K110: Install | L110: 20 | M110: =ROUND(IF(K110="Authorized User",L110/3,L110),2) -> 20 | N110: 20 | O110: 1 | P110: 35700 | Q110: Reinstatement | R110: SPATIAL | S110: ADD-ON | T110: INSTALL | U110: =IF(ISNUMBER(SEARCH("ADD-ON",$I110)),"ADD-ON","NOT AN ADD-ON") -> NOT AN ADD-ON | V110: =CONCATENATE(R110,S110,T110,U110) -> SPATIALADD-ONINSTALLNOT AN ADD-ON
A111: Enterprise Asset Management | B111: MAXIMO | C111: MXA SPACIAL | D111: 5724U36 | E111: IBM Maximo Spatial Asset Management | F111: Maximo Spatial Asset Management | G111: 215 | H111: D0H1BLL | I111: IBM MAXIMO SPATIAL ASSET MANAGEMENT AUTHORIZED USER LICENSE + SW SUBSCRIPTION & SUPPORT 12 MONTHS | J111: D0H1BLL | K111: Authorized User | L111: 0 | M111: =ROUND(IF(K111="Authorized User",L111/3,L111),2) -> 0 | N111: 5 | O111: 1.6666667 | P111: 215 | Q111: License + S&S | R111: SPATIAL | S111: ADD-ON | T111: AUTHORIZED | U111: =IF(ISNUMBER(SEARCH("ADD-ON",$I111)),"ADD-ON","NOT AN ADD-ON") -> NOT AN ADD-ON | V111: =CONCATENATE(R111,S111,T111,U111) -> SPATIALADD-ONAUTHORIZEDNOT AN ADD-ON
A112: Enterprise Asset Management | B112: MAXIMO | C112: MXA SPACIAL | D112: 5724U36 | E112: IBM Maximo Spatial Asset Management | F112: Maximo Spatial Asset Management | G112: 130 | H112: D0H1CLL | I112: IBM MAXIMO SPATIAL ASSET MANAGEMENT AUTHORIZED USER SW SUBSCRIPTION & SUPPORT REINSTATEMENT 12 MONTHS | J112: D0H1BLL | K112: Authorized User | L112: 0 | M112: =ROUND(IF(K112="Authorized User",L112/3,L112),2) -> 0 | N112: 5 | O112: 1.6666667 | P112: 215 | Q112: Reinstatement | R112: SPATIAL | S112: ADD-ON | T112: AUTHORIZED | U112: =IF(ISNUMBER(SEARCH("ADD-ON",$I112)),"ADD-ON","NOT AN ADD-ON") -> NOT AN ADD-ON | V112: =CONCATENATE(R112,S112,T112,U112) -> SPATIALADD-ONAUTHORIZEDNOT AN ADD-ON
A113: Enterprise Asset Management | B113: MAXIMO | C113: MXA SPACIAL | D113: 5724U36 | E113: IBM Maximo Spatial Asset Management | F113: Maximo Spatial Asset Management | G113: 215 | H113: D0H1DLL | I113: IBM MAXIMO SPATIAL ASSET MANAGEMENT FOR LINUX ON SYSTEM Z AUTHORIZED USER LICENSE + SW SUBSCRIPTION & SUPPORT 12 MONTHS | J113: D0H1DLL | K113: Authorized User | L113: 0 | M113: =ROUND(IF(K113="Authorized User",L113/3,L113),2) -> 0 | N113: 5 | O113: 1.6666667 | P113: 215 | Q113: License + S&S | R113: SPATIAL | S113: ADD-ON | T113: AUTHORIZED | U113: =IF(ISNUMBER(SEARCH("ADD-ON",$I113)),"ADD-ON","NOT AN ADD-ON") -> NOT AN ADD-ON | V113: =CONCATENATE(R113,S113,T113,U113) -> SPATIALADD-ONAUTHORIZEDNOT AN ADD-ON
A114: Enterprise Asset Management | B114: MAXIMO | C114: MXA SPACIAL | D114: 5724U36 | E114: IBM Maximo Spatial Asset Management | F114: Maximo Spatial Asset Management | G114: 130 | H114: D0H1ELL | I114: IBM MAXIMO SPATIAL ASSET MANAGEMENT FOR LINUX ON SYSTEM Z AUTHORIZED USER SW SUBSCRIPTION & SUPPORT REINSTATEMENT 12 MONTHS | J114: D0H1DLL | K114: Authorized User | L114: 0 | M114: =ROUND(IF(K114="Authorized User",L114/3,L114),2) -> 0 | N114: 5 | O114: 1.6666667 | P114: 215 | Q114: Reinstatement | R114: SPATIAL | S114: ADD-ON | T114: AUTHORIZED | U114: =IF(ISNUMBER(SEARCH("ADD-ON",$I114)),"ADD-ON","NOT AN ADD-ON") -> NOT AN ADD-ON | V114: =CONCATENATE(R114,S114,T114,U114) -> SPATIALADD-ONAUTHORIZEDNOT AN ADD-ON
A115: Enterprise Asset Management | B115: MAXIMO | C115: MXA SPACIAL | D115: 5724U36 | E115: IBM Maximo Spatial Asset Management | F115: Maximo Spatial Asset Management | G115: 35700 | H115: D0H1FLL | I115: IBM MAXIMO SPATIAL ASSET MANAGEMENT FOR LINUX ON SYSTEM Z INSTALL LICENSE + SW SUBSCRIPTION & SUPPORT 12 MONTHS | J115: D0H1FLL | K115: Install | L115: 20 | M115: =ROUND(IF(K115="Authorized User",L115/3,L115),2) -> 20 | N115: 20 | O115: 1 | P115: 35700 | Q115: License + S&S | R115: SPATIAL | S115: ADD-ON | T115: INSTALL | U115: =IF(ISNUMBER(SEARCH("ADD-ON",$I115)),"ADD-ON","NOT AN ADD-ON") -> NOT AN ADD-ON | V115: =CONCATENATE(R115,S115,T115,U115) -> SPATIALADD-ONINSTALLNOT AN ADD-ON
A116: Enterprise Asset Management | B116: MAXIMO | C116: MXA SPACIAL | D116: 5724U36 | E116: IBM Maximo Spatial Asset Management | F116: Maximo Spatial Asset Management | G116: 21400 | H116: D0H1GLL | I116: IBM MAXIMO SPATIAL ASSET MANAGEMENT FOR LINUX ON SYSTEM Z INSTALL SW SUBSCRIPTION & SUPPORT REINSTATEMENT 12 MONTHS | J116: D0H1FLL | K116: Install | L116: 20 | M116: =ROUND(IF(K116="Authorized User",L116/3,L116),2) -> 20 | N116: 20 | O116: 1 | P116: 35700 | Q116: Reinstatement | R116: SPATIAL | S116: ADD-ON | T116: INSTALL | U116: =IF(ISNUMBER(SEARCH("ADD-ON",$I116)),"ADD-ON","NOT AN ADD-ON") -> NOT AN ADD-ON | V116: =CONCATENATE(R116,S116,T116,U116) -> SPATIALADD-ONINSTALLNOT AN ADD-ON
A117: Enterprise Asset Management | B117: MAXIMO | C117: MXA HSE | D117: 5724U18 | E117: IBM Maximo Asset Management | F117: Maximo Asset Management | G117: 2680 | H117: D0L7QLL | I117: IBM MAXIMO HEALTH,SAFETY AND ENVIRONMENT MANAGER AUTHORIZED USER FOR LINUX ON SYSTEM Z LICENSE + SW SUBSCRIPTION & SUPPORT 12 MONTHS | J117: D0L7QLL | K117: Authorized User | L117: 15 | M117: =ROUND(IF(K117="Authorized User",L117/3,L117),2) -> 5 | N117: 15 | O117: 5 | P117: 2680 | Q117: License + S&S | R117: HEALTH SAFETY AND ENVIRONMENT MANAGER | S117: HSE | T117: AUTHORIZED | U117: =IF(ISNUMBER(SEARCH("ADD-ON",$I117)),"ADD-ON","NOT AN ADD-ON") -> NOT AN ADD-ON | V117: =CONCATENATE(R117,S117,T117,U117) -> HEALTH SAFETY AND ENVIRONMENT MANAGERHSEAUTHORIZEDNOT AN ADD-ON
A118: Enterprise Asset Management | B118: MAXIMO | C118: MXA HSE | D118: 5724U18 | E118: IBM Maximo Asset Management | F118: Maximo Asset Management | G118: 1610 | H118: D0L7RLL | I118: IBM MAXIMO HEALTH,SAFETY AND ENVIRONMENT MANAGER AUTHORIZED USER FOR LINUX ON SYSTEM Z SW SUBSCRIPTION & SUPPORT REINSTATEMENT 12 MONTHS | J118: D0L7QLL | K118: Authorized User | L118: 15 | M118: =ROUND(IF(K118="Authorized User",L118/3,L118),2) -> 5 | N118: 15 | O118: 5 | P118: 2680 | Q118: Reinstatement | R118: HEALTH SAFETY AND ENVIRONMENT MANAGER | S118: HSE | T118: AUTHORIZED | U118: =IF(ISNUMBER(SEARCH("ADD-ON",$I118)),"ADD-ON","NOT AN ADD-ON") -> NOT AN ADD-ON | V118: =CONCATENATE(R118,S118,T118,U118) -> HEALTH SAFETY AND ENVIRONMENT MANAGERHSEAUTHORIZEDNOT AN ADD-ON
A119: Enterprise Asset Management | B119: MAXIMO | C119: MXA HSE | D119: 5724U18 | E119: IBM Maximo Asset Management | F119: Maximo Asset Management | G119: 2680 | H119: D0L7TLL | I119: IBM MAXIMO HEALTH,SAFETY AND ENVIRONMENT MANAGER AUTHORIZED USER LICENSE + SW SUBSCRIPTION & SUPPORT 12 MONTHS | J119: D0L7TLL | K119: Authorized User | L119: 15 | M119: =ROUND(IF(K119="Authorized User",L119/3,L119),2) -> 5 | N119: 15 | O119: 5 | P119: 2680 | Q119: License + S&S | R119: HEALTH SAFETY AND ENVIRONMENT MANAGER | S119: HSE | T119: AUTHORIZED | U119: =IF(ISNUMBER(SEARCH("ADD-ON",$I119)),"ADD-ON","NOT AN ADD-ON") -> NOT AN ADD-ON | V119: =CONCATENATE(R119,S119,T119,U119) -> HEALTH SAFETY AND ENVIRONMENT MANAGERHSEAUTHORIZEDNOT AN ADD-ON
A120: Enterprise Asset Management | B120: MAXIMO | C120: MXA HSE | D120: 5724U18 | E120: IBM Maximo Asset Management | F120: Maximo Asset Management | G120: 1610 | H120: D0L7ULL | I120: IBM MAXIMO HEALTH,SAFETY AND ENVIRONMENT MANAGER AUTHORIZED USER SW SUBSCRIPTION & SUPPORT REINSTATEMENT 12 MONTHS | J120: D0L7TLL | K120: Authorized User | L120: 15 | M120: =ROUND(IF(K120="Authorized User",L120/3,L120),2) -> 5 | N120: 15 | O120: 5 | P120: 2680 | Q120: Reinstatement | R120: HEALTH SAFETY AND ENVIRONMENT MANAGER | S120: HSE | T120: AUTHORIZED | U120: =IF(ISNUMBER(SEARCH("ADD-ON",$I120)),"ADD-ON","NOT AN ADD-ON") -> NOT AN ADD-ON | V120: =CONCATENATE(R120,S120,T120,U120) -> HEALTH SAFETY AND ENVIRONMENT MANAGERHSEAUTHORIZEDNOT AN ADD-ON
... A168: Enterprise Asset Management | B168: MAXIMO | C168: MXI LIFESCI | D168: 5724U23 | E168: IBM Maximo for Life Sciences | F168: Maximo for Life Science | G168: 4470 | H168: D0T13LL | I168: IBM MAXIMO FOR LIFE SCIENCES FOR LINUX ON SYSTEM Z AUTHORIZED USER FROM MAXIMO FOR LIFE SCIENCES LIMITED USE FOR LINUX ON SYSTEM Z AUTHORIZED USER TRADE UP LICENCE + SW SUBSCRIPTION & SUPPORT 12 MONTHS | J168: D0H0MLL | K168: Authorized User | L168: 10 | M168: =ROUND(IF(K168="Authorized User",L168/3,L168),2) -> 3.33 | N168: 5 | O168: 1.6666667 | P168: 712 | Q168: Trade-Up | R168: LIFE SCIENCES | S168: LIFE SCIENCES | T168: AUTHORIZED | U168: =IF(ISNUMBER(SEARCH("ADD-ON",$I168)),"ADD-ON","NOT AN ADD-ON") -> NOT AN ADD-ON | V168: =CONCATENATE(R168,S168,T168,U168) -> LIFE SCIENCESLIFE SCIENCESAUTHORIZEDNOT AN ADD-ON
...

Sheet Upgrade Parts Future_K_v4.1
A2: UT_LEVEL_CODE_30_DSCR | B2: IBM_SW_PILLAR_CODE | C2: IBM_SW_FAM_CODE | D2: IBM_PROD_ID | E2: IBM_PROD_ID_DSCR | F2: WWIDE_PROD_CODE_DSCR | G2: Eligible Part List Price | H2: Eligible Part # | I2: Eligible Part Description | J2: Eligible Part Parent Lic + S&S Part # | K2: CU_DSCR | L2: AppPoint for upgrade | M2: Upgrade Price Metric Conversion | N2: MAS AppPoint (Ltd, Base, Prm) | O2: Price Metric Conversion | P2: Parent Lic + S&S Part # US List Price | Q2: Part Type | R2: Offering name | S2: Core/IS/Add-ons/Anywhere | T2: AUTHORIZED | U2: Add-on Parts
A3: Enterprise Asset Management | B3: MAXIMO | C3: MXA ANYWHERE | D3: 5725M39 | E3: IBM Maximo Anywhere | F3: Maximo Anywhere | G3: 280 | H3: E0K39LL | I3: IBM MAXIMO ANYWHERE ADD-ON AUTHORIZED USER ANNUAL SW SUBSCRIPTION & SUPPORT RENEWAL | J3: D17CCLL | K3: Authorized User | L3: 0 | M3: =ROUND(IF(K3="Authorized User",L3/3,L3),2) -> 0 | N3: 5 | O3: =N3/3 -> 1.6666667 | P3: 1400 | Q3: Renewal | R3: ANYWHERE | S3: ANYWHERE | T3: AUTHORIZED | U3: =IF(ISNUMBER(SEARCH("ADD-ON",$I3)),"ADD-ON","NOT AN ADD-ON") -> ADD-ON | V3: =CONCATENATE(R3,S3,T3,U3) -> ANYWHEREANYWHEREAUTHORIZEDADD-ON
A4: Enterprise Asset Management | B4: MAXIMO | C4: MXA ANYWHERE | D4: 5725M39 | E4: IBM Maximo Anywhere | F4: Maximo Anywhere | G4: 1400 | H4: D17CCLL | I4: IBM MAXIMO ANYWHERE ADD-ON AUTHORIZED USER LICENSE + SW SUBSCRIPTION & SUPPORT 12 MONTHS | J4: D17CCLL | K4: Authorized User | L4: 0 | M4: =ROUND(IF(K4="Authorized User",L4/3,L4),2) -> 0 | N4: 5 | O4: =N4/3 -> 1.6666667 | P4: 1400 | Q4: License + S&S | R4: ANYWHERE | S4: ANYWHERE | T4: AUTHORIZED | U4: =IF(ISNUMBER(SEARCH("ADD-ON",$I4)),"ADD-ON","NOT AN ADD-ON") -> ADD-ON | V4: =CONCATENATE(R4,S4,T4,U4) -> ANYWHEREANYWHEREAUTHORIZEDADD-ON
A5: Enterprise Asset Management | B5: MAXIMO | C5: MXA ANYWHERE | D5: 5725M39 | E5: IBM Maximo Anywhere | F5: Maximo Anywhere | G5: 839 | H5: D17CDLL | I5: IBM MAXIMO ANYWHERE ADD-ON AUTHORIZED USER SW SUBSCRIPTION & SUPPORT REINSTATEMENT 12 MONTHS | J5: D17CCLL | K5: Authorized User | L5: 0 | M5: =ROUND(IF(K5="Authorized User",L5/3,L5),2) -> 0 | N5: 5 | O5: =N5/3 -> 1.6666667 | P5: 1400 | Q5: Reinstatement | R5: ANYWHERE | S5: ANYWHERE | T5: AUTHORIZED | U5: =IF(ISNUMBER(SEARCH("ADD-ON",$I5)),"ADD-ON","NOT AN ADD-ON") -> ADD-ON | V5: =CONCATENATE(R5,S5,T5,U5) -> ANYWHEREANYWHEREAUTHORIZEDADD-ON
A6: Enterprise Asset Management | B6: MAXIMO | C6: MXA ANYWHERE | D6: 5725M39 | E6: IBM Maximo Anywhere | F6: Maximo Anywhere | G6: 852 | H6: E0N3QLL | I6: IBM MAXIMO ANYWHERE ADD-ON CONCURRENT USER ANNUAL SW SUBSCRIPTION & SUPPORT RENEWAL 12 MONTHS | J6: D1QBGLL | K6: Concurrent User | L6: 0 | M6: =ROUND(IF(K6="Authorized User",L6/3,L6),2) -> 0 | N6: 5 | O6: 1 | P6: 4260 | Q6: Renewal | R6: ANYWHERE | S6: ANYWHERE | T6: AUTHORIZED | U6: =IF(ISNUMBER(SEARCH("ADD-ON",$I6)),"ADD-ON","NOT AN ADD-ON") -> ADD-ON | V6: =CONCATENATE(R6,S6,T6,U6) -> ANYWHEREANYWHEREAUTHORIZEDADD-ON
A7: Enterprise Asset Management | B7: MAXIMO | C7: MXA ANYWHERE | D7: 5725M39 | E7: IBM Maximo Anywhere | F7: Maximo Anywhere | G7: 4260 | H7: D1QBGLL | I7: IBM MAXIMO ANYWHERE ADD-ON CONCURRENT USER LICENSE + SW SUBSCRIPTION & SUPPORT 12 MONTHS | J7: D1QBGLL | K7: Concurrent User | L7: 0 | M7: =ROUND(IF(K7="Authorized User",L7/3,L7),2) -> 0 | N7: 5 | O7: 1 | P7: 4260 | Q7: License + S&S | R7: ANYWHERE | S7: ANYWHERE | T7: AUTHORIZED | U7: =IF(ISNUMBER(SEARCH("ADD-ON",$I7)),"ADD-ON","NOT AN ADD-ON") -> ADD-ON | V7: =CONCATENATE(R7,S7,T7,U7) -> ANYWHEREANYWHEREAUTHORIZEDADD-ON
A8: Enterprise Asset Management | B8: MAXIMO | C8: MXA ANYWHERE | D8: 5725M39 | E8: IBM Maximo Anywhere | F8: Maximo Anywhere | G8: 2550 | H8: D1QBHLL | I8: IBM MAXIMO ANYWHERE ADD-ON CONCURRENT USER SW SUBSCRIPTION & SUPPORT REINSTATEMENT 12 MONTHS | J8: D1QBGLL | K8: Concurrent User | L8: 0 | M8: =ROUND(IF(K8="Authorized User",L8/3,L8),2) -> 0 | N8: 5 | O8: 1 | P8: 4260 | Q8: Reinstatement | R8: ANYWHERE | S8: ANYWHERE | T8: AUTHORIZED | U8: =IF(ISNUMBER(SEARCH("ADD-ON",$I8)),"ADD-ON","NOT AN ADD-ON") -> ADD-ON | V8: =CONCATENATE(R8,S8,T8,U8) -> ANYWHEREANYWHEREAUTHORIZEDADD-ON
A9: Enterprise Asset Management | B9: MAXIMO | C9: MXA ANYWHERE | D9: 5725M39 | E9: IBM Maximo Anywhere | F9: Maximo Anywhere | G9: 918 | H9: D1QBMLL | I9: IBM MAXIMO ANYWHERE ADD-ON CONCURRENT USER LINUX ON Z SYSTEM TRADE UP FROM 3 MAXIMO ANYWHERE ADD-ON AUTHORIZED USER ON Z SYSTEM + SW SUBSCRIPTION & SUPPORT 12 MONTHS | J9: D1QBKLL | K9: Concurrent User | L9: 0 | M9: =ROUND(IF(K9="Authorized User",L9/3,L9),2) -> 0 | N9: 5 | O9: 1 | P9: 4260 | Q9: Trade-Up | R9: ANYWHERE | S9: ANYWHERE | T9: AUTHORIZED | U9: =IF(ISNUMBER(SEARCH("ADD-ON",$I9)),"ADD-ON","NOT AN ADD-ON") -> ADD-ON | V9: =CONCATENATE(R9,S9,T9,U9) -> ANYWHEREANYWHEREAUTHORIZEDADD-ON
A10: Enterprise Asset Management | B10: MAXIMO | C10: MXA ANYWHERE | D10: 5725M39 | E10: IBM Maximo Anywhere | F10: Maximo Anywhere | G10: 852 | H10: E0N3RLL | I10: IBM MAXIMO ANYWHERE ADD-ON CONCURRENT USER LINUX Z SYSTEM ANNUAL SW SUBSCRIPTION & SUPPORT RENEWAL | J10: D1QBKLL | K10: Concurrent User | L10: 0 | M10: =ROUND(IF(K10="Authorized User",L10/3,L10),2) -> 0 | N10: 5 | O10: 1 | P10: 4260 | Q10: Renewal | R10: ANYWHERE | S10: ANYWHERE | T10: AUTHORIZED | U10: =IF(ISNUMBER(SEARCH("ADD-ON",$I10)),"ADD-ON","NOT AN ADD-ON") -> ADD-ON | V10: =CONCATENATE(R10,S10,T10,U10) -> ANYWHEREANYWHEREAUTHORIZEDADD-ON
A11: Enterprise Asset Management | B11: MAXIMO | C11: MXA ANYWHERE | D11: 5725M39 | E11: IBM Maximo Anywhere | F11: Maximo Anywhere | G11: 4260 | H11: D1QBKLL | I11: IBM MAXIMO ANYWHERE ADD-ON CONCURRENT USER LINUX Z SYSTEM SW SUBSCRIPTION & SUPPORT 12 MONTHS | J11: D1QBKLL | K11: Concurrent User | L11: 0 | M11: =ROUND(IF(K11="Authorized User",L11/3,L11),2) -> 0 | N11: 5 | O11: 1 | P11: 4260 | Q11: License + S&S | R11: ANYWHERE | S11: ANYWHERE | T11: AUTHORIZED | U11: =IF(ISNUMBER(SEARCH("ADD-ON",$I11)),"ADD-ON","NOT AN ADD-ON") -> ADD-ON | V11: =CONCATENATE(R11,S11,T11,U11) -> ANYWHEREANYWHEREAUTHORIZEDADD-ON
A12: Enterprise Asset Management | B12: MAXIMO | C12: MXA ANYWHERE | D12: 5725M39 | E12: IBM Maximo Anywhere | F12: Maximo Anywhere | G12: 2550 | H12: D1QBLLL | I12: IBM MAXIMO ANYWHERE ADD-ON CONCURRENT USER LINUX Z SYSTEM SW SUBSCRIPTION & SUPPORT REINSTATEMENT 12 MONTHS | J12: D1QBKLL | K12: Concurrent User | L12: 0 | M12: =ROUND(IF(K12="Authorized User",L12/3,L12),2) -> 0 | N12: 5 | O12: 1 | P12: 4260 | Q12: Reinstatement | R12: ANYWHERE | S12: ANYWHERE | T12: AUTHORIZED | U12: =IF(ISNUMBER(SEARCH("ADD-ON",$I12)),"ADD-ON","NOT AN ADD-ON") -> ADD-ON | V12: =CONCATENATE(R12,S12,T12,U12) -> ANYWHEREANYWHEREAUTHORIZEDADD-ON
A13: Enterprise Asset Management | B13: MAXIMO | C13: MXA ANYWHERE | D13: 5725M39 | E13: IBM Maximo Anywhere | F13: Maximo Anywhere | G13: 918 | H13: D1QBILL | I13: IBM MAXIMO ANYWHERE ADD-ON CONCURRENT USER TRADE UP FROM 3 MAXIMO ANYWHERE ADD-ON AUTHORIZED USER + SW SUBSCRIPTION & SUPPORT 12 MONTHS | J13: D1QBGLL | K13: Concurrent User | L13: 0 | M13: =ROUND(IF(K13="Authorized User",L13/3,L13),2) -> 0 | N13: 5 | O13: 1 | P13: 4260 | Q13: Trade-Up | R13: ANYWHERE | S13: ANYWHERE | T13: AUTHORIZED | U13: =IF(ISNUMBER(SEARCH("ADD-ON",$I13)),"ADD-ON","NOT AN ADD-ON") -> ADD-ON | V13: =CONCATENATE(R13,S13,T13,U13) -> ANYWHEREANYWHEREAUTHORIZEDADD-ON
A14: Enterprise Asset Management | B14: MAXIMO | C14: MXA ANYWHERE | D14: 5725M39 | E14: IBM Maximo Anywhere | F14: Maximo Anywhere | G14: 280 | H14: E0K3ALL | I14: IBM MAXIMO ANYWHERE ADD-ON FOR LINUX ON SYSTEM Z AUTHORIZED USER ANNUAL SW SUBSCRIPTION & SUPPORT RENEWAL | J14: D17CELL | K14: Authorized User | L14: 0 | M14: =ROUND(IF(K14="Authorized User",L14/3,L14),2) -> 0 | N14: 5 | O14: =N14/3 -> 1.6666667 | P14: 1400 | Q14: Renewal | R14: ANYWHERE | S14: ANYWHERE | T14: AUTHORIZED | U14: =IF(ISNUMBER(SEARCH("ADD-ON",$I14)),"ADD-ON","NOT AN ADD-ON") -> ADD-ON | V14: =CONCATENATE(R14,S14,T14,U14) -> ANYWHEREANYWHEREAUTHORIZEDADD-ON
A15: Enterprise Asset Management | B15: MAXIMO | C15: MXA ANYWHERE | D15: 5725M39 | E15: IBM Maximo Anywhere | F15: Maximo Anywhere | G15: 1400 | H15: D17CELL | I15: IBM MAXIMO ANYWHERE ADD-ON FOR LINUX ON SYSTEM Z AUTHORIZED USER LICENSE + SW SUBSCRIPTION & SUPPORT 12 MONTHS | J15: D17CELL | K15: Authorized User | L15: 0 | M15: =ROUND(IF(K15="Authorized User",L15/3,L15),2) -> 0 | N15: 5 | O15: =N15/3 -> 1.6666667 | P15: 1400 | Q15: License + S&S | R15: ANYWHERE | S15: ANYWHERE | T15: AUTHORIZED | U15: =IF(ISNUMBER(SEARCH("ADD-ON",$I15)),"ADD-ON","NOT AN ADD-ON") -> ADD-ON | V15: =CONCATENATE(R15,S15,T15,U15) -> ANYWHEREANYWHEREAUTHORIZEDADD-ON
A16: Enterprise Asset Management | B16: MAXIMO | C16: MXA ANYWHERE | D16: 5725M39 | E16: IBM Maximo Anywhere | F16: Maximo Anywhere | G16: 839 | H16: D17CFLL | I16: IBM MAXIMO ANYWHERE ADD-ON FOR LINUX ON SYSTEM Z AUTHORIZED USER SW SUBSCRIPTION & SUPPORT REINSTATEMENT 12 MONTHS | J16: D17CELL | K16: Authorized User | L16: 0 | M16: =ROUND(IF(K16="Authorized User",L16/3,L16),2) -> 0 | N16: 5 | O16: =N16/3 -> 1.6666667 | P16: 1400 | Q16: Reinstatement | R16: ANYWHERE | S16: ANYWHERE | T16: AUTHORIZED | U16: =IF(ISNUMBER(SEARCH("ADD-ON",$I16)),"ADD-ON","NOT AN ADD-ON") -> ADD-ON | V16: =CONCATENATE(R16,S16,T16,U16) -> ANYWHEREANYWHEREAUTHORIZEDADD-ON
A17: Enterprise Asset Management | B17: MAXIMO | C17: MXA ANYWHERE | D17: 5725M39 | E17: IBM Maximo Anywhere | F17: Maximo Anywhere | G17: 1410 | H17: E0N3NLL | I17: IBM MAXIMO ANYWHERE CONCURRENT USER ANNUAL SW SUBSCRIPTION & SUPPORT RENEWAL 12 MONTHS | J17: D1QB8LL | K17: Concurrent User | L17: 5 | M17: =ROUND(IF(K17="Authorized User",L17/3,L17),2) -> 5 | N17: 5 | O17: 1 | P17: 7030 | Q17: Renewal | R17: ANYWHERE | S17: ANYWHERE | T17: AUTHORIZED | U17: =IF(ISNUMBER(SEARCH("ADD-ON",$I17)),"ADD-ON","NOT AN ADD-ON") -> NOT AN ADD-ON | V17: =CONCATENATE(R17,S17,T17,U17) -> ANYWHEREANYWHEREAUTHORIZEDNOT AN ADD-ON
A18: Enterprise Asset Management | B18: MAXIMO | C18: MXA ANYWHERE | D18: 5725M39 | E18: IBM Maximo Anywhere | F18: Maximo Anywhere | G18: 7030 | H18: D1QB8LL | I18: IBM MAXIMO ANYWHERE CONCURRENT USER LICENSE + SW SUBSCRIPTION & SUPPORT 12 MONTHS | J18: D1QB8LL | K18: Concurrent User | L18: 5 | M18: =ROUND(IF(K18="Authorized User",L18/3,L18),2) -> 5 | N18: 5 | O18: 1 | P18: 7030 | Q18: License + S&S | R18: ANYWHERE | S18: ANYWHERE | T18: AUTHORIZED | U18: =IF(ISNUMBER(SEARCH("ADD-ON",$I18)),"ADD-ON","NOT AN ADD-ON") -> NOT AN ADD-ON | V18: =CONCATENATE(R18,S18,T18,U18) -> ANYWHEREANYWHEREAUTHORIZEDNOT AN ADD-ON
A19: Enterprise Asset Management | B19: MAXIMO | C19: MXA ANYWHERE | D19: 5725M39 | E19: IBM Maximo Anywhere | F19: Maximo Anywhere | G19: 4220 | H19: D1QB9LL | I19: IBM MAXIMO ANYWHERE CONCURRENT USER SW SUBSCRIPTION & SUPPORT REINSTATEMENT 12 MONTHS | J19: D1QB8LL | K19: Concurrent User | L19: 5 | M19: =ROUND(IF(K19="Authorized User",L19/3,L19),2) -> 5 | N19: 5 | O19: 1 | P19: 7030 | Q19: Reinstatement | R19: ANYWHERE | S19: ANYWHERE | T19: AUTHORIZED | U19: =IF(ISNUMBER(SEARCH("ADD-ON",$I19)),"ADD-ON","NOT AN ADD-ON") -> NOT AN ADD-ON | V19: =CONCATENATE(R19,S19,T19,U19) -> ANYWHEREANYWHEREAUTHORIZEDNOT AN ADD-ON
A20: Enterprise Asset Management | B20: MAXIMO | C20: MXA ANYWHERE | D20: 5725M39 | E20: IBM Maximo Anywhere | F20: Maximo Anywhere | G20: 1500 | H20: D1QBELL | I20: IBM MAXIMO ANYWHERE CONCURRENT USER LINUX ON Z SYSTEM TRADE UP FROM 3 MAXIMO ANYWHERE AUTHORIZED USER ON Z SYSTEM + SW SUBSCRIPTION & SUPPORT 12 MONTHS | J20: D1QBKLL | K20: Concurrent User | L20: 5 | M20: =ROUND(IF(K20="Authorized User",L20/3,L20),2) -> 5 | N20: 5 | O20: 1 | P20: 4260 | Q20: Trade-Up | R20: ANYWHERE | S20: ANYWHERE | T20: AUTHORIZED | U20: =IF(ISNUMBER(SEARCH("ADD-ON",$I20)),"ADD-ON","NOT AN ADD-ON") -> NOT AN ADD-ON | V20: =CONCATENATE(R20,S20,T20,U20) -> ANYWHEREANYWHEREAUTHORIZEDNOT AN ADD-ON
A21: Enterprise Asset Management | B21: MAXIMO | C21: MXA ANYWHERE | D21: 5725M39 | E21: IBM Maximo Anywhere | F21: Maximo Anywhere | G21: 1410 | H21: E0N3PLL | I21: IBM MAXIMO ANYWHERE CONCURRENT USER LINUX Z SYSTEM ANNUAL SW SUBSCRIPTION & SUPPORT RENEWAL | J21: D1QBCLL | K21: Concurrent User | L21: 5 | M21: =ROUND(IF(K21="Authorized User",L21/3,L21),2) -> 5 | N21: 5 | O21: 1 | P21: 7030 | Q21: Renewal | R21: ANYWHERE | S21: ANYWHERE | T21: AUTHORIZED | U21: =IF(ISNUMBER(SEARCH("ADD-ON",$I21)),"ADD-ON","NOT AN ADD-ON") -> NOT AN ADD-ON | V21: =CONCATENATE(R21,S21,T21,U21) -> ANYWHEREANYWHEREAUTHORIZEDNOT AN ADD-ON
A22: Enterprise Asset Management | B22: MAXIMO | C22: MXA ANYWHERE | D22: 5725M39 | E22: IBM Maximo Anywhere | F22: Maximo Anywhere | G22: 7030 | H22: D1QBCLL | I22: IBM MAXIMO ANYWHERE CONCURRENT USER LINUX Z SYSTEM SW SUBSCRIPTION & SUPPORT 12 MONTHS | J22: D1QBCLL | K22: Concurrent User | L22: 5 | M22: =ROUND(IF(K22="Authorized User",L22/3,L22),2) -> 5 | N22: 5 | O22: 1 | P22: 7030 | Q22: License + S&S | R22: ANYWHERE | S22: ANYWHERE | T22: AUTHORIZED | U22: =IF(ISNUMBER(SEARCH("ADD-ON",$I22)),"ADD-ON","NOT AN ADD-ON") -> NOT AN ADD-ON | V22: =CONCATENATE(R22,S22,T22,U22) -> ANYWHEREANYWHEREAUTHORIZEDNOT AN ADD-ON
A23: Enterprise Asset Management | B23: MAXIMO | C23: MXA ANYWHERE | D23: 5725M39 | E23: IBM Maximo Anywhere | F23: Maximo Anywhere | G23: 4220 | H23: D1QBDLL | I23: IBM MAXIMO ANYWHERE CONCURRENT USER LINUX Z SYSTEM SW SUBSCRIPTION & SUPPORT REINSTATEMENT 12 MONTHS | J23: D1QBCLL | K23: Concurrent User | L23: 5 | M23: =ROUND(IF(K23="Authorized User",L23/3,L23),2) -> 5 | N23: 5 | O23: 1 | P23: 7030 | Q23: Reinstatement | R23: ANYWHERE | S23: ANYWHERE | T23: AUTHORIZED | U23: =IF(ISNUMBER(SEARCH("ADD-ON",$I23)),"ADD-ON","NOT AN ADD-ON") -> NOT AN ADD-ON | V23: =CONCATENATE(R23,S23,T23,U23) -> ANYWHEREANYWHEREAUTHORIZEDNOT AN ADD-ON
A24: Enterprise Asset Management | B24: MAXIMO | C24: MXA ANYWHERE | D24: 5725M39 | E24: IBM Maximo Anywhere | F24: Maximo Anywhere | G24: 1500 | H24: D1QBALL | I24: IBM MAXIMO ANYWHERE CONCURRENT USER TRADE UP FROM 3 MAXIMO ANYWHERE AUTHORIZED USER + SW SUBSCRIPTION & SUPPORT 12 MONTHS | J24: D1QB8LL | K24: Concurrent User | L24: 5 | M24: =ROUND(IF(K24="Authorized User",L24/3,L24),2) -> 5 | N24: 5 | O24: 1 | P24: 7030 | Q24: Trade-Up | R24: ANYWHERE | S24: ANYWHERE | T24: AUTHORIZED | U24: =IF(ISNUMBER(SEARCH("ADD-ON",$I24)),"ADD-ON","NOT AN ADD-ON") -> NOT AN ADD-ON | V24: =CONCATENATE(R24,S24,T24,U24) -> ANYWHEREANYWHEREAUTHORIZEDNOT AN ADD-ON
A25: Enterprise Asset Management | B25: MAXIMO | C25: MXA ANYWHERE | D25: 5725M39 | E25: IBM Maximo Anywhere | F25: Maximo Anywhere | G25: 1570 | H25: D10SCLL | I25: IBM MAXIMO ANYWHERE FOR LINUX ON SYSTEM Z AUTHORIZED USER FROM MAXIMO EVERYPLACE FOR LINUX ON SYSTEM Z AUTHORIZED USER TRADE UP LICENSE + SW SUBSCRIPTION & SUPPORT 12 MONTHS | J25: D1QBCLL | K25: Authorized User | L25: 5 | M25: =ROUND(IF(K25="Authorized User",L25/3,L25),2) -> 1.67 | N25: 5 | O25: =N25/3 -> 1.6666667 | P25: 7030 | Q25: Trade-Up | R25: ANYWHERE | S25: ANYWHERE | T25: AUTHORIZED | U25: =IF(ISNUMBER(SEARCH("ADD-ON",$I25)),"ADD-ON","NOT AN ADD-ON") -> NOT AN ADD-ON | V25: =CONCATENATE(R25,S25,T25,U25) -> ANYWHEREANYWHEREAUTHORIZEDNOT AN ADD-ON
A26: Enterprise Asset Management | B26: MAXIMO | C26: MXA ANYWHERE | D26: 5725M39 | E26: IBM Maximo Anywhere | F26: Maximo Anywhere | G26: 461 | H26: E0I3ZLL | I26: IBM MAXIMO ANYWHERE FOR LINUX ON SYSTEM Z AUTHORIZED USER ANNUAL SW SUBSCRIPTION & SUPPORT RENEWAL | J26: D10SALL | K26: Authorized User | L26: 5 | M26: =ROUND(IF(K26="Authorized User",L26/3,L26),2) -> 1.67 | N26: 5 | O26: =N26/3 -> 1.6666667 | P26: 2310 | Q26: Renewal | R26: ANYWHERE | S26: ANYWHERE | T26: AUTHORIZED | U26: =IF(ISNUMBER(SEARCH("ADD-ON",$I26)),"ADD-ON","NOT AN ADD-ON") -> NOT AN ADD-ON | V26: =CONCATENATE(R26,S26,T26,U26) -> ANYWHEREANYWHEREAUTHORIZEDNOT AN ADD-ON
A27: Enterprise Asset Management | B27: MAXIMO | C27: MXA ANYWHERE | D27: 5725M39 | E27: IBM Maximo Anywhere | F27: Maximo Anywhere | G27: 2310 | H27: D10SALL | I27: IBM MAXIMO ANYWHERE FOR LINUX ON SYSTEM Z AUTHORIZED USER LICENSE + SW SUBSCRIPTION & SUPPORT 12 MONTHS | J27: D10SALL | K27: Authorized User | L27: 5 | M27: =ROUND(IF(K27="Authorized User",L27/3,L27),2) -> 1.67 | N27: 5 | O27: =N27/3 -> 1.6666667 | P27: 2310 | Q27: License + S&S | R27: ANYWHERE | S27: ANYWHERE | T27: AUTHORIZED | U27: =IF(ISNUMBER(SEARCH("ADD-ON",$I27)),"ADD-ON","NOT AN ADD-ON") -> NOT AN ADD-ON | V27: =CONCATENATE(R27,S27,T27,U27) -> ANYWHEREANYWHEREAUTHORIZEDNOT AN ADD-ON
A28: Enterprise Asset Management | B28: MAXIMO | C28: MXA ANYWHERE | D28: 5725M39 | E28: IBM Maximo Anywhere | F28: Maximo Anywhere | G28: 1390 | H28: D10SBLL | I28: IBM MAXIMO ANYWHERE FOR LINUX ON SYSTEM Z AUTHORIZED USER SW SUBSCRIPTION & SUPPORT REINSTATE 12 MONTHS | J28: D10SALL | K28: Authorized User | L28: 5 | M28: =ROUND(IF(K28="Authorized User",L28/3,L28),2) -> 1.67 | N28: 5 | O28: =N28/3 -> 1.6666667 | P28: 2310 | Q28: Reinstatement | R28: ANYWHERE | S28: ANYWHERE | T28: AUTHORIZED | U28: =IF(ISNUMBER(SEARCH("ADD-ON",$I28)),"ADD-ON","NOT AN ADD-ON") -> NOT AN ADD-ON | V28: =CONCATENATE(R28,S28,T28,U28) -> ANYWHEREANYWHEREAUTHORIZEDNOT AN ADD-ON
A29: Enterprise Asset Management | B29: MAXIMO | C29: MXA ANYWHERE | D29: 5725M39 | E29: IBM Maximo Anywhere | F29: Maximo Anywhere | G29: 1570 | H29: D10RBLL | I29: IBM MAXIMO ANYWHERE PER AUTHORIZED USER FROM MAXIMO EVERYPLACE AUTHORIZED USER TRADE UP LICENSE + SW SUBSCRIPTION & SUPPORT 12 MONTHS | J29: D1QB8LL | K29: Authorized User | L29: 5 | M29: =ROUND(IF(K29="Authorized User",L29/3,L29),2) -> 1.67 | N29: 5 | O29: =N29/3 -> 1.6666667 | P29: 7030 | Q29: Trade-Up | R29: ANYWHERE | S29: ANYWHERE | T29: AUTHORIZED | U29: =IF(ISNUMBER(SEARCH("ADD-ON",$I29)),"ADD-ON","NOT AN ADD-ON") -> NOT AN ADD-ON | V29: =CONCATENATE(R29,S29,T29,U29) -> ANYWHEREANYWHEREAUTHORIZEDNOT AN ADD-ON
A30: Enterprise Asset Management | B30: MAXIMO | C30: MXA ANYWHERE | D30: 5725M39 | E30: IBM Maximo Anywhere | F30: Maximo Anywhere | G30: 461 | H30: E0I3NLL | I30: IBM MAXIMO ANYWHERE PER AUTHORIZED USER ANNUAL SW SUBSCRIPTION & SUPPORT RENEWAL | J30: D10R9LL | K30: Authorized User | L30: 5 | M30: =ROUND(IF(K30="Authorized User",L30/3,L30),2) -> 1.67 | N30: 5 | O30: =N30/3 -> 1.6666667 | P30: 2310 | Q30: Renewal | R30: ANYWHERE | S30: ANYWHERE | T30: AUTHORIZED | U30: =IF(ISNUMBER(SEARCH("ADD-ON",$I30)),"ADD-ON","NOT AN ADD-ON") -> NOT AN ADD-ON | V30: =CONCATENATE(R30,S30,T30,U30) -> ANYWHEREANYWHEREAUTHORIZEDNOT AN ADD-ON
A31: Enterprise Asset Management | B31: MAXIMO | C31: MXA ANYWHERE | D31: 5725M39 | E31: IBM Maximo Anywhere | F31: Maximo Anywhere | G31: 2310 | H31: D10R9LL | I31: IBM MAXIMO ANYWHERE PER AUTHORIZED USER LICENSE + SW SUBSCRIPTION & SUPPORT 12 MONTHS | J31: D10R9LL | K31: Authorized User | L31: 5 | M31: =ROUND(IF(K31="Authorized User",L31/3,L31),2) -> 1.67 | N31: 5 | O31: =N31/3 -> 1.6666667 | P31: 2310 | Q31: License + S&S | R31: ANYWHERE | S31: ANYWHERE | T31: AUTHORIZED | U31: =IF(ISNUMBER(SEARCH("ADD-ON",$I31)),"ADD-ON","NOT AN ADD-ON") -> NOT AN ADD-ON | V31: =CONCATENATE(R31,S31,T31,U31) -> ANYWHEREANYWHEREAUTHORIZEDNOT AN ADD-ON
A32: Enterprise Asset Management | B32: MAXIMO | C32: MXA ANYWHERE | D32: 5725M39 | E32: IBM Maximo Anywhere | F32: Maximo Anywhere | G32: 1390 | H32: D10RALL | I32: IBM MAXIMO ANYWHERE PER AUTHORIZED USER SW SUBSCRIPTION & SUPPORT REINSTATE 12 MONTHS | J32: D10R9LL | K32: Authorized User | L32: 5 | M32: =ROUND(IF(K32="Authorized User",L32/3,L32),2) -> 1.67 | N32: 5 | O32: =N32/3 -> 1.6666667 | P32: 2310 | Q32: Reinstatement | R32: ANYWHERE | S32: ANYWHERE | T32: AUTHORIZED | U32: =IF(ISNUMBER(SEARCH("ADD-ON",$I32)),"ADD-ON","NOT AN ADD-ON") -> NOT AN ADD-ON | V32: =CONCATENATE(R32,S32,T32,U32) -> ANYWHEREANYWHEREAUTHORIZEDNOT AN ADD-ON
A33: Enterprise Asset Management | B33: MAXIMO | C33: MXA CONFIG | D33: 5724U28 | E33: IBM Maximo Asset Configuration Manager | F33: Maximo Asset Configuration Manager | G33: 1790 | H33: E04QNLL | I33: IBM MAXIMO ASSET CONFIGURATION MANAGER ASSET ANNUAL SW SUBSCRIPTION & SUPPORT RENEWAL | J33: D03WULL | K33: Asset | L33: Manual Input required | M33: =ROUND(IF(K33="Authorized User",L33/3,L33),2) -> #VALUE! | N33: 15 | O33: 5 | P33: 8980 | Q33: Renewal | R33: ASSET CONFIGURATION MANAGER | S33: ACM | T33: ASSET | U33: =IF(ISNUMBER(SEARCH("ADD-ON",$I33)),"ADD-ON","NOT AN ADD-ON") -> NOT AN ADD-ON | V33: =CONCATENATE(R33,S33,T33,U33) -> ASSET CONFIGURATION MANAGERACMASSETNOT AN ADD-ON
A34: Enterprise Asset Management | B34: MAXIMO | C34: MXA CONFIG | D34: 5724U28 | E34: IBM Maximo Asset Configuration Manager | F34: Maximo Asset Configuration Manager | G34: 8980 | H34: D03WULL | I34: IBM MAXIMO ASSET CONFIGURATION MANAGER ASSET LICENSE + SW SUBSCRIPTION & SUPPORT 12 MONTHS | J34: D03WULL | K34: Asset | L34: Manual Input required | M34: =ROUND(IF(K34="Authorized User",L34/3,L34),2) -> #VALUE! | N34: 15 | O34: 5 | P34: 8980 | Q34: License + S&S | R34: ASSET CONFIGURATION MANAGER | S34: ACM | T34: ASSET | U34: =IF(ISNUMBER(SEARCH("ADD-ON",$I34)),"ADD-ON","NOT AN ADD-ON") -> NOT AN ADD-ON | V34: =CONCATENATE(R34,S34,T34,U34) -> ASSET CONFIGURATION MANAGERACMASSETNOT AN ADD-ON
A35: Enterprise Asset Management | B35: MAXIMO | C35: MXA CONFIG | D35: 5724U28 | E35: IBM Maximo Asset Configuration Manager | F35: Maximo Asset Configuration Manager | G35: 5390 | H35: D03WVLL | I35: IBM MAXIMO ASSET CONFIGURATION MANAGER ASSET SW SUBSCRIPTION & SUPPORT REINSTATEMENT 12 MONTHS | J35: D03WULL | K35: Asset | L35: Manual Input required | M35: =ROUND(IF(K35="Authorized User",L35/3,L35),2) -> #VALUE! | N35: 15 | O35: 5 | P35: 8980 | Q35: Reinstatement | R35: ASSET CONFIGURATION MANAGER | S35: ACM | T35: ASSET | U35: =IF(ISNUMBER(SEARCH("ADD-ON",$I35)),"ADD-ON","NOT AN ADD-ON") -> NOT AN ADD-ON | V35: =CONCATENATE(R35,S35,T35,U35) -> ASSET CONFIGURATION MANAGERACMASSETNOT AN ADD-ON
A36: Enterprise Asset Management | B36: MAXIMO | C36: MXA CONFIG | D36: 5724U28 | E36: IBM Maximo Asset Configuration Manager | F36: Maximo Asset Configuration Manager | G36: 1140 | H36: E04QQLL | I36: IBM MAXIMO ASSET CONFIGURATION MANAGER AUTHORIZED USER ANNUAL SW SUBSCRIPTION & SUPPORT RENEWAL | J36: D03WYLL | K36: Authorized User | L36: 15 | M36: =ROUND(IF(K36="Authorized User",L36/3,L36),2) -> 5 | N36: 15 | O36: 5 | P36: 5740 | Q36: Renewal | R36: ASSET CONFIGURATION MANAGER | S36: ACM | T36: AUTHORIZED | U36: =IF(ISNUMBER(SEARCH("ADD-ON",$I36)),"ADD-ON","NOT AN ADD-ON") -> NOT AN ADD-ON | V36: =CONCATENATE(R36,S36,T36,U36) -> ASSET CONFIGURATION MANAGERACMAUTHORIZEDNOT AN ADD-ON
A37: Enterprise Asset Management | B37: MAXIMO | C37: MXA CONFIG | D37: 5724U28 | E37: IBM Maximo Asset Configuration Manager | F37: Maximo Asset Configuration Manager | G37: 5740 | H37: D03WYLL | I37: IBM MAXIMO ASSET CONFIGURATION MANAGER AUTHORIZED USER LICENSE + SW SUBSCRIPTION & SUPPORT 12 MONTHS | J37: D03WYLL | K37: Authorized User | L37: 15 | M37: =ROUND(IF(K37="Authorized User",L37/3,L37),2) -> 5 | N37: 15 | O37: 5 | P37: 5740 | Q37: License + S&S | R37: ASSET CONFIGURATION MANAGER | S37: ACM | T37: AUTHORIZED | U37: =IF(ISNUMBER(SEARCH("ADD-ON",$I37)),"ADD-ON","NOT AN ADD-ON") -> NOT AN ADD-ON | V37: =CONCATENATE(R37,S37,T37,U37) -> ASSET CONFIGURATION MANAGERACMAUTHORIZEDNOT AN ADD-ON
A38: Enterprise Asset Management | B38: MAXIMO | C38: MXA CONFIG | D38: 5724U28 | E38: IBM Maximo Asset Configuration Manager | F38: Maximo Asset Configuration Manager | G38: 3440 | H38: D03WZLL | I38: IBM MAXIMO ASSET CONFIGURATION MANAGER AUTHORIZED USER SW SUBSCRIPTION & SUPPORT REINSTATEMENT 12 MONTHS | J38: D03WYLL | K38: Authorized User | L38: 15 | M38: =ROUND(IF(K38="Authorized User",L38/3,L38),2) -> 5 | N38: 15 | O38: 5 | P38: 5740 | Q38: Reinstatement | R38: ASSET CONFIGURATION MANAGER | S38: ACM | T38: AUTHORIZED | U38: =IF(ISNUMBER(SEARCH("ADD-ON",$I38)),"ADD-ON","NOT AN ADD-ON") -> NOT AN ADD-ON | V38: =CONCATENATE(R38,S38,T38,U38) -> ASSET CONFIGURATION MANAGERACMAUTHORIZEDNOT AN ADD-ON
A39: Enterprise Asset Management | B39: MAXIMO | C39: MXA CONFIG | D39: 5724U28 | E39: IBM Maximo Asset Configuration Manager | F39: Maximo Asset Configuration Manager | G39: 3500 | H39: E0N3LLL | I39: IBM MAXIMO ASSET CONFIGURATION MANAGER CONCURRENT USER ANNUAL SW SUBSCRIPTION & SUPPORT RENEWAL 12 MONTHS | J39: D1QB0LL | K39: Concurrent User | L39: 15 | M39: =ROUND(IF(K39="Authorized User",L39/3,L39),2) -> 15 | N39: 15 | O39: 1 | P39: 17500 | Q39: Renewal | R39: ASSET CONFIGURATION MANAGER | S39: ACM | T39: AUTHORIZED | U39: =IF(ISNUMBER(SEARCH("ADD-ON",$I39)),"ADD-ON","NOT AN ADD-ON") -> NOT AN ADD-ON | V39: =CONCATENATE(R39,S39,T39,U39) -> ASSET CONFIGURATION MANAGERACMAUTHORIZEDNOT AN ADD-ON
A40: Enterprise Asset Management | B40: MAXIMO | C40: MXA CONFIG | D40: 5724U28 | E40: IBM Maximo Asset Configuration Manager | F40: Maximo Asset Configuration Manager | G40: 17500 | H40: D1QB0LL | I40: IBM MAXIMO ASSET CONFIGURATION MANAGER CONCURRENT USER LICENSE + SW SUBSCRIPTION & SUPPORT 12 MONTHS | J40: D1QB0LL | K40: Concurrent User | L40: 15 | M40: =ROUND(IF(K40="Authorized User",L40/3,L40),2) -> 15 | N40: 15 | O40: 1 | P40: 17500 | Q40: License + S&S | R40: ASSET CONFIGURATION MANAGER | S40: ACM | T40: AUTHORIZED | U40: =IF(ISNUMBER(SEARCH("ADD-ON",$I40)),"ADD-ON","NOT AN ADD-ON") -> NOT AN ADD-ON | V40: =CONCATENATE(R40,S40,T40,U40) -> ASSET CONFIGURATION MANAGERACMAUTHORIZEDNOT AN ADD-ON
A41: Enterprise Asset Management | B41: MAXIMO | C41: MXA CONFIG | D41: 5724U28 | E41: IBM Maximo Asset Configuration Manager | F41: Maximo Asset Configuration Manager | G41: 10500 | H41: D1QB1LL | I41: IBM MAXIMO ASSET CONFIGURATION MANAGER CONCURRENT USER SW SUBSCRIPTION & SUPPORT REINSTATEMENT 12 MONTHS | J41: D1QB0LL | K41: Concurrent User | L41: 15 | M41: =ROUND(IF(K41="Authorized User",L41/3,L41),2) -> 15 | N41: 15 | O41: 1 | P41: 17500 | Q41: Reinstatement | R41: ASSET CONFIGURATION MANAGER | S41: ACM | T41: AUTHORIZED | U41: =IF(ISNUMBER(SEARCH("ADD-ON",$I41)),"ADD-ON","NOT AN ADD-ON") -> NOT AN ADD-ON | V41: =CONCATENATE(R41,S41,T41,U41) -> ASSET CONFIGURATION MANAGERACMAUTHORIZEDNOT AN ADD-ON
A42: Enterprise Asset Management | B42: MAXIMO | C42: MXA CONFIG | D42: 5724U28 | E42: IBM Maximo Asset Configuration Manager | F42: Maximo Asset Configuration Manager | G42: 3760 | H42: D1QB6LL | I42: IBM MAXIMO ASSET CONFIGURATION MANAGER CONCURRENT USER LINUX ON Z SYSTEM TRADE UP FROM 3 MAXIMO ASSET CONFIGURATION MANAGER AUTHORIZED USER ON Z SYSTEM + SW SUBSCRIPTION & SUPPORT 12 MONTHS | J42: D1QB4LL | K42: Concurrent User | L42: 15 | M42: =ROUND(IF(K42="Authorized User",L42/3,L42),2) -> 15 | N42: 15 | O42: 1 | P42: 17500 | Q42: Trade-Up | R42: ASSET CONFIGURATION MANAGER | S42: ACM | T42: AUTHORIZED | U42: =IF(ISNUMBER(SEARCH("ADD-ON",$I42)),"ADD-ON","NOT AN ADD-ON") -> NOT AN ADD-ON | V42: =CONCATENATE(R42,S42,T42,U42) -> ASSET CONFIGURATION MANAGERACMAUTHORIZEDNOT AN ADD-ON
A43: Enterprise Asset Management | B43: MAXIMO | C43: MXA CONFIG | D43: 5724U28 | E43: IBM Maximo Asset Configuration Manager | F43: Maximo Asset Configuration Manager | G43: 3500 | H43: E0N3MLL | I43: IBM MAXIMO ASSET CONFIGURATION MANAGER CONCURRENT USER LINUX Z SYSTEM ANNUAL SW SUBSCRIPTION & SUPPORT RENEWAL | J43: D1QB4LL | K43: Concurrent User | L43: 15 | M43: =ROUND(IF(K43="Authorized User",L43/3,L43),2) -> 15 | N43: 15 | O43: 1 | P43: 17500 | Q43: Renewal | R43: ASSET CONFIGURATION MANAGER | S43: ACM | T43: AUTHORIZED | U43: =IF(ISNUMBER(SEARCH("ADD-ON",$I43)),"ADD-ON","NOT AN ADD-ON") -> NOT AN ADD-ON | V43: =CONCATENATE(R43,S43,T43,U43) -> ASSET CONFIGURATION MANAGERACMAUTHORIZEDNOT AN ADD-ON
A44: Enterprise Asset Management | B44: MAXIMO | C44: MXA CONFIG | D44: 5724U28 | E44: IBM Maximo Asset Configuration Manager | F44: Maximo Asset Configuration Manager | G44: 17500 | H44: D1QB4LL | I44: IBM MAXIMO ASSET CONFIGURATION MANAGER CONCURRENT USER LINUX Z SYSTEM + SW SUBSCRIPTION & SUPPORT 12 MONTHS | J44: D1QB4LL | K44: Concurrent User | L44: 15 | M44: =ROUND(IF(K44="Authorized User",L44/3,L44),2) -> 15 | N44: 15 | O44: 1 | P44: 17500 | Q44: License + S&S | R44: ASSET CONFIGURATION MANAGER | S44: ACM | T44: AUTHORIZED | U44: =IF(ISNUMBER(SEARCH("ADD-ON",$I44)),"ADD-ON","NOT AN ADD-ON") -> NOT AN ADD-ON | V44: =CONCATENATE(R44,S44,T44,U44) -> ASSET CONFIGURATION MANAGERACMAUTHORIZEDNOT AN ADD-ON
A45: Enterprise Asset Management | B45: MAXIMO | C45: MXA CONFIG | D45: 5724U28 | E45: IBM Maximo Asset Configuration Manager | F45: Maximo Asset Configuration Manager | G45: 10500 | H45: D1QB5LL | I45: IBM MAXIMO ASSET CONFIGURATION MANAGER CONCURRENT USER LINUX Z SYSTEM SW SUBSCRIPTION & SUPPORT REINSTATEMENT 12 MONTHS | J45: D1QB4LL | K45: Concurrent User | L45: 15 | M45: =ROUND(IF(K45="Authorized User",L45/3,L45),2) -> 15 | N45: 15 | O45: 1 | P45: 17500 | Q45: Reinstatement | R45: ASSET CONFIGURATION MANAGER | S45: ACM | T45: AUTHORIZED | U45: =IF(ISNUMBER(SEARCH("ADD-ON",$I45)),"ADD-ON","NOT AN ADD-ON") -> NOT AN ADD-ON | V45: =CONCATENATE(R45,S45,T45,U45) -> ASSET CONFIGURATION MANAGERACMAUTHORIZEDNOT AN ADD-ON
A46: Enterprise Asset Management | B46: MAXIMO | C46: MXA CONFIG | D46: 5724U28 | E46: IBM Maximo Asset Configuration Manager | F46: Maximo Asset Configuration Manager | G46: 3760 | H46: D1QB2LL | I46: IBM MAXIMO ASSET CONFIGURATION MANAGER CONCURRENT USER TRADE UP FROM 3 MAXIMO ASSET CONFIGURATION MANAGER AUTHORIZED USER + SW SUBSCRIPTION & SUPPORT 12 MONTHS | J46: D1QB0LL | K46: Concurrent User | L46: 15 | M46: =ROUND(IF(K46="Authorized User",L46/3,L46),2) -> 15 | N46: 15 | O46: 1 | P46: 17500 | Q46: Trade-Up | R46: ASSET CONFIGURATION MANAGER | S46: ACM | T46: AUTHORIZED | U46: =IF(ISNUMBER(SEARCH("ADD-ON",$I46)),"ADD-ON","NOT AN ADD-ON") -> NOT AN ADD-ON | V46: =CONCATENATE(R46,S46,T46,U46) -> ASSET CONFIGURATION MANAGERACMAUTHORIZEDNOT AN ADD-ON
A47: Enterprise Asset Management | B47: MAXIMO | C47: MXA CONFIG | D47: 5724U28 | E47: IBM Maximo Asset Configuration Manager | F47: Maximo Asset Configuration Manager | G47: 1790 | H47: E05USLL | I47: IBM MAXIMO ASSET CONFIGURATION MANAGER FOR LINUX ON SYSTEM Z ASSET SW SUBSCRIPTION & SUPPORT RENEWAL | J47: D06GFLL | K47: Asset | L47: Manual Input required | M47: =ROUND(IF(K47="Authorized User",L47/3,L47),2) -> #VALUE! | N47: 15 | O47: 5 | P47: 8980 | Q47: Renewal | R47: ASSET CONFIGURATION MANAGER | S47: ACM | T47: ASSET | U47: =IF(ISNUMBER(SEARCH("ADD-ON",$I47)),"ADD-ON","NOT AN ADD-ON") -> NOT AN ADD-ON | V47: =CONCATENATE(R47,S47,T47,U47) -> ASSET CONFIGURATION MANAGERACMASSETNOT AN ADD-ON
A48: Enterprise Asset Management | B48: MAXIMO | C48: MXA CONFIG | D48: 5724U28 | E48: IBM Maximo Asset Configuration Manager | F48: Maximo Asset Configuration Manager | G48: 8980 | H48: D06GFLL | I48: IBM MAXIMO ASSET CONFIGURATION MANAGER FOR LINUX ON SYSTEM Z ASSET LICENSE + SW SUBSCRIPTION & SUPPORT 12 MONTHS | J48: D06GFLL | K48: Asset | L48: Manual Input required | M48: =ROUND(IF(K48="Authorized User",L48/3,L48),2) -> #VALUE! | N48: 15 | O48: 5 | P48: 8980 | Q48: License + S&S | R48: ASSET CONFIGURATION MANAGER | S48: ACM | T48: ASSET | U48: =IF(ISNUMBER(SEARCH("ADD-ON",$I48)),"ADD-ON","NOT AN ADD-ON") -> NOT AN ADD-ON | V48: =CONCATENATE(R48,S48,T48,U48) -> ASSET CONFIGURATION MANAGERACMASSETNOT AN ADD-ON
A49: Enterprise Asset Management | B49: MAXIMO | C49: MXA CONFIG | D49: 5724U28 | E49: IBM Maximo Asset Configuration Manager | F49: Maximo Asset Configuration Manager | G49: 5390 | H49: D06GGLL | I49: IBM MAXIMO ASSET CONFIGURATION MANAGER FOR LINUX ON SYSTEM Z ASSET SW SUBSCRIPTION & SUPPORT REINSTATEMENT 12 MONTHS | J49: D06GFLL | K49: Asset | L49: Manual Input required | M49: =ROUND(IF(K49="Authorized User",L49/3,L49),2) -> #VALUE! | N49: 15 | O49: 5 | P49: 8980 | Q49: Reinstatement | R49: ASSET CONFIGURATION MANAGER | S49: ACM | T49: ASSET | U49: =IF(ISNUMBER(SEARCH("ADD-ON",$I49)),"ADD-ON","NOT AN ADD-ON") -> NOT AN ADD-ON | V49: =CONCATENATE(R49,S49,T49,U49) -> ASSET CONFIGURATION MANAGERACMASSETNOT AN ADD-ON
A50: Enterprise Asset Management | B50: MAXIMO | C50: MXA CONFIG | D50: 5724U28 | E50: IBM Maximo Asset Configuration Manager | F50: Maximo Asset Configuration Manager | G50: 1140 | H50: E05UYLL | I50: IBM MAXIMO ASSET CONFIGURATION MANAGER FOR LINUX ON SYSTEM Z AUTHORIZED USER SW SUBSCRIPTION & SUPPORT RENEWAL | J50: D06GWLL | K50: Authorized User | L50: 15 | M50: =ROUND(IF(K50="Authorized User",L50/3,L50),2) -> 5 | N50: 15 | O50: 5 | P50: 5740 | Q50: Renewal | R50: ASSET CONFIGURATION MANAGER | S50: ACM | T50: AUTHORIZED | U50: =IF(ISNUMBER(SEARCH("ADD-ON",$I50)),"ADD-ON","NOT AN ADD-ON") -> NOT AN ADD-ON | V50: =CONCATENATE(R50,S50,T50,U50) -> ASSET CONFIGURATION MANAGERACMAUTHORIZEDNOT AN ADD-ON
A51: Enterprise Asset Management | B51: MAXIMO | C51: MXA CONFIG | D51: 5724U28 | E51: IBM Maximo Asset Configuration Manager | F51: Maximo Asset Configuration Manager | G51: 5740 | H51: D06GWLL | I51: IBM MAXIMO ASSET CONFIGURATION MANAGER FOR LINUX ON SYSTEM Z AUTHORIZED USER LICENSE + SW SUBSCRIPTION & SUPPORT 12 MONTHS | J51: D06GWLL | K51: Authorized User | L51: 15 | M51: =ROUND(IF(K51="Authorized User",L51/3,L51),2) -> 5 | N51: 15 | O51: 5 | P51: 5740 | Q51: License + S&S | R51: ASSET CONFIGURATION MANAGER | S51: ACM | T51: AUTHORIZED | U51: =IF(ISNUMBER(SEARCH("ADD-ON",$I51)),"ADD-ON","NOT AN ADD-ON") -> NOT AN ADD-ON | V51: =CONCATENATE(R51,S51,T51,U51) -> ASSET CONFIGURATION MANAGERACMAUTHORIZEDNOT AN ADD-ON
A52: Enterprise Asset Management | B52: MAXIMO | C52: MXA CONFIG | D52: 5724U28 | E52: IBM Maximo Asset Configuration Manager | F52: Maximo Asset Configuration Manager | G52: 3440 | H52: D06GXLL | I52: IBM MAXIMO ASSET CONFIGURATION MANAGER FOR LINUX ON SYSTEM Z AUTHORIZED USER SW SUBSCRIPTION & SUPPORT REINSTATEMENT 12 MONTHS | J52: D06GWLL | K52: Authorized User | L52: 15 | M52: =ROUND(IF(K52="Authorized User",L52/3,L52),2) -> 5 | N52: 15 | O52: 5 | P52: 5740 | Q52: Reinstatement | R52: ASSET CONFIGURATION MANAGER | S52: ACM | T52: AUTHORIZED | U52: =IF(ISNUMBER(SEARCH("ADD-ON",$I52)),"ADD-ON","NOT AN ADD-ON") -> NOT AN ADD-ON | V52: =CONCATENATE(R52,S52,T52,U52) -> ASSET CONFIGURATION MANAGERACMAUTHORIZEDNOT AN ADD-ON
A53: Enterprise Asset Management | B53: MAXIMO | C53: MX CORE | D53: 5724U18 | E53: IBM Maximo Asset Management | F53: Maximo Asset Management | G53: 4090 | H53: D0T0NLL | I53: IBM MAXIMO ASSET MANAGEMENT AUTHORIZED USER FROM MAXIMO ASSET MANAGEMENT LIMITED USE AUTHORIZED USER TRADE UP LICENCE + SW SUBSCRIPTION & SUPPORT 12 MONTHS | J53: D0GYALL | K53: Authorized User | L53: 10 | M53: =ROUND(IF(K53="Authorized User",L53/3,L53),2) -> 3.33 | N53: 10 | O53: 3.3333333 | P53: 6390 | Q53: Trade-Up | R53: ASSET MANAGEMENT (CORE) | S53: ASSET MANAGEMENT (CORE) | T53: AUTHORIZED | U53: =IF(ISNUMBER(SEARCH("ADD-ON",$I53)),"ADD-ON","NOT AN ADD-ON") -> NOT AN ADD-ON | V53: =CONCATENATE(R53,S53,T53,U53) -> ASSET MANAGEMENT (CORE)ASSET MANAGEMENT (CORE)AUTHORIZEDNOT AN ADD-ON
A54: Enterprise Asset Management | B54: MAXIMO | C54: MX CORE | D54: 5724U18 | E54: IBM Maximo Asset Management | F54: Maximo Asset Management | G54: 1290 | H54: E0AUULL | I54: IBM MAXIMO ASSET MANAGEMENT AUTHORIZED USER ANNUAL SW SUBSCRIPTION & SUPPORT RENEWAL | J54: D0GYALL | K54: Authorized User | L54: 10 | M54: =ROUND(IF(K54="Authorized User",L54/3,L54),2) -> 3.33 | N54: 10 | O54: 3.3333333 | P54: 6390 | Q54: Renewal | R54: ASSET MANAGEMENT (CORE) | S54: ASSET MANAGEMENT (CORE) | T54: AUTHORIZED | U54: =IF(ISNUMBER(SEARCH("ADD-ON",$I54)),"ADD-ON","NOT AN ADD-ON") -> NOT AN ADD-ON | V54: =CONCATENATE(R54,S54,T54,U54) -> ASSET MANAGEMENT (CORE)ASSET MANAGEMENT (CORE)AUTHORIZEDNOT AN ADD-ON
A55: Enterprise Asset Management | B55: MAXIMO | C55: MX CORE | D55: 5724U18 | E55: IBM Maximo Asset Management | F55: Maximo Asset Management | G55: 6390 | H55: D0GYALL | I55: IBM MAXIMO ASSET MANAGEMENT AUTHORIZED USER LICENSE + SW SUBSCRIPTION & SUPPORT 12 MONTHS | J55: D0GYALL | K55: Authorized User | L55: 10 | M55: =ROUND(IF(K55="Authorized User",L55/3,L55),2) -> 3.33 | N55: 10 | O55: 3.3333333 | P55: 6390 | Q55: License + S&S | R55: ASSET MANAGEMENT (CORE) | S55: ASSET MANAGEMENT (CORE) | T55: AUTHORIZED | U55: =IF(ISNUMBER(SEARCH("ADD-ON",$I55)),"ADD-ON","NOT AN ADD-ON") -> NOT AN ADD-ON | V55: =CONCATENATE(R55,S55,T55,U55) -> ASSET MANAGEMENT (CORE)ASSET MANAGEMENT (CORE)AUTHORIZEDNOT AN ADD-ON
A56: Enterprise Asset Management | B56: MAXIMO | C56: MX CORE | D56: 5724U18 | E56: IBM Maximo Asset Management | F56: Maximo Asset Management | G56: 3830 | H56: D0GYBLL | I56: IBM MAXIMO ASSET MANAGEMENT AUTHORIZED USER SW SUBSCRIPTION & SUPPORT REINSTATEMENT 12 MONTHS | J56: D0GYALL | K56: Authorized User | L56: 10 | M56: =ROUND(IF(K56="Authorized User",L56/3,L56),2) -> 3.33 | N56: 10 | O56: 3.3333333 | P56: 6390 | Q56: Reinstatement | R56: ASSET MANAGEMENT (CORE) | S56: ASSET MANAGEMENT (CORE) | T56: AUTHORIZED | U56: =IF(ISNUMBER(SEARCH("ADD-ON",$I56)),"ADD-ON","NOT AN ADD-ON") -> NOT AN ADD-ON | V56: =CONCATENATE(R56,S56,T56,U56) -> ASSET MANAGEMENT (CORE)ASSET MANAGEMENT (CORE)AUTHORIZEDNOT AN ADD-ON
A57: Enterprise Asset Management | B57: MAXIMO | C57: MX CORE | D57: 5724U18 | E57: IBM Maximo Asset Management | F57: Maximo Asset Management | G57: 3890 | H57: E0N2NLL | I57: IBM MAXIMO ASSET MANAGEMENT CONCURRENT USER ANNUAL SW SUBSCRIPTION & SUPPORT RENEWAL 12 MONTHS | J57: D1Q6ELL | K57: Concurrent User | L57: 10 | M57: =ROUND(IF(K57="Authorized User",L57/3,L57),2) -> 10 | N57: 10 | O57: 1 | P57: 19400 | Q57: Renewal | R57: ASSET MANAGEMENT (CORE) | S57: ASSET MANAGEMENT (CORE) | T57: AUTHORIZED | U57: =IF(ISNUMBER(SEARCH("ADD-ON",$I57)),"ADD-ON","NOT AN ADD-ON") -> NOT AN ADD-ON | V57: =CONCATENATE(R57,S57,T57,U57) -> ASSET MANAGEMENT (CORE)ASSET MANAGEMENT (CORE)AUTHORIZEDNOT AN ADD-ON
A58: Enterprise Asset Management | B58: MAXIMO | C58: MX CORE | D58: 5724U18 | E58: IBM Maximo Asset Management | F58: Maximo Asset Management | G58: 19400 | H58: D1Q6ELL | I58: IBM MAXIMO ASSET MANAGEMENT CONCURRENT USER LICENSE + SW SUBSCRIPTION & SUPPORT 12 MONTHS | J58: D1Q6ELL | K58: Concurrent User | L58: 10 | M58: =ROUND(IF(K58="Authorized User",L58/3,L58),2) -> 10 | N58: 10 | O58: 1 | P58: 19400 | Q58: License + S&S | R58: ASSET MANAGEMENT (CORE) | S58: ASSET MANAGEMENT (CORE) | T58: AUTHORIZED | U58: =IF(ISNUMBER(SEARCH("ADD-ON",$I58)),"ADD-ON","NOT AN ADD-ON") -> NOT AN ADD-ON | V58: =CONCATENATE(R58,S58,T58,U58) -> ASSET MANAGEMENT (CORE)ASSET MANAGEMENT (CORE)AUTHORIZEDNOT AN ADD-ON
A59: Enterprise Asset Management | B59: MAXIMO | C59: MX CORE | D59: 5724U18 | E59: IBM Maximo Asset Management | F59: Maximo Asset Management | G59: 11600 | H59: D1Q6FLL | I59: IBM MAXIMO ASSET MANAGEMENT CONCURRENT USER SW SUBSCRIPTION & SUPPORT REINSTATEMENT 12 MONTHS | J59: D1Q6ELL | K59: Concurrent User | L59: 10 | M59: =ROUND(IF(K59="Authorized User",L59/3,L59),2) -> 10 | N59: 10 | O59: 1 | P59: 19400 | Q59: Reinstatement | R59: ASSET MANAGEMENT (CORE) | S59: ASSET MANAGEMENT (CORE) | T59: AUTHORIZED | U59: =IF(ISNUMBER(SEARCH("ADD-ON",$I59)),"ADD-ON","NOT AN ADD-ON") -> NOT AN ADD-ON | V59: =CONCATENATE(R59,S59,T59,U59) -> ASSET MANAGEMENT (CORE)ASSET MANAGEMENT (CORE)AUTHORIZEDNOT AN ADD-ON
A60: Enterprise Asset Management | B60: MAXIMO | C60: MX CORE | D60: 5724U18 | E60: IBM Maximo Asset Management | F60: Maximo Asset Management | G60: 13000 | H60: D1SVWLL | I60: IBM MAXIMO ASSET MANAGEMENT CONCURRENT USER LINUX ON SYSTEM Z TRADE UP FROM 3 MAXIMO ASSET MANAGEMENT LIMITED USER ON SYSTEM Z | J60: D1Q6JLL | K60: Concurrent User | L60: 10 | M60: =ROUND(IF(K60="Authorized User",L60/3,L60),2) -> 10 | N60: 10 | O60: 1 | P60: 19400 | Q60: Trade-Up | R60: ASSET MANAGEMENT (CORE) | S60: ASSET MANAGEMENT (CORE) | T60: AUTHORIZED | U60: =IF(ISNUMBER(SEARCH("ADD-ON",$I60)),"ADD-ON","NOT AN ADD-ON") -> NOT AN ADD-ON | V60: =CONCATENATE(R60,S60,T60,U60) -> ASSET MANAGEMENT (CORE)ASSET MANAGEMENT (CORE)AUTHORIZEDNOT AN ADD-ON
A61: Enterprise Asset Management | B61: MAXIMO | C61: MX CORE | D61: 5724U18 | E61: IBM Maximo Asset Management | F61: Maximo Asset Management | G61: 4180 | H61: D1Q6LLL | I61: IBM MAXIMO ASSET MANAGEMENT CONCURRENT USER LINUX ON Z SYSTEM TRADE UP FROM 3 MAXIMO ASSET MANAGEMENT AUTHORIZED USER ON Z SYSTEM + SW SUBSCRIPTION & SUPPORT 12 MONTHS | J61: D1Q6JLL | K61: Concurrent User | L61: 10 | M61: =ROUND(IF(K61="Authorized User",L61/3,L61),2) -> 10 | N61: 10 | O61: 1 | P61: 19400 | Q61: Trade-Up | R61: ASSET MANAGEMENT (CORE) | S61: ASSET MANAGEMENT (CORE) | T61: AUTHORIZED | U61: =IF(ISNUMBER(SEARCH("ADD-ON",$I61)),"ADD-ON","NOT AN ADD-ON") -> NOT AN ADD-ON | V61: =CONCATENATE(R61,S61,T61,U61) -> ASSET MANAGEMENT (CORE)ASSET MANAGEMENT (CORE)AUTHORIZEDNOT AN ADD-ON
... A218: Enterprise Asset Management | B218: MAXIMO | C218: MXI AVIATION | D218: 5725U87 | E218: IBM Maximo for Aviation | F218: Maximo for Aviation | G218: 6320 | H218: D1GVJLL | I218: IBM MAXIMO FOR AVIATION LIMITED USE FOR LINUX ON SYSTEM Z CONCURRENT USER SW SUBSCRIPTION & SUPPORT REINSTATEMENT 12 MONTHS | J218: D1GVILL | K218: Concurrent User | L218: 5 | M218: =ROUND(IF(K218="Authorized User",L218/3,L218),2) -> 5 | N218: 5 | O218: 1 | P218: 10500 | Q218: Reinstatement | R218: AVIATION | S218: INDUSTRY SOLUTION | T218: LIMITED | U218: =IF(ISNUMBER(SEARCH("ADD-ON",$I218)),"ADD-ON","NOT AN ADD-ON") -> NOT AN ADD-ON | V218: =CONCATENATE(R218,S218,T218,U218) -> AVIATIONINDUSTRY SOLUTIONLIMITEDNOT AN ADD-ON
A219: Enterprise Asset Management | B219: MAXIMO | C219: MXI LIFESCI | D219: 5724U23 | E219: IBM Maximo for Life Sciences | F219: Maximo for Life Science | G219: 142 | H219: E0AVMLL | I219: IBM MAXIMO FOR LIFE SCIENCES ADD ON AUTHORIZED USER ANNUAL SW SUBSCRIPTION & SUPPORT RENEWAL | J219: D0H0GLL | K219: Authorized User | L219: 0 | M219: =ROUND(IF(K219="Authorized User",L219/3,L219),2) -> 0 | N219: 5 | O219: 1.67 | P219: 712 | Q219: Renewal | R219: LIFE SCIENCES | S219: LIFE SCIENCES | T219: AUTHORIZED | U219: ADD-ON | V219: =CONCATENATE(R219,S219,T219,U219) -> LIFE SCIENCESLIFE SCIENCESAUTHORIZEDADD-ON
A220: Enterprise Asset Management | B220: MAXIMO | C220: MXI LIFESCI | D220: 5724U23 | E220: IBM Maximo for Life Sciences | F220: Maximo for Life Science | G220: 712 | H220: D0H0GLL | I220: IBM MAXIMO FOR LIFE SCIENCES ADD ON AUTHORIZED USER LICENSE + SW SUBSCRIPTION & SUPPORT 12 MONTHS | J220: D0H0GLL | K220: Authorized User | L220: 0 | M220: =ROUND(IF(K220="Authorized User",L220/3,L220),2) -> 0 | N220: 5 | O220: 1.67 | P220: 712 | Q220: License + S&S | R220: LIFE SCIENCES | S220: LIFE SCIENCES | T220: AUTHORIZED | U220: ADD-ON | V220: =CONCATENATE(R220,S220,T220,U220) -> LIFE SCIENCESLIFE SCIENCESAUTHORIZEDADD-ON
A221: Enterprise Asset Management | B221: MAXIMO | C221: MXI LIFESCI | D221: 5724U23 | E221: IBM Maximo for Life Sciences | F221: Maximo for Life Science | G221: 427 | H221: D0H0HLL | I221: IBM MAXIMO FOR LIFE SCIENCES ADD ON AUTHORIZED USER SW SUBSCRIPTION & SUPPORT REINSTATEMENT 12 MONTHS | J221: D0H0GLL | K221: Authorized User | L221: 0 | M221: =ROUND(IF(K221="Authorized User",L221/3,L221),2) -> 0 | N221: 5 | O221: 1.67 | P221: 712 | Q221: Reinstatement | R221: LIFE SCIENCES | S221: LIFE SCIENCES | T221: AUTHORIZED | U221: ADD-ON | V221: =CONCATENATE(R221,S221,T221,U221) -> LIFE SCIENCESLIFE SCIENCESAUTHORIZEDADD-ON
A222: Enterprise Asset Management | B222: MAXIMO | C222: MXI LIFESCI | D222: 5724U23 | E222: IBM Maximo for Life Sciences | F222: Maximo for Life Science | G222: 434 | H222: E0N89LL | I222: IBM MAXIMO FOR LIFE SCIENCES ADD ON CONCURRENT USER ANNUAL SW SUBSCRIPTION & SUPPORT RENEWAL | J222: D1R7LLL | K222: Concurrent User | L222: 0 | M222: =ROUND(IF(K222="Authorized User",L222/3,L222),2) -> 0 | N222: 5 | O222: 1 | P222: 2170 | Q222: Renewal | R222: LIFE SCIENCES | S222: LIFE SCIENCES | T222: AUTHORIZED | U222: ADD-ON | V222: =CONCATENATE(R222,S222,T222,U222) -> LIFE SCIENCESLIFE SCIENCESAUTHORIZEDADD-ON
A223: Enterprise Asset Management | B223: MAXIMO | C223: MXI LIFESCI | D223: 5724U23 | E223: IBM Maximo for Life Sciences | F223: Maximo for Life Science | G223: 2170 | H223: D1R7LLL | I223: IBM MAXIMO FOR LIFE SCIENCES ADD ON CONCURRENT USER LICENSE + SW SUBSCRIPTION & SUPPORT 12 MONTHS | J223: D1R7LLL | K223: Concurrent User | L223: 0 | M223: =ROUND(IF(K223="Authorized User",L223/3,L223),2) -> 0 | N223: 5 | O223: 1 | P223: 2170 | Q223: License + S&S | R223: LIFE SCIENCES | S223: LIFE SCIENCES | T223: AUTHORIZED | U223: ADD-ON | V223: =CONCATENATE(R223,S223,T223,U223) -> LIFE SCIENCESLIFE SCIENCESAUTHORIZEDADD-ON
A224: Enterprise Asset Management | B224: MAXIMO | C224: MXI LIFESCI | D224: 5724U23 | E224: IBM Maximo for Life Sciences | F224: Maximo for Life Science | G224: 1310 | H224: D1R7MLL | I224: IBM MAXIMO FOR LIFE SCIENCES ADD ON CONCURRENT USER SW SUBSCRIPTION & SUPPORT REINSTATEMENT 12 MONTHS | J224: D1R7LLL | K224: Concurrent User | L224: 0 | M224: =ROUND(IF(K224="Authorized User",L224/3,L224),2) -> 0 | N224: 5 | O224: 1 | P224: 2170 | Q224: Reinstatement | R224: LIFE SCIENCES | S224: LIFE SCIENCES | T224: AUTHORIZED | U224: ADD-ON | V224: =CONCATENATE(R224,S224,T224,U224) -> LIFE SCIENCESLIFE SCIENCESAUTHORIZEDADD-ON
A225: Enterprise Asset Management | B225: MAXIMO | C225: MXI LIFESCI | D225: 5724U23 | E225: IBM Maximo for Life Sciences | F225: Maximo for Life Science | G225: 434 | H225: E0N8ALL | I225: IBM MAXIMO FOR LIFE SCIENCES ADD ON CONCURRENT USER LINUX Z SYSTEM ANNUAL SW SUBSCRIPTION & SUPPORT RENEWAL | J225: D1R7QLL | K225: Concurrent User | L225: 0 | M225: =ROUND(IF(K225="Authorized User",L225/3,L225),2) -> 0 | N225: 5 | O225: 1 | P225: 2170 | Q225: Renewal | R225: LIFE SCIENCES | S225: LIFE SCIENCES | T225: AUTHORIZED | U225: ADD-ON | V225: =CONCATENATE(R225,S225,T225,U225) -> LIFE SCIENCESLIFE SCIENCESAUTHORIZEDADD-ON
A226: Enterprise Asset Management | B226: MAXIMO | C226: MXI LIFESCI | D226: 5724U23 | E226: IBM Maximo for Life Sciences | F226: Maximo for Life Science | G226: 2170 | H226: D1R7QLL | I226: IBM MAXIMO FOR LIFE SCIENCES ADD ON CONCURRENT USER LICENSE LINUX Z SYSTEM + SW SUBSCRIPTION & SUPPORT 12 MONTHS | J226: D1R7QLL | K226: Concurrent User | L226: 0 | M226: =ROUND(IF(K226="Authorized User",L226/3,L226),2) -> 0 | N226: 5 | O226: 1 | P226: 2170 | Q226: License + S&S | R226: LIFE SCIENCES | S226: LIFE SCIENCES | T226: AUTHORIZED | U226: ADD-ON | V226: =CONCATENATE(R226,S226,T226,U226) -> LIFE SCIENCESLIFE SCIENCESAUTHORIZEDADD-ON
A227: Enterprise Asset Management | B227: MAXIMO | C227: MXI LIFESCI | D227: 5724U23 | E227: IBM Maximo for Life Sciences | F227: Maximo for Life Science | G227: 1310 | H227: D1R7RLL | I227: IBM MAXIMO FOR LIFE SCIENCES ADD ON CONCURRENT USER LINUX Z SYSTEM SW SUBSCRIPTION & SUPPORT REINSTATEMENT 12 MONTHS | J227: D1R7QLL | K227: Concurrent User | L227: 0 | M227: =ROUND(IF(K227="Authorized User",L227/3,L227),2) -> 0 | N227: 5 | O227: 1 | P227: 2170 | Q227: Reinstatement | R227: LIFE SCIENCES | S227: LIFE SCIENCES | T227: AUTHORIZED | U227: ADD-ON | V227: =CONCATENATE(R227,S227,T227,U227) -> LIFE SCIENCESLIFE SCIENCESAUTHORIZEDADD-ON
A228: Enterprise Asset Management | B228: MAXIMO | C228: MXI LIFESCI | D228: 5724U23 | E228: IBM Maximo for Life Sciences | F228: Maximo for Life Science | G228: 467 | H228: D1R7SLL | I228: IBM MAXIMO FOR LIFE SCIENCES ADD ON CONCURRENT USER LINUX Z SYSTEM TRADE UP FROM 3 MAXIMO FOR LIFE SCIENCES AUTHORIZED USER LINUX Z SYSTEM + SW SUBSCRIPTION & SUPPORT 12 MONTHS | J228: D1R7QLL | K228: Concurrent User | L228: 0 | M228: =ROUND(IF(K228="Authorized User",L228/3,L228),2) -> 0 | N228: 5 | O228: 1 | P228: 2170 | Q228: Trade-Up | R228: LIFE SCIENCES | S228: LIFE SCIENCES | T228: AUTHORIZED | U228: ADD-ON | V228: =CONCATENATE(R228,S228,T228,U228) -> LIFE SCIENCESLIFE SCIENCESAUTHORIZEDADD-ON
A229: Enterprise Asset Management | B229: MAXIMO | C229: MXI LIFESCI | D229: 5724U23 | E229: IBM Maximo for Life Sciences | F229: Maximo for Life Science | G229: 467 | H229: D1R7NLL | I229: IBM MAXIMO FOR LIFE SCIENCES ADD ON CONCURRENT USER TRADE UP FROM 3 MAXIMO LIFE SCIENCES AUTHORIZED USER + SW SUBSCRIPTION & SUPPORT 12 MONTHS | J229: D1R7LLL | K229: Concurrent User | L229: 0 | M229: =ROUND(IF(K229="Authorized User",L229/3,L229),2) -> 0 | N229: 5 | O229: 1 | P229: 2170 | Q229: Trade-Up | R229: LIFE SCIENCES | S229: LIFE SCIENCES | T229: AUTHORIZED | U229: ADD-ON | V229: =CONCATENATE(R229,S229,T229,U229) -> LIFE SCIENCESLIFE SCIENCESAUTHORIZEDADD-ON
A230: Enterprise Asset Management | B230: MAXIMO | C230: MXI LIFESCI | D230: 5724U23 | E230: IBM Maximo for Life Sciences | F230: Maximo for Life Science | G230: 1920 | H230: D0H0FLL | I230: IBM MAXIMO FOR LIFE SCIENCES AUTHORIZED USER FROM MAXIMO ASSET MANAGEMENT AUTHORIZED USER TRADE UP LICENSE + SW SUBSCRIPTION & SUPPORT 12 MONTHS | J230: D0H0CLL | K230: Authorized User | L230: 10 | M230: =ROUND(IF(K230="Authorized User",L230/3,L230),2) -> 3.33 | N230: 5 | O230: 1.67 | P230: 6980 | Q230: Trade-Up | R230: LIFE SCIENCES | S230: LIFE SCIENCES | T230: AUTHORIZED | U230: =IF(ISNUMBER(SEARCH("ADD-ON",$I230)),"ADD-ON","NOT AN ADD-ON") -> NOT AN ADD-ON | V230: =CONCATENATE(R230,S230,T230,U230) -> LIFE SCIENCESLIFE SCIENCESAUTHORIZEDNOT AN ADD-ON
A231: Enterprise Asset Management | B231: MAXIMO | C231: MXI LIFESCI | D231: 5724U23 | E231: IBM Maximo for Life Sciences | F231: Maximo for Life Science | G231: 4710 | H231: D0H0ELL | I231: IBM MAXIMO FOR LIFE SCIENCES AUTHORIZED USER FROM MAXIMO ASSET MANAGEMENT LIMITED USE AUTHORIZED USER TRADE UP LICENSE + SW SUBSCRIPTION & SUPPORT 12 MONTHS | J231: D0H0CLL | K231: Authorized User | L231: 10 | M231: =ROUND(IF(K231="Authorized User",L231/3,L231),2) -> 3.33 | N231: 5 | O231: 1.67 | P231: 6980 | Q231: Trade-Up | R231: LIFE SCIENCES | S231: LIFE SCIENCES | T231: AUTHORIZED | U231: =IF(ISNUMBER(SEARCH("ADD-ON",$I231)),"ADD-ON","NOT AN ADD-ON") -> NOT AN ADD-ON | V231: =CONCATENATE(R231,S231,T231,U231) -> LIFE SCIENCESLIFE SCIENCESAUTHORIZEDNOT AN ADD-ON
A232: Enterprise Asset Management | B232: MAXIMO | C232: MXI LIFESCI | D232: 5724U23 | E232: IBM Maximo for Life Sciences | F232: Maximo for Life Science | G232: 4470 | H232: D0T12LL | I232: IBM MAXIMO FOR LIFE SCIENCES AUTHORIZED USER FROM MAXIMO FOR LIFE SCIENCES LIMITED USE AUTHORIZED USER TRADE UP LICENCE + SW SUBSCRIPTION & SUPPORT 12 MONTHS | J232: D0H0CLL | K232: Authorized User | L232: 10 | M232: =ROUND(IF(K232="Authorized User",L232/3,L232),2) -> 3.33 | N232: 5 | O232: 1.67 | P232: 6980 | Q232: Trade-Up | R232: LIFE SCIENCES | S232: LIFE SCIENCES | T232: AUTHORIZED | U232: =IF(ISNUMBER(SEARCH("ADD-ON",$I232)),"ADD-ON","NOT AN ADD-ON") -> NOT AN ADD-ON | V232: =CONCATENATE(R232,S232,T232,U232) -> LIFE SCIENCESLIFE SCIENCESAUTHORIZEDNOT AN ADD-ON
A233: Enterprise Asset Management | B233: MAXIMO | C233: MXI LIFESCI | D233: 5724U23 | E233: IBM Maximo for Life Sciences | F233: Maximo for Life Science | G233: 1400 | H233: E0AVLLL | I233: IBM MAXIMO FOR LIFE SCIENCES AUTHORIZED USER ANNUAL SW SUBSCRIPTION & SUPPORT RENEWAL | J233: D0H0CLL | K233: Authorized User | L233: 10 | M233: =ROUND(IF(K233="Authorized User",L233/3,L233),2) -> 3.33 | N233: 5 | O233: 1.67 | P233: 6980 | Q233: Renewal | R233: LIFE SCIENCES | S233: LIFE SCIENCES | T233: AUTHORIZED | U233: =IF(ISNUMBER(SEARCH("ADD-ON",$I233)),"ADD-ON","NOT AN ADD-ON") -> NOT AN ADD-ON | V233: =CONCATENATE(R233,S233,T233,U233) -> LIFE SCIENCESLIFE SCIENCESAUTHORIZEDNOT AN ADD-ON
A234: Enterprise Asset Management | B234: MAXIMO | C234: MXI LIFESCI | D234: 5724U23 | E234: IBM Maximo for Life Sciences | F234: Maximo for Life Science | G234: 6980 | H234: D0H0CLL | I234: IBM MAXIMO FOR LIFE SCIENCES AUTHORIZED USER LICENSE + SW SUBSCRIPTION & SUPPORT 12 MONTHS | J234: D0H0CLL | K234: Authorized User | L234: 10 | M234: =ROUND(IF(K234="Authorized User",L234/3,L234),2) -> 3.33 | N234: 5 | O234: 1.67 | P234: 6980 | Q234: License + S&S | R234: LIFE SCIENCES | S234: LIFE SCIENCES | T234: AUTHORIZED | U234: =IF(ISNUMBER(SEARCH("ADD-ON",$I234)),"ADD-ON","NOT AN ADD-ON") -> NOT AN ADD-ON | V234: =CONCATENATE(R234,S234,T234,U234) -> LIFE SCIENCESLIFE SCIENCESAUTHORIZEDNOT AN ADD-ON
A235: Enterprise Asset Management | B235: MAXIMO | C235: MXI LIFESCI | D235: 5724U23 | E235: IBM Maximo for Life Sciences | F235: Maximo for Life Science | G235: 4180 | H235: D0H0DLL | I235: IBM MAXIMO FOR LIFE SCIENCES AUTHORIZED USER SW SUBSCRIPTION & SUPPORT REINSTATEMENT 12 MONTHS | J235: D0H0CLL | K235: Authorized User | L235: 10 | M235: =ROUND(IF(K235="Authorized User",L235/3,L235),2) -> 3.33 | N235: 5 | O235: 1.67 | P235: 6980 | Q235: Reinstatement | R235: LIFE SCIENCES | S235: LIFE SCIENCES | T235: AUTHORIZED | U235: =IF(ISNUMBER(SEARCH("ADD-ON",$I235)),"ADD-ON","NOT AN ADD-ON") -> NOT AN ADD-ON | V235: =CONCATENATE(R235,S235,T235,U235) -> LIFE SCIENCESLIFE SCIENCESAUTHORIZEDNOT AN ADD-ON
A236: Enterprise Asset Management | B236: MAXIMO | C236: MXI LIFESCI | D236: 5724U23 | E236: IBM Maximo for Life Sciences | F236: Maximo for Life Science | G236: 4260 | H236: E0N87LL | I236: IBM MAXIMO FOR LIFE SCIENCES CONCURRENT USER ANNUAL SW SUBSCRIPTION & SUPPORT RENEWAL | J236: D1R7BLL | K236: Concurrent User | L236: 10 | M236: =ROUND(IF(K236="Authorized User",L236/3,L236),2) -> 10 | N236: 5 | O236: 1 | P236: 21300 | Q236: Renewal | R236: LIFE SCIENCES | S236: LIFE SCIENCES | T236: AUTHORIZED | U236: =IF(ISNUMBER(SEARCH("ADD-ON",$I236)),"ADD-ON","NOT AN ADD-ON") -> NOT AN ADD-ON | V236: =CONCATENATE(R236,S236,T236,U236) -> LIFE SCIENCESLIFE SCIENCESAUTHORIZEDNOT AN ADD-ON
A237: Enterprise Asset Management | B237: MAXIMO | C237: MXI LIFESCI | D237: 5724U23 | E237: IBM Maximo for Life Sciences | F237: Maximo for Life Science | G237: 21300 | H237: D1R7BLL | I237: IBM MAXIMO FOR LIFE SCIENCES CONCURRENT USER LICENSE + SW SUBSCRIPTION & SUPPORT 12 MONTHS | J237: D1R7BLL | K237: Concurrent User | L237: 10 | M237: =ROUND(IF(K237="Authorized User",L237/3,L237),2) -> 10 | N237: 5 | O237: 1 | P237: 21300 | Q237: License + S&S | R237: LIFE SCIENCES | S237: LIFE SCIENCES | T237: AUTHORIZED | U237: =IF(ISNUMBER(SEARCH("ADD-ON",$I237)),"ADD-ON","NOT AN ADD-ON") -> NOT AN ADD-ON | V237: =CONCATENATE(R237,S237,T237,U237) -> LIFE SCIENCESLIFE SCIENCESAUTHORIZEDNOT AN ADD-ON
A238: Enterprise Asset Management | B238: MAXIMO | C238: MXI LIFESCI | D238: 5724U23 | E238: IBM Maximo for Life Sciences | F238: Maximo for Life Science | G238: 12900 | H238: D1R7CLL | I238: IBM MAXIMO FOR LIFE SCIENCES CONCURRENT USER SW SUBSCRIPTION & SUPPORT REINSTATEMENT 12 MONTHS | J238: D1R7BLL | K238: Concurrent User | L238: 10 | M238: =ROUND(IF(K238="Authorized User",L238/3,L238),2) -> 10 | N238: 5 | O238: 1 | P238: 21300 | Q238: Reinstatement | R238: LIFE SCIENCES | S238: LIFE SCIENCES | T238: AUTHORIZED | U238: =IF(ISNUMBER(SEARCH("ADD-ON",$I238)),"ADD-ON","NOT AN ADD-ON") -> NOT AN ADD-ON | V238: =CONCATENATE(R238,S238,T238,U238) -> LIFE SCIENCESLIFE SCIENCESAUTHORIZEDNOT AN ADD-ON
A239: Enterprise Asset Management | B239: MAXIMO | C239: MXI LIFESCI | D239: 5724U23 | E239: IBM Maximo for Life Sciences | F239: Maximo for Life Science | G239: 4260 | H239: E0N88LL | I239: IBM MAXIMO FOR LIFE SCIENCES CONCURRENT USER LINUX Z SYSTEM ANNUAL SW SUBSCRIPTION & SUPPORT RENEWAL | J239: D1R7GLL | K239: Concurrent User | L239: 10 | M239: =ROUND(IF(K239="Authorized User",L239/3,L239),2) -> 10 | N239: 5 | O239: 1 | P239: 21300 | Q239: Renewal | R239: LIFE SCIENCES | S239: LIFE SCIENCES | T239: AUTHORIZED | U239: =IF(ISNUMBER(SEARCH("ADD-ON",$I239)),"ADD-ON","NOT AN ADD-ON") -> NOT AN ADD-ON | V239: =CONCATENATE(R239,S239,T239,U239) -> LIFE SCIENCESLIFE SCIENCESAUTHORIZEDNOT AN ADD-ON
A240: Enterprise Asset Management | B240: MAXIMO | C240: MXI LIFESCI | D240: 5724U23 | E240: IBM Maximo for Life Sciences | F240: Maximo for Life Science | G240: 21300 | H240: D1R7GLL | I240: IBM MAXIMO FOR LIFE SCIENCES CONCURRENT USER LICENSE LINUX Z SYSTEM + SW SUBSCRIPTION & SUPPORT 12 MONTHS | J240: D1R7GLL | K240: Concurrent User | L240: 10 | M240: =ROUND(IF(K240="Authorized User",L240/3,L240),2) -> 10 | N240: 5 | O240: 1 | P240: 21300 | Q240: License + S&S | R240: LIFE SCIENCES | S240: LIFE SCIENCES | T240: AUTHORIZED | U240: =IF(ISNUMBER(SEARCH("ADD-ON",$I240)),"ADD-ON","NOT AN ADD-ON") -> NOT AN ADD-ON | V240: =CONCATENATE(R240,S240,T240,U240) -> LIFE SCIENCESLIFE SCIENCESAUTHORIZEDNOT AN ADD-ON
A241: Enterprise Asset Management | B241: MAXIMO | C241: MXI LIFESCI | D241: 5724U23 | E241: IBM Maximo for Life Sciences | F241: Maximo for Life Science | G241: 12900 | H241: D1R7HLL | I241: IBM MAXIMO FOR LIFE SCIENCES CONCURRENT USER LINUX Z SYSTEM SW SUBSCRIPTION & SUPPORT REINSTATEMENT 12 MONTHS | J241: D1R7GLL | K241: Concurrent User | L241: 10 | M241: =ROUND(IF(K241="Authorized User",L241/3,L241),2) -> 10 | N241: 5 | O241: 1 | P241: 21300 | Q241: Reinstatement | R241: LIFE SCIENCES | S241: LIFE SCIENCES | T241: AUTHORIZED | U241: =IF(ISNUMBER(SEARCH("ADD-ON",$I241)),"ADD-ON","NOT AN ADD-ON") -> NOT AN ADD-ON | V241: =CONCATENATE(R241,S241,T241,U241) -> LIFE SCIENCESLIFE SCIENCESAUTHORIZEDNOT AN ADD-ON
... A245: Enterprise Asset Management | B245: MAXIMO | C245: MXI LIFESCI | D245: 5724U23 | E245: IBM Maximo for Life Sciences | F245: Maximo for Life Science | G245: 5940 | H245: D1R7DLL | I245: IBM MAXIMO FOR LIFE SCIENCES CONCURRENT USER TRADE UP FROM MAXIMO ASSET MANAGEMENT CONCURRENT USER + SW SUBSCRIPTION & SUPPORT 12 MONTHS | J245: D1R7BLL | K245: Concurrent User | L245: 10 | M245: =ROUND(IF(K245="Authorized User",L245/3,L245),2) -> 10 | N245: 5 | O245: 1 | P245: 21300 | Q245: Trade-Up | R245: LIFE SCIENCES | S245: LIFE SCIENCES | T245: AUTHORIZED | U245: =IF(ISNUMBER(SEARCH("ADD-ON",$I245)),"ADD-ON","NOT AN ADD-ON") -> NOT AN ADD-ON | V245: =CONCATENATE(R245,S245,T245,U245) -> LIFE SCIENCESLIFE SCIENCESAUTHORIZEDNOT AN ADD-ON
A246: Enterprise Asset Management | B246: MAXIMO | C246: MXI LIFESCI | D246: 5724U23 | E246: IBM Maximo for Life Sciences | F246: Maximo for Life Science | G246: 142 | H246: E0AVPLL | I246: IBM MAXIMO FOR LIFE SCIENCES FOR LINUX ON SYSTEM Z ADD ON AUTHORIZED USER ANNUAL SW SUBSCRIPTION & SUPPORT RENEWAL | J246: D0H0MLL | K246: Authorized User | L246: 0 | M246: =ROUND(IF(K246="Authorized User",L246/3,L246),2) -> 0 | N246: 5 | O246: 1.6666667 | P246: 712 | Q246: Renewal | R246: LIFE SCIENCES | S246: LIFE SCIENCES | T246: AUTHORIZED | U246: ADD-ON | V246: =CONCATENATE(R246,S246,T246,U246) -> LIFE SCIENCESLIFE SCIENCESAUTHORIZEDADD-ON
A247: Enterprise Asset Management | B247: MAXIMO | C247: MXI LIFESCI | D247: 5724U23 | E247: IBM Maximo for Life Sciences | F247: Maximo for Life Science | G247: 712 | H247: D0H0MLL | I247: IBM MAXIMO FOR LIFE SCIENCES FOR LINUX ON SYSTEM Z ADD ON AUTHORIZED USER LICENSE + SW SUBSCRIPTION & SUPPORT 12 MONTHS | J247: D0H0MLL | K247: Authorized User | L247: 0 | M247: =ROUND(IF(K247="Authorized User",L247/3,L247),2) -> 0 | N247: 5 | O247: 1.6666667 | P247: 712 | Q247: License + S&S | R247: LIFE SCIENCES | S247: LIFE SCIENCES | T247: AUTHORIZED | U247: ADD-ON | V247: =CONCATENATE(R247,S247,T247,U247) -> LIFE SCIENCESLIFE SCIENCESAUTHORIZEDADD-ON
A248: Enterprise Asset Management | B248: MAXIMO | C248: MXI LIFESCI | D248: 5724U23 | E248: IBM Maximo for Life Sciences | F248: Maximo for Life Science | G248: 427 | H248: D0H0NLL | I248: IBM MAXIMO FOR LIFE SCIENCES FOR LINUX ON SYSTEM Z ADD ON AUTHORIZED USER SW SUBSCRIPTION & SUPPORT REINSTATEMENT 12 MONTHS | J248: D0H0MLL | K248: Authorized User | L248: 0 | M248: =ROUND(IF(K248="Authorized User",L248/3,L248),2) -> 0 | N248: 5 | O248: 1.6666667 | P248: 712 | Q248: Reinstatement | R248: LIFE SCIENCES | S248: LIFE SCIENCES | T248: AUTHORIZED | U248: ADD-ON | V248: =CONCATENATE(R248,S248,T248,U248) -> LIFE SCIENCESLIFE SCIENCESAUTHORIZEDADD-ON
A249: Enterprise Asset Management | B249: MAXIMO | C249: MXI LIFESCI | D249: 5724U23 | E249: IBM Maximo for Life Sciences | F249: Maximo for Life Science | G249: 1920 | H249: D0H0KLL | I249: IBM MAXIMO FOR LIFE SCIENCES FOR LINUX ON SYSTEM Z AUTHORIZED USER FROM MAXIMO ASSET MANAGEMENT LINUX ON SYSTEM Z AUTHORIZED USER TRADE UP LICENSE + SW SUBSCRIPTION & SUPPORT 12 MONTHS | J249: D0H0MLL | K249: Authorized User | L249: 10 | M249: =ROUND(IF(K249="Authorized User",L249/3,L249),2) -> 3.33 | N249: 5 | O249: 1.6666667 | P249: 712 | Q249: Trade-Up | R249: LIFE SCIENCES | S249: LIFE SCIENCES | T249: AUTHORIZED | U249: =IF(ISNUMBER(SEARCH("ADD-ON",$I249)),"ADD-ON","NOT AN ADD-ON") -> NOT AN ADD-ON | V249: =CONCATENATE(R249,S249,T249,U249) -> LIFE SCIENCESLIFE SCIENCESAUTHORIZEDNOT AN ADD-ON
A250: Enterprise Asset Management | B250: MAXIMO | C250: MXI LIFESCI | D250: 5724U23 | E250: IBM Maximo for Life Sciences | F250: Maximo for Life Science | G250: 4710 | H250: D0H0LLL | I250: IBM MAXIMO FOR LIFE SCIENCES FOR LINUX ON SYSTEM Z AUTHORIZED USER FROM MAXIMO ASSET MANAGEMENT LINUX ON SYSTEM Z LIMITED USE AUTHORIZED USER TRADE UP LICENSE + SW SUBSCRIPTION & SUPPORT 12 MONTHS | J250: D0H0MLL | K250: Authorized User | L250: 10 | M250: =ROUND(IF(K250="Authorized User",L250/3,L250),2) -> 3.33 | N250: 5 | O250: 1.6666667 | P250: 712 | Q250: Trade-Up | R250: LIFE SCIENCES | S250: LIFE SCIENCES | T250: AUTHORIZED | U250: =IF(ISNUMBER(SEARCH("ADD-ON",$I250)),"ADD-ON","NOT AN ADD-ON") -> NOT AN ADD-ON | V250: =CONCATENATE(R250,S250,T250,U250) -> LIFE SCIENCESLIFE SCIENCESAUTHORIZEDNOT AN ADD-ON
A251: Enterprise Asset Management | B251: MAXIMO | C251: MXI LIFESCI | D251: 5724U23 | E251: IBM Maximo for Life Sciences | F251: Maximo for Life Science | G251: 4470 | H251: D0T13LL | I251: IBM MAXIMO FOR LIFE SCIENCES FOR LINUX ON SYSTEM Z AUTHORIZED USER FROM MAXIMO FOR LIFE SCIENCES LIMITED USE FOR LINUX ON SYSTEM Z AUTHORIZED USER TRADE UP LICENCE + SW SUBSCRIPTION & SUPPORT 12 MONTHS | J251: D0H0MLL | K251: Authorized User | L251: 10 | M251: =ROUND(IF(K251="Authorized User",L251/3,L251),2) -> 3.33 | N251: 5 | O251: 1.6666667 | P251: 712 | Q251: Trade-Up | R251: LIFE SCIENCES | S251: LIFE SCIENCES | T251: AUTHORIZED | U251: =IF(ISNUMBER(SEARCH("ADD-ON",$I251)),"ADD-ON","NOT AN ADD-ON") -> NOT AN ADD-ON | V251: =CONCATENATE(R251,S251,T251,U251) -> LIFE SCIENCESLIFE SCIENCESAUTHORIZEDNOT AN ADD-ON
A252: Enterprise Asset Management | B252: MAXIMO | C252: MXI LIFESCI | D252: 5724U23 | E252: IBM Maximo for Life Sciences | F252: Maximo for Life Science | G252: 1400 | H252: E0AVNLL | I252: IBM MAXIMO FOR LIFE SCIENCES FOR LINUX ON SYSTEM Z AUTHORIZED USER ANNUAL SW SUBSCRIPTION & SUPPORT RENEWAL | J252: D0H0ILL | K252: Authorized User | L252: 10 | M252: =ROUND(IF(K252="Authorized User",L252/3,L252),2) -> 3.33 | N252: 5 | O252: 1.6666667 | P252: 6980 | Q252: Renewal | R252: LIFE SCIENCES | S252: LIFE SCIENCES | T252: AUTHORIZED | U252: =IF(ISNUMBER(SEARCH("ADD-ON",$I252)),"ADD-ON","NOT AN ADD-ON") -> NOT AN ADD-ON | V252: =CONCATENATE(R252,S252,T252,U252) -> LIFE SCIENCESLIFE SCIENCESAUTHORIZEDNOT AN ADD-ON
A253: Enterprise Asset Management | B253: MAXIMO | C253: MXI LIFESCI | D253: 5724U23 | E253: IBM Maximo for Life Sciences | F253: Maximo for Life Science | G253: 6980 | H253: D0H0ILL | I253: IBM MAXIMO FOR LIFE SCIENCES FOR LINUX ON SYSTEM Z AUTHORIZED USER LICENSE + SW SUBSCRIPTION & SUPPORT 12 MONTHS | J253: D0H0ILL | K253: Authorized User | L253: 10 | M253: =ROUND(IF(K253="Authorized User",L253/3,L253),2) -> 3.33 | N253: 5 | O253: 1.6666667 | P253: 6980 | Q253: License + S&S | R253: LIFE SCIENCES | S253: LIFE SCIENCES | T253: AUTHORIZED | U253: =IF(ISNUMBER(SEARCH("ADD-ON",$I253)),"ADD-ON","NOT AN ADD-ON") -> NOT AN ADD-ON | V253: =CONCATENATE(R253,S253,T253,U253) -> LIFE SCIENCESLIFE SCIENCESAUTHORIZEDNOT AN ADD-ON
A254: Enterprise Asset Management | B254: MAXIMO | C254: MXI LIFESCI | D254: 5724U23 | E254: IBM Maximo for Life Sciences | F254: Maximo for Life Science | G254: 4180 | H254: D0H0JLL | I254: IBM MAXIMO FOR LIFE SCIENCES FOR LINUX ON SYSTEM Z AUTHORIZED USER SW SUBSCRIPTION & SUPPORT REINSTATEMENT 12 MONTHS | J254: D0H0ILL | K254: Authorized User | L254: 10 | M254: =ROUND(IF(K254="Authorized User",L254/3,L254),2) -> 3.33 | N254: 5 | O254: 1.6666667 | P254: 6980 | Q254: Reinstatement | R254: LIFE SCIENCES | S254: LIFE SCIENCES | T254: AUTHORIZED | U254: =IF(ISNUMBER(SEARCH("ADD-ON",$I254)),"ADD-ON","NOT AN ADD-ON") -> NOT AN ADD-ON | V254: =CONCATENATE(R254,S254,T254,U254) -> LIFE SCIENCESLIFE SCIENCESAUTHORIZEDNOT AN ADD-ON
A255: Enterprise Asset Management | B255: MAXIMO | C255: MXI LIFESCI | D255: 5724U23 | E255: IBM Maximo for Life Sciences | F255: Maximo for Life Science | G255: 953 | H255: D0T07LL | I255: IBM MAXIMO FOR LIFE SCIENCES LIMITED USE AUTHORIZED USER FROM MAXIMO ASSET MANAGEMENT LIMITED USE AUTHORIZED USER TRADE UP LICENCE + SW SUBSCRIPTION & SUPPORT 12 MONTHS | J255: D0T05LL | K255: Authorized User | L255: 5 | M255: =ROUND(IF(K255="Authorized User",L255/3,L255),2) -> 1.67 | N255: 5 | O255: 1.6666667 | P255: 3480 | Q255: Trade-Up | R255: LIFE SCIENCES | S255: LIFE SCIENCES | T255: LIMITED | U255: =IF(ISNUMBER(SEARCH("ADD-ON",$I255)),"ADD-ON","NOT AN ADD-ON") -> NOT AN ADD-ON | V255: =CONCATENATE(R255,S255,T255,U255) -> LIFE SCIENCESLIFE SCIENCESLIMITEDNOT AN ADD-ON
A256: Enterprise Asset Management | B256: MAXIMO | C256: MXI LIFESCI | D256: 5724U23 | E256: IBM Maximo for Life Sciences | F256: Maximo for Life Science | G256: 695 | H256: E0EEQLL | I256: IBM MAXIMO FOR LIFE SCIENCES LIMITED USE AUTHORIZED USER ANNUAL SW SUBSCRIPTION & SUPPORT RENEWAL | J256: D0T05LL | K256: Authorized User | L256: 5 | M256: =ROUND(IF(K256="Authorized User",L256/3,L256),2) -> 1.67 | N256: 5 | O256: 1.6666667 | P256: 3480 | Q256: Renewal | R256: LIFE SCIENCES | S256: LIFE SCIENCES | T256: LIMITED | U256: =IF(ISNUMBER(SEARCH("ADD-ON",$I256)),"ADD-ON","NOT AN ADD-ON") -> NOT AN ADD-ON | V256: =CONCATENATE(R256,S256,T256,U256) -> LIFE SCIENCESLIFE SCIENCESLIMITEDNOT AN ADD-ON
A257: Enterprise Asset Management | B257: MAXIMO | C257: MXI LIFESCI | D257: 5724U23 | E257: IBM Maximo for Life Sciences | F257: Maximo for Life Science | G257: 3480 | H257: D0T05LL | I257: IBM MAXIMO FOR LIFE SCIENCES LIMITED USE AUTHORIZED USER LICENCE + SW SUBSCRIPTION & SUPPORT 12 MONTHS | J257: D0T05LL | K257: Authorized User | L257: 5 | M257: =ROUND(IF(K257="Authorized User",L257/3,L257),2) -> 1.67 | N257: 5 | O257: 1.6666667 | P257: 3480 | Q257: License + S&S | R257: LIFE SCIENCES | S257: LIFE SCIENCES | T257: LIMITED | U257: =IF(ISNUMBER(SEARCH("ADD-ON",$I257)),"ADD-ON","NOT AN ADD-ON") -> NOT AN ADD-ON | V257: =CONCATENATE(R257,S257,T257,U257) -> LIFE SCIENCESLIFE SCIENCESLIMITEDNOT AN ADD-ON
A258: Enterprise Asset Management | B258: MAXIMO | C258: MXI LIFESCI | D258: 5724U23 | E258: IBM Maximo for Life Sciences | F258: Maximo for Life Science | G258: 2090 | H258: D0T06LL | I258: IBM MAXIMO FOR LIFE SCIENCES LIMITED USE AUTHORIZED USER SW SUBSCRIPTION & SUPPORT REINSTATEMENT 12 MONTHS | J258: D0T05LL | K258: Authorized User | L258: 5 | M258: =ROUND(IF(K258="Authorized User",L258/3,L258),2) -> 1.67 | N258: 5 | O258: 1.6666667 | P258: 3480 | Q258: Reinstatement | R258: LIFE SCIENCES | S258: LIFE SCIENCES | T258: LIMITED | U258: =IF(ISNUMBER(SEARCH("ADD-ON",$I258)),"ADD-ON","NOT AN ADD-ON") -> NOT AN ADD-ON | V258: =CONCATENATE(R258,S258,T258,U258) -> LIFE SCIENCESLIFE SCIENCESLIMITEDNOT AN ADD-ON
A259: Enterprise Asset Management | B259: MAXIMO | C259: MXI LIFESCI | D259: 5724U23 | E259: IBM Maximo for Life Sciences | F259: Maximo for Life Science | G259: 953 | H259: D0T0GLL | I259: IBM MAXIMO FOR LIFE SCIENCES LIMITED USE FOR LINUX ON SYSTEM Z AUTHORIZED USER FROM MAXIMO ASSET MANAGEMENT LIMITED USE FOR LINUX ON SYSTEM Z AUTHORIZED USER TRADE UP LICENCE + SW SUBSCRIPTION & SUPPORT 12 MONTHS | J259: D0T0ALL | K259: Authorized User | L259: 5 | M259: =ROUND(IF(K259="Authorized User",L259/3,L259),2) -> 1.67 | N259: 5 | O259: 1.6666667 | P259: 3480 | Q259: Trade-Up | R259: LIFE SCIENCES | S259: LIFE SCIENCES | T259: LIMITED | U259: =IF(ISNUMBER(SEARCH("ADD-ON",$I259)),"ADD-ON","NOT AN ADD-ON") -> NOT AN ADD-ON | V259: =CONCATENATE(R259,S259,T259,U259) -> LIFE SCIENCESLIFE SCIENCESLIMITEDNOT AN ADD-ON
A260: Enterprise Asset Management | B260: MAXIMO | C260: MXI LIFESCI | D260: 5724U23 | E260: IBM Maximo for Life Sciences | F260: Maximo for Life Science | G260: 695 | H260: E0EESLL | I260: IBM MAXIMO FOR LIFE SCIENCES LIMITED USE FOR LINUX ON SYSTEM Z AUTHORIZED USER ANNUAL SW SUBSCRIPTION & SUPPORT RENEWAL | J260: D0T0ALL | K260: Authorized User | L260: 5 | M260: =ROUND(IF(K260="Authorized User",L260/3,L260),2) -> 1.67 | N260: 5 | O260: 1.6666667 | P260: 3480 | Q260: Renewal | R260: LIFE SCIENCES | S260: LIFE SCIENCES | T260: LIMITED | U260: =IF(ISNUMBER(SEARCH("ADD-ON",$I260)),"ADD-ON","NOT AN ADD-ON") -> NOT AN ADD-ON | V260: =CONCATENATE(R260,S260,T260,U260) -> LIFE SCIENCESLIFE SCIENCESLIMITEDNOT AN ADD-ON
...

Sheet Upgrade Parts Future_K_v6.4
A2: UT_LEVEL_CODE_30_DSCR | B2: IBM_SW_PILLAR_CODE | C2: IBM_SW_FAM_CODE | D2: IBM_PROD_ID | E2: IBM_PROD_ID_DSCR | F2: WWIDE_PROD_CODE_DSCR | G2: Eligible Part List Price | H2: Eligible Part # | I2: Eligible Part Description | J2: Eligible Part Parent Lic + S&S Part # | K2: CU_DSCR | L2: AppPoint for upgrade | M2: Upgrade Price Metric Conversion | N2: MAS AppPoint (Ltd, Base, Prm) | O2: Price Metric Conversion | P2: Parent Lic + S&S Part # US List Price | Q2: Part Type | R2: Offering name | S2: Core/IS/Add-ons/Anywhere | T2: AUTHORIZED | U2: Add-on Parts
A3: Enterprise Asset Management | B3: MAXIMO | C3: MXA CONFIG | D3: 5724U28 | E3: IBM Maximo Asset Configuration Manager | F3: Maximo Asset Configuration Manager | G3: 8980 | H3: D03WULL | I3: IBM MAXIMO ASSET CONFIGURATION MANAGER ASSET LICENSE + SW SUBSCRIPTION & SUPPORT 12 MONTHS | J3: D03WULL | K3: Asset | L3: Manual Input required | M3: =ROUND(IF(K3="Authorized User",L3/3,L3),2) -> #VALUE! | N3: 15 | O3: 5 | P3: 8980 | Q3: License + S&S | R3: ASSET CONFIGURATION MANAGER | S3: ACM | T3: ASSET | U3: =IF(ISNUMBER(SEARCH("ADD-ON",$I3)),"ADD-ON","NOT AN ADD-ON") -> NOT AN ADD-ON | V3: =CONCATENATE(R3,S3,T3,U3) -> ASSET CONFIGURATION MANAGERACMASSETNOT AN ADD-ON
A4: Enterprise Asset Management | B4: MAXIMO | C4: MXA CONFIG | D4: 5724U28 | E4: IBM Maximo Asset Configuration Manager | F4: Maximo Asset Configuration Manager | G4: 5390 | H4: D03WVLL | I4: IBM MAXIMO ASSET CONFIGURATION MANAGER ASSET SW SUBSCRIPTION & SUPPORT REINSTATEMENT 12 MONTHS | J4: D03WULL | K4: Asset | L4: Manual Input required | M4: =ROUND(IF(K4="Authorized User",L4/3,L4),2) -> #VALUE! | N4: 15 | O4: 5 | P4: 8980 | Q4: Reinstatement | R4: ASSET CONFIGURATION MANAGER | S4: ACM | T4: ASSET | U4: =IF(ISNUMBER(SEARCH("ADD-ON",$I4)),"ADD-ON","NOT AN ADD-ON") -> NOT AN ADD-ON | V4: =CONCATENATE(R4,S4,T4,U4) -> ASSET CONFIGURATION MANAGERACMASSETNOT AN ADD-ON
A5: Enterprise Asset Management | B5: MAXIMO | C5: MXA CONFIG | D5: 5724U28 | E5: IBM Maximo Asset Configuration Manager | F5: Maximo Asset Configuration Manager | G5: 5740 | H5: D03WYLL | I5: IBM MAXIMO ASSET CONFIGURATION MANAGER AUTHORIZED USER LICENSE + SW SUBSCRIPTION & SUPPORT 12 MONTHS | J5: D03WYLL | K5: Authorized User | L5: 2 | M5: 1 | N5: 2 | O5: 1 | P5: 5740 | Q5: License + S&S | R5: ASSET CONFIGURATION MANAGER | S5: ACM | T5: AUTHORIZED | U5: =IF(ISNUMBER(SEARCH("ADD-ON",$I5)),"ADD-ON","NOT AN ADD-ON") -> NOT AN ADD-ON | V5: =CONCATENATE(R5,S5,T5,U5) -> ASSET CONFIGURATION MANAGERACMAUTHORIZEDNOT AN ADD-ON
A6: Enterprise Asset Management | B6: MAXIMO | C6: MXA CONFIG | D6: 5724U28 | E6: IBM Maximo Asset Configuration Manager | F6: Maximo Asset Configuration Manager | G6: 3440 | H6: D03WZLL | I6: IBM MAXIMO ASSET CONFIGURATION MANAGER AUTHORIZED USER SW SUBSCRIPTION & SUPPORT REINSTATEMENT 12 MONTHS | J6: D03WYLL | K6: Authorized User | L6: 2 | M6: 1 | N6: 2 | O6: 1 | P6: 5740 | Q6: Reinstatement | R6: ASSET CONFIGURATION MANAGER | S6: ACM | T6: AUTHORIZED | U6: =IF(ISNUMBER(SEARCH("ADD-ON",$I6)),"ADD-ON","NOT AN ADD-ON") -> NOT AN ADD-ON | V6: =CONCATENATE(R6,S6,T6,U6) -> ASSET CONFIGURATION MANAGERACMAUTHORIZEDNOT AN ADD-ON
A7: Enterprise Asset Management | B7: MAXIMO | C7: MXA CALIBRAT | D7: 5724U33 | E7: IBM Maximo Calibration | F7: Maximo Calibration | G7: 584 | H7: D03X4LL | I7: IBM MAXIMO CALIBRATION AUTHORIZED USER LICENSE + SW SUBSCRIPTION & SUPPORT 12 MONTHS | J7: D03X4LL | K7: Authorized User | L7: 0 | M7: =ROUND(IF(K7="Authorized User",L7/3,L7),2) -> 0 | N7: 5 | O7: 1.6666667 | P7: 584 | Q7: License + S&S | R7: CALIBRATION | S7: ADD-ON | T7: AUTHORIZED | U7: =IF(ISNUMBER(SEARCH("ADD-ON",$I7)),"ADD-ON","NOT AN ADD-ON") -> NOT AN ADD-ON | V7: =CONCATENATE(R7,S7,T7,U7) -> CALIBRATIONADD-ONAUTHORIZEDNOT AN ADD-ON
A8: Enterprise Asset Management | B8: MAXIMO | C8: MXA CALIBRAT | D8: 5724U33 | E8: IBM Maximo Calibration | F8: Maximo Calibration | G8: 350 | H8: D03X5LL | I8: IBM MAXIMO CALIBRATION AUTHORIZED USER SW SUBSCRIPTION & SUPPORT REINSTATEMENT 12 MONTHS | J8: D03X4LL | K8: Authorized User | L8: 0 | M8: =ROUND(IF(K8="Authorized User",L8/3,L8),2) -> 0 | N8: 5 | O8: 1.6666667 | P8: 584 | Q8: Reinstatement | R8: CALIBRATION | S8: ADD-ON | T8: AUTHORIZED | U8: =IF(ISNUMBER(SEARCH("ADD-ON",$I8)),"ADD-ON","NOT AN ADD-ON") -> NOT AN ADD-ON | V8: =CONCATENATE(R8,S8,T8,U8) -> CALIBRATIONADD-ONAUTHORIZEDNOT AN ADD-ON
A9: Enterprise Asset Management | B9: MAXIMO | C9: MXA LINEAR | D9: 5724U18 | E9: IBM Maximo Asset Management | F9: Maximo Asset Management | G9: 712 | H9: D040SLL | I9: IBM MAXIMO LINEAR ASSET MANAGER AUTHORIZED USER LICENSE + SW SUBSCRIPTION & SUPPORT 12 MONTHS | J9: D040SLL | K9: Authorized User | L9: 0 | M9: =ROUND(IF(K9="Authorized User",L9/3,L9),2) -> 0 | N9: 5 | O9: 1.6666667 | P9: 712 | Q9: License + S&S | R9: LINEAR | S9: ADD-ON | T9: AUTHORIZED | U9: =IF(ISNUMBER(SEARCH("ADD-ON",$I9)),"ADD-ON","NOT AN ADD-ON") -> NOT AN ADD-ON | V9: =CONCATENATE(R9,S9,T9,U9) -> LINEARADD-ONAUTHORIZEDNOT AN ADD-ON
A10: Enterprise Asset Management | B10: MAXIMO | C10: MXA LINEAR | D10: 5724U18 | E10: IBM Maximo Asset Management | F10: Maximo Asset Management | G10: 427 | H10: D040TLL | I10: IBM MAXIMO LINEAR ASSET MANAGER AUTHORIZED USER SW SUBSCRIPTION & SUPPORT REINSTATEMENT 12 MONTHS | J10: D040SLL | K10: Authorized User | L10: 0 | M10: =ROUND(IF(K10="Authorized User",L10/3,L10),2) -> 0 | N10: 5 | O10: 1.6666667 | P10: 712 | Q10: Reinstatement | R10: LINEAR | S10: ADD-ON | T10: AUTHORIZED | U10: =IF(ISNUMBER(SEARCH("ADD-ON",$I10)),"ADD-ON","NOT AN ADD-ON") -> NOT AN ADD-ON | V10: =CONCATENATE(R10,S10,T10,U10) -> LINEARADD-ONAUTHORIZEDNOT AN ADD-ON
A11: Enterprise Asset Management | B11: MAXIMO | C11: MX ENT ADP | D11: 5724T00 | E11: IBM Maximo Enterprise Adapter | F11: Maximo Enterprise Adapter | G11: 161000 | H11: D04QDLL | I11: IBM MAXIMO ENTERPRISE ADAPTER FOR SAP APPLICATIONS SERVER LICENSE + SW SUBSCRIPTION & SUPPORT 12 MONTHS | J11: D04QDLL | K11: Server | L11: 80 | M11: =ROUND(IF(K11="Authorized User",L11/3,L11),2) -> 80 | N11: 80 | O11: 1 | P11: 161000 | Q11: License + S&S | R11: ADAPTER FOR SAP | S11: ADAPTER | T11: ADAPTER | U11: =IF(ISNUMBER(SEARCH("ADD-ON",$I11)),"ADD-ON","NOT AN ADD-ON") -> NOT AN ADD-ON | V11: =CONCATENATE(R11,S11,T11,U11) -> ADAPTER FOR SAPADAPTERADAPTERNOT AN ADD-ON
A12: Enterprise Asset Management | B12: MAXIMO | C12: MX ENT ADP | D12: 5724T00 | E12: IBM Maximo Enterprise Adapter | F12: Maximo Enterprise Adapter | G12: 96300 | H12: D04QELL | I12: IBM MAXIMO ENTERPRISE ADAPTER FOR SAP APPLICATIONS SERVER SW SUBSCRIPTION & SUPPORT REINSTATEMENT 12 MONTHS | J12: D04QDLL | K12: Server | L12: 80 | M12: =ROUND(IF(K12="Authorized User",L12/3,L12),2) -> 80 | N12: 80 | O12: 1 | P12: 161000 | Q12: Reinstatement | R12: ADAPTER FOR SAP | S12: ADAPTER | T12: ADAPTER | U12: =IF(ISNUMBER(SEARCH("ADD-ON",$I12)),"ADD-ON","NOT AN ADD-ON") -> NOT AN ADD-ON | V12: =CONCATENATE(R12,S12,T12,U12) -> ADAPTER FOR SAPADAPTERADAPTERNOT AN ADD-ON
A13: Enterprise Asset Management | B13: MAXIMO | C13: MXS EAM | D13: 5724U18 | E13: IBM Maximo Asset Management | F13: Maximo Asset Management | G13: 1780 | H13: D04XSLL | I13: IBM MAXIMO ASSET MANAGEMENT MANAGED SERVICE PROVIDERS LIMITED USE AUTHORIZED USER LICENSE + SW SUBSCRIPTION & SUPPORT 12 MONTHS | J13: D04XSLL | K13: Authorized User | L13: 0 | M13: =ROUND(IF(K13="Authorized User",L13/3,L13),2) -> 0 | N13: 5 | O13: 1.6666667 | P13: 1780 | Q13: License + S&S | R13: MANAGED SERVICE PROVIDERS | S13: MSP | T13: LIMITED | U13: =IF(ISNUMBER(SEARCH("ADD-ON",$I13)),"ADD-ON","NOT AN ADD-ON") -> NOT AN ADD-ON | V13: =CONCATENATE(R13,S13,T13,U13) -> MANAGED SERVICE PROVIDERSMSPLIMITEDNOT AN ADD-ON
A14: Enterprise Asset Management | B14: MAXIMO | C14: MXS EAM | D14: 5724U18 | E14: IBM Maximo Asset Management | F14: Maximo Asset Management | G14: 1070 | H14: D04XTLL | I14: IBM MAXIMO ASSET MANAGEMENT MANAGED SERVICE PROVIDERS LIMITED USE AUTHORIZED USER SW SUBSCRIPTION & SUPPORT REINSTATEMENT 12 MONTHS | J14: D04XSLL | K14: Authorized User | L14: 0 | M14: =ROUND(IF(K14="Authorized User",L14/3,L14),2) -> 0 | N14: 2 | O14: 1.6666667 | P14: 1780 | Q14: Reinstatement | R14: MANAGED SERVICE PROVIDERS | S14: MSP | T14: LIMITED | U14: =IF(ISNUMBER(SEARCH("ADD-ON",$I14)),"ADD-ON","NOT AN ADD-ON") -> NOT AN ADD-ON | V14: =CONCATENATE(R14,S14,T14,U14) -> MANAGED SERVICE PROVIDERSMSPLIMITEDNOT AN ADD-ON
A15: Enterprise Asset Management | B15: MAXIMO | C15: MXS EAM | D15: 5724U18 | E15: IBM Maximo Asset Management | F15: Maximo Asset Management | G15: 3570 | H15: D04XWLL | I15: IBM MAXIMO ASSET MANAGEMENT MANAGED SERVICE PROVIDERS AUTHORIZED USER LICENSE + SW SUBSCRIPTION & SUPPORT 12 MONTHS | J15: D04XWLL | K15: Authorized User | L15: 2 | M15: 1 | N15: 2 | O15: 1 | P15: 3570 | Q15: License + S&S | R15: MANAGED SERVICE PROVIDERS | S15: MSP | T15: AUTHORIZED | U15: =IF(ISNUMBER(SEARCH("ADD-ON",$I15)),"ADD-ON","NOT AN ADD-ON") -> NOT AN ADD-ON | V15: =CONCATENATE(R15,S15,T15,U15) -> MANAGED SERVICE PROVIDERSMSPAUTHORIZEDNOT AN ADD-ON
A16: Enterprise Asset Management | B16: MAXIMO | C16: MXS EAM | D16: 5724U18 | E16: IBM Maximo Asset Management | F16: Maximo Asset Management | G16: 2140 | H16: D04XXLL | I16: IBM MAXIMO ASSET MANAGEMENT MANAGED SERVICE PROVIDERS AUTHORIZED USER SW SUBSCRIPTION & SUPPORT REINSTATEMENT 12 MONTHS | J16: D04XWLL | K16: Authorized User | L16: 2 | M16: 1 | N16: 2 | O16: 1 | P16: 3570 | Q16: Reinstatement | R16: MANAGED SERVICE PROVIDERS | S16: MSP | T16: AUTHORIZED | U16: =IF(ISNUMBER(SEARCH("ADD-ON",$I16)),"ADD-ON","NOT AN ADD-ON") -> NOT AN ADD-ON | V16: =CONCATENATE(R16,S16,T16,U16) -> MANAGED SERVICE PROVIDERSMSPAUTHORIZEDNOT AN ADD-ON
A17: Enterprise Asset Management | B17: MAXIMO | C17: MXS INTERNAL | D17: 5724U18 | E17: IBM Maximo Asset Management | F17: Maximo Asset Management | G17: 1070 | H17: D04Y0LL | I17: IBM MAXIMO ASSET MANAGEMENT INTERNAL SERVICE PROVIDERS AUTHORIZED USER LICENSE + SW SUBSCRIPTION & SUPPORT 12 MONTHS | J17: D04Y0LL | K17: Authorized User | L17: 2 | M17: 1 | N17: 2 | O17: 1 | P17: 1070 | Q17: License + S&S | R17: INTERNAL SERVICE PROVIDERS | S17: ADD-ON | T17: AUTHORIZED | U17: =IF(ISNUMBER(SEARCH("ADD-ON",$I17)),"ADD-ON","NOT AN ADD-ON") -> NOT AN ADD-ON | V17: =CONCATENATE(R17,S17,T17,U17) -> INTERNAL SERVICE PROVIDERSADD-ONAUTHORIZEDNOT AN ADD-ON
A18: Enterprise Asset Management | B18: MAXIMO | C18: MXS INTERNAL | D18: 5724U18 | E18: IBM Maximo Asset Management | F18: Maximo Asset Management | G18: 643 | H18: D04Y1LL | I18: IBM MAXIMO ASSET MANAGEMENT INTERNAL SERVICE PROVIDERS AUTHORIZED USER SW SUBSCRIPTION & SUPPORT REINSTATEMENT 12 MONTHS | J18: D04Y0LL | K18: Authorized User | L18: 2 | M18: 1 | N18: 2 | O18: 1 | P18: 1070 | Q18: Reinstatement | R18: INTERNAL SERVICE PROVIDERS | S18: ADD-ON | T18: AUTHORIZED | U18: =IF(ISNUMBER(SEARCH("ADD-ON",$I18)),"ADD-ON","NOT AN ADD-ON") -> NOT AN ADD-ON | V18: =CONCATENATE(R18,S18,T18,U18) -> INTERNAL SERVICE PROVIDERSADD-ONAUTHORIZEDNOT AN ADD-ON
A19: Enterprise Asset Management | B19: MAXIMO | C19: MXS EAM | D19: 5724U18 | E19: IBM Maximo Asset Management | F19: Maximo Asset Management | G19: 3570 | H19: D06FILL | I19: IBM MAXIMO ASSET MANAGEMENT MANAGED SERVICE PROVIDERS FOR LINUX ON SYSTEM Z AUTHORIZED USER LICENSE + SW SUBSCRIPTION & SUPPORT 12 MONTHS | J19: D06FILL | K19: Authorized User | L19: 2 | M19: 1 | N19: 2 | O19: 1 | P19: 3570 | Q19: License + S&S | R19: MANAGED SERVICE PROVIDERS | S19: MSP | T19: AUTHORIZED | U19: =IF(ISNUMBER(SEARCH("ADD-ON",$I19)),"ADD-ON","NOT AN ADD-ON") -> NOT AN ADD-ON | V19: =CONCATENATE(R19,S19,T19,U19) -> MANAGED SERVICE PROVIDERSMSPAUTHORIZEDNOT AN ADD-ON
A20: Enterprise Asset Management | B20: MAXIMO | C20: MXS EAM | D20: 5724U18 | E20: IBM Maximo Asset Management | F20: Maximo Asset Management | G20: 2140 | H20: D06FJLL | I20: IBM MAXIMO ASSET MANAGEMENT MANAGED SERVICE PROVIDERS FOR LINUX ON SYSTEM Z AUTHORIZED USER SW SUBSCRIPTION & SUPPORT REINSTATEMENT 12 MONTHS | J20: D06FILL | K20: Authorized User | L20: 2 | M20: 1 | N20: 2 | O20: 1 | P20: 3570 | Q20: Reinstatement | R20: MANAGED SERVICE PROVIDERS | S20: MSP | T20: AUTHORIZED | U20: =IF(ISNUMBER(SEARCH("ADD-ON",$I20)),"ADD-ON","NOT AN ADD-ON") -> NOT AN ADD-ON | V20: =CONCATENATE(R20,S20,T20,U20) -> MANAGED SERVICE PROVIDERSMSPAUTHORIZEDNOT AN ADD-ON
A21: Enterprise Asset Management | B21: MAXIMO | C21: MXA LINEAR | D21: 5724U18 | E21: IBM Maximo Asset Management | F21: Maximo Asset Management | G21: 712 | H21: D06FKLL | I21: IBM MAXIMO LINEAR ASSET MANAGER FOR LINUX ON SYSTEM Z AUTHORIZED USER LICENSE + SW SUBSCRIPTION & SUPPORT 12 MONTHS | J21: D06FKLL | K21: Authorized User | L21: 0 | M21: =ROUND(IF(K21="Authorized User",L21/3,L21),2) -> 0 | N21: 2 | O21: 1.6666667 | P21: 712 | Q21: License + S&S | R21: LINEAR | S21: ADD-ON | T21: AUTHORIZED | U21: =IF(ISNUMBER(SEARCH("ADD-ON",$I21)),"ADD-ON","NOT AN ADD-ON") -> NOT AN ADD-ON | V21: =CONCATENATE(R21,S21,T21,U21) -> LINEARADD-ONAUTHORIZEDNOT AN ADD-ON
